Workbook
Name Slicer_Channel: #N/A
Name Slicer_Country: #N/A
Name Slicer_Months__OrderDate: #N/A
Name Slicer_ProductCategory: #N/A
Name Slicer_Region: #N/A
Name Slicer_Salesperson: #N/A

Sheet Data
A1: OrderID | B1: OrderDate | C1: RequiredDate | D1: Region | E1: Country | F1: City | G1: CustomerSegment | H1: Channel | I1: Salesperson | J1: ProductCategory | K1: SKU | L1: UnitCost | M1: UnitPrice | N1: DiscountPct | O1: Quantity
A2: ORD-2024-275203 | B2: 45362 | C2: 45388 | D2: Africa | E2: Kenya | F2: Kisumu | G2: Corporate | H2: Retail | I2: C. Otieno | J2: Components | K2: CMP-8270 | L2: 279.24 | M2: 608.9 | N2: 0.112 | O2: 9
A3: ORD-2024-358795 | B3: 45588 | C3: 45587 | D3: Africa | E3: Nigeria | F3: Port Harcourt | G3: Education | H3: Online | I3: J. Njeri | J3: Printers | K3: PRN-9322 | L3: 1084.39 | M3: 759.33 | N3: 0.237 | O3: 31
A4: ORD-2023-373538 | B4: 44985 | C4: 45010 | D4: Africa | E4: Kenya | F4: Nairobi | G4: Corporate | H4: Retail | I4: I. Johnson | J4: Networking | K4: NET-9666 | L4: 1460.76 | M4: -30.66 | N4: 0.131 | O4: 12
A5: ORD-2025-168148 | B5: 45745 | C5: 45749 | D5: Africa | E5: Nigeria | F5: Lagos | G5: Non-Profit | H5: Marketplace | I5: G. Dubois | J5: Phones | K5: PHN-4556 | L5: 259.93 | M5: 255.94 | N5: 0.072 | O5: 22
A6: ORD-2023-824839 | B6: 45266 | C6: 45291 | D6: Asia | E6: Japan | F6: Osaka | G6: Consumer | H6: Retail | I6: L. Okafor | J6: Printers | K6: PRN-8041 | L6: 663.03 | M6: 813.51 | N6: 0.102 | O6: 15
A7: ORD-2023-723587 | B7: 44928 | C7: 44931 | D7: Americas | E7: Canada | F7: Toronto | G7: Corporate | H7: Distributor | I7: B. Chen | J7: Laptops | K7: LAP-8555 | L7: 315.87 | M7: 591.68 | N7: 0 | O7: 7
A8: ORD-2024-336584 | B8: 45653 | C8: 45671 | D8: Asia | E8: India | F8: Bengaluru | G8: Small Business | H8: Marketplace | I8: E. Garcia | J8: Monitors | K8: MON-8629 | L8: 586.07 | M8: 845.97 | N8: 0.147 | O8: 4
A9: ORD-2023-112666 | B9: 44941 | C9: 44939 | D9: Africa | E9: Nigeria | F9: Abuja | G9: Education | H9: Online | I9: O. Wang | J9: Printers | K9: PRN-6276 | L9: 28.38 | M9: 47.22 | N9: 0.194 | O9: 18
A10: ORD-2024-589570 | B10: 45416 | C10: 45441 | D10: Africa | E10: Nigeria | F10: Abuja | G10: Non-Profit | H10: Marketplace | I10: O. Wang | J10: Monitors | K10: MON-6892 | L10: 1295.34 | M10: 2530.81 | N10: 0.031 | O10: 6
A11: ORD-2025-997421 | B11: 45798 | C11: 45817 | D11: Americas | E11: Brazil | F11: São Paulo | G11: Non-Profit | H11: Online | I11: A. Patel | J11: Components | K11: CMP-3731 | L11: 1331.38 | M11: 2309.56 | N11: 0.149 | O11: 31
A12: ORD-2024-210687 | B12: 45319 | C12: 45331 | D12: Europe | E12: Germany | F12: Berlin | G12: Corporate | H12: Online | I12: G. Dubois | J12: Accessories | K12: ACC-7938 | L12: 644.17 | M12: 700.12 | N12: 0.006 | O12: 23
A13: ORD-2025-515515 | B13: 45660 | C13: 45680 | D13: Asia | E13: Japan | F13: Osaka | G13: Corporate | H13: Distributor | I13: F. Müller | J13: Phones | K13: PHN-7019 | L13: 908.6 | M13: 691.37 | N13: 0.25 | O13: 20
... A34: ORD-2025-474710 | B34: 45862 | C34: 45875 | D34: Africa | E34: South Africa | F34: Johannesburg | G34: Education | H34: Marketplace | I34: D. Smith | J34: Networking | K34: NET-7966 | L34: 1463.9 | M34: 2633.02 | N34: 0.084 | O34: 4
A35: ORD-2024-629525 | B35: 45400 | C35: 45420 | D35: Europe | E35: United Kingdom | F35: London | G35: Non-Profit | I35: D. Smith | J35: Laptops | K35: LAP-9932 | L35: 645.33 | M35: 1321.85 | N35: 0 | O35: 10
A36: ORD-2024-167215 | B36: 45527 | C36: 45525 | D36: Africa | E36: South Africa | F36: Johannesburg | G36: Education | H36: Retail | I36: E. Garcia | J36: Components | K36: CMP-1559 | L36: 1432.52 | M36: 3036.87 | N36: 0 | O36: 9
A37: ORD-2023-864121 | B37: 45012 | C37: 45038 | D37: Asia | E37: India | F37: Delhi | G37: Non-Profit | H37: Marketplace | I37: J. Njeri | J37: Printers | K37: PRN-4506 | L37: 178.53 | M37: 199.37 | N37: 0.101 | O37: 37
A38: ORD-2024-692673 | B38: 45358 | C38: 45376 | D38: Europe | E38: Germany | F38: Munich | G38: Corporate | H38: Online | I38: B. Chen | J38: Components | K38: CMP-7617 | L38: 712.84 | M38: 927.51 | N38: 0.243 | O38: 27
A39: ORD-2025-718992 | B39: 45832 | C39: 45848 | D39: Asia | E39: China | F39: Shanghai | G39: Enterprise | H39: Direct | I39: N. Brown | J39: Components | K39: CMP-8390 | L39: 757.19 | M39: 1735.41 | N39: 0.136 | O39: 8
A40: ORD-2024-599522 | B40: 45401 | C40: 45418 | D40: Africa | E40: Nigeria | F40: Port Harcourt | G40: Non-Profit | H40: Online | I40: A. Patel | J40: Printers | K40: PRN-7303 | L40: 865.33 | M40: 1395.64 | N40: 0.175 | O40: 13
A41: ORD-2023-651638 | B41: 45094 | C41: 45101 | D41: Americas | E41: USA | F41: San Francisco | G41: Corporate | H41: Retail | I41: I. Johnson | J41: Printers | K41: PRN-6536 | L41: 313.99 | M41: 454.42 | N41: 0.129 | O41: 9
A42: ORD-2024-635626 | B42: 45531 | C42: 45554 | D42: Europe | E42: Germany | F42: Berlin | G42: Small Business | H42: Direct | I42: D. Smith | J42: Monitors | K42: MON-9967 | L42: 1024.01 | M42: 1580.97 | N42: 0.037 | O42: 27
A43: ORD-2024-296582 | B43: 45302 | C43: 45324 | D43: Africa | E43: South Africa | F43: Durban | G43: Consumer | H43: Online | I43: K. Singh | J43: Networking | K43: NET-1412 | L43: 1206.2 | M43: 1759.79 | N43: 0 | O43: 6
A44: ORD-2024-998320 | B44: 45590 | C44: 45610 | D44: Africa | E44: Kenya | F44: Mombasa | G44: Corporate | H44: Direct | I44: H. Kim | J44: Printers | K44: PRN-3143 | L44: 1396.48 | M44: 3204.5 | N44: 0.318 | O44: 14
A45: ORD-2025-820255 | B45: 45806 | C45: 45828 | D45: Europe | E45: Germany | F45: Berlin | G45: Corporate | H45: Direct | I45: A. Patel | J45: Printers | K45: PRN-9787 | L45: 483.47 | M45: 1135.43 | N45: 0.146 | O45: 11
A46: ORD-2024-389336 | B46: 45432 | C46: 45445 | D46: Americas | E46: Canada | F46: Vancouver | G46: Enterprise | H46: Marketplace | I46: K. Singh | J46: Components | K46: CMP-5946 | L46: 675.43 | M46: 996.36 | N46: 0.182 | O46: 22
A47: ORD-2023-308124 | B47: 45035 | C47: 45046 | D47: Asia | E47: India | F47: Delhi | G47: Small Business | H47: Retail | I47: A. Patel | J47: Networking | K47: NET-2062 | L47: 826.55 | M47: 1397.05 | N47: 0.169 | O47: 28
... A77: ORD-2023-722117 | B77: 45187 | C77: 45207 | D77: Asia | E77: India | F77: Delhi | G77: Small Business | H77: Direct | I77: B. Chen | J77: Components | K77: CMP-1009 | L77: 825.64 | M77: 1108.43 | N77: 0.114 | O77: 7
A78: ORD-2024-446699 | B78: 45532 | C78: 45560 | D78: Americas | E78: Brazil | F78: Rio de Janeiro | G78: Non-Profit | H78: Online | J78: Accessories | K78: ACC-4490 | L78: 1394.65 | M78: 3144.1 | N78: 0.134 | O78: 13
A79: ORD-2024-451005 | B79: 45473 | C79: 45471 | D79: Americas | E79: Brazil | F79: Rio de Janeiro | G79: Small Business | H79: Direct | I79: L. Okafor | J79: Accessories | K79: ACC-9162 | L79: 1112.98 | M79: 2095.73 | N79: 0.072 | O79: 17
A80: ORD-2023-290279 | B80: 45091 | C80: 45093 | D80: Europe | E80: United Kingdom | F80: Manchester | G80: Non-Profit | H80: Direct | I80: K. Singh | J80: Components | K80: CMP-5820 | L80: 357.36 | M80: 703.62 | N80: 0.257 | O80: 20
A81: ORD-2024-192263 | B81: 45617 | C81: 45647 | D81: Europe | E81: France | F81: Marseille | G81: Small Business | H81: Direct | I81: I. Johnson | J81: Monitors | K81: MON-7943 | L81: 1122.68 | M81: 1997.19 | N81: 0.186 | O81: 3
A82: ORD-2023-159379 | B82: 44965 | C82: 44968 | D82: Africa | E82: South Africa | F82: Cape Town | G82: Corporate | H82: Direct | I82: M. Rossi | J82: Networking | K82: NET-5018 | L82: 1410.05 | M82: 2763.95 | N82: 0.161 | O82: 26
A83: ORD-2023-343322 | B83: 45157 | C83: 45181 | D83: Americas | E83: Canada | F83: Vancouver | G83: Enterprise | H83: Retail | I83: I. Johnson | J83: Printers | K83: PRN-9669 | L83: 1183.95 | M83: 1503.53 | N83: 0.241 | O83: 16
A84: ORD-2025-114382 | B84: 45791 | C84: 45801 | D84: Europe | E84: France | F84: Paris | G84: Small Business | H84: Marketplace | I84: K. Singh | J84: Components | K84: CMP-2865 | L84: 170.39 | M84: 388.04 | N84: 0.084 | O84: 15
A85: ORD-2025-488349 | B85: 45770 | C85: 45769 | D85: Americas | E85: USA | F85: San Francisco | G85: Non-Profit | H85: Distributor | I85: D. Smith | J85: Monitors | K85: MON-3371 | L85: 23.24 | M85: 44.57 | N85: 0.215 | O85: 15
A86: ORD-2025-330203 | B86: 45741 | C86: 45764 | D86: Europe | E86: United Kingdom | F86: London | G86: Consumer | H86: Retail | I86: H. Kim | J86: Networking | K86: NET-7166 | L86: 1421.19 | M86: 1808.26 | N86: 0.104 | O86: 13
A87: ORD-2023-841426 | B87: 45282 | C87: 45283 | D87: Africa | E87: South Africa | F87: Cape Town | G87: Non-Profit | H87: Marketplace | I87: D. Smith | J87: Components | K87: CMP-4531 | L87: 1186.18 | M87: 1285.09 | N87: 0.07 | O87: 11
A88: ORD-2024-594592 | B88: 45388 | C88: 45407 | D88: Asia | E88: China | F88: Shanghai | G88: Corporate | H88: Retail | I88: K. Singh | J88: Components | K88: CMP-8196 | L88: 1366.48 | M88: 1678.14 | N88: 0.154 | O88: 10
A89: ORD-2025-863978 | B89: 45876 | C89: 45888 | D89: Africa | E89: Kenya | F89: Nakuru | G89: Corporate | I89: M. Rossi | J89: Components | K89: CMP-2854 | L89: 601.51 | M89: 679.35 | N89: 0.188 | O89: 3
A90: ORD-2024-604471 | B90: 45312 | C90: 45316 | D90: Asia | E90: India | F90: Delhi | G90: Consumer | H90: Direct | I90: C. Otieno | J90: Monitors | K90: MON-8973 | L90: 523.7 | M90: 1109.92 | N90: 0.03 | O90: 11
A91: ORD-2023-258768 | B91: 45106 | C91: 45109 | D91: Asia | E91: Japan | F91: Nagoya | G91: Education | H91: Marketplace | I91: F. Müller | J91: Monitors | K91: MON-2990 | L91: 55.65 | M91: 83.57 | N91: 0.066 | O91: 8
A92: ORD-2025-626047 | B92: 45775 | C92: 45792 | D92: Asia | E92: Japan | F92: Nagoya | G92: Education | H92: Direct | I92: N. Brown | J92: Networking | K92: NET-1966 | L92: 691.19 | M92: 1284.3 | N92: 0.074 | O92: 7
A93: ORD-2025-526752 | B93: 45817 | C93: 45833 | D93: Asia | E93: India | F93: Hyderabad | G93: Enterprise | H93: Distributor | I93: M. Rossi | J93: Phones | K93: PHN-3482 | L93: 527.33 | M93: 911.72 | N93: 0.144 | O93: 25
A94: ORD-2023-374486 | B94: 45101 | C94: 45100 | D94: Americas | E94: Brazil | F94: Rio de Janeiro | G94: Non-Profit | H94: Retail | I94: E. Garcia | J94: Printers | K94: PRN-6490 | L94: 804.01 | M94: 1405.07 | N94: 0.096 | O94: 8
A95: ORD-2024-997336 | B95: 45569 | C95: 45598 | D95: Africa | E95: Nigeria | F95: Abuja | G95: Corporate | H95: Distributor | I95: F. Müller | J95: Accessories | K95: ACC-9038 | L95: 412.09 | M95: 968.94 | N95: 0.099 | O95: 23
A96: ORD-2025-725646 | B96: 45910 | C96: 45930 | D96: Africa | E96: Kenya | F96: Mombasa | G96: Corporate | H96: Direct | I96: L. Okafor | J96: Phones | K96: PHN-6954 | L96: 1009.48 | M96: 1088.81 | N96: 0.16 | O96: 6
A97: ORD-2023-868734 | B97: 45022 | C97: 45043 | D97: Europe | E97: United Kingdom | F97: Manchester | G97: Enterprise | H97: Distributor | I97: I. Johnson | J97: Printers | K97: PRN-8970 | L97: 1084.79 | M97: 2484.99 | N97: 0.034 | O97: 18
A98: ORD-2025-262491 | B98: 45870 | C98: 45885 | D98: Asia | E98: India | G98: Enterprise | H98: Direct | I98: O. Wang | J98: Monitors | K98: MON-1822 | L98: 24.44 | M98: 28.69 | N98: 0.146 | O98: 6
A99: ORD-2024-638884 | B99: 45440 | C99: 45438 | D99: Africa | E99: Nigeria | F99: Abuja | G99: Enterprise | H99: Online | I99: F. Müller | J99: Accessories | K99: ACC-5177 | L99: 1227.08 | M99: 1896.62 | N99: 0 | O99: 18
A100: ORD-2025-541501 | B100: 45860 | C100: 45887 | D100: Asia | E100: China | F100: Shenzhen | G100: Non-Profit | H100: Marketplace | I100: M. Rossi | J100: Networking | K100: NET-1804 | L100: 547.32 | M100: 419.17 | N100: 0.092 | O100: 14
A101: ORD-2023-422918 | B101: 44985 | C101: 45005 | D101: Europe | E101: Germany | F101: Berlin | G101: Small Business | H101: Direct | I101: H. Kim | J101: Laptops | K101: LAP-3679 | L101: 1200.78 | M101: 2001.17 | N101: 0.292 | O101: 18
A102: ORD-2025-328504 | B102: 45684 | C102: 45703 | D102: Asia | E102: China | F102: Shenzhen | G102: Non-Profit | H102: Direct | I102: L. Okafor | J102: Phones | K102: PHN-8368 | L102: 1253.22 | M102: 3104.71 | N102: 0 | O102: 17
A103: ORD-2024-851883 | B103: 45304 | C103: 45313 | D103: Asia | E103: India | F103: Mumbai | G103: Enterprise | H103: Marketplace | I103: J. Njeri | J103: Components | K103: CMP-8141 | L103: 313.6 | M103: 334.28 | N103: 0.14 | O103: 22
A104: ORD-2025-662997 | B104: 45747 | C104: 45751 | D104: Africa | E104: Kenya | F104: Nakuru | G104: Corporate | H104: Direct | I104: C. Otieno | J104: Laptops | K104: LAP-7136 | L104: 862.08 | M104: 1952.83 | N104: 0 | O104: 7
A105: ORD-2024-478165 | B105: 45631 | C105: 45654 | D105: Americas | E105: Canada | F105: Vancouver | G105: Corporate | H105: Direct | I105: F. Müller | J105: Accessories | K105: ACC-2386 | L105: 107.03 | M105: 242.29 | N105: 0.18 | O105: 30
A106: ORD-2024-771210 | B106: 45549 | C106: 45570 | D106: Asia | E106: China | F106: Shanghai | G106: Small Business | H106: Online | I106: H. Kim | J106: Laptops | K106: LAP-5150 | L106: 1405.56 | M106: 2968.87 | N106: 0.169 | O106: 5
A107: ORD-2024-155337 | B107: 45433 | C107: 45439 | D107: Africa | E107: South Africa | F107: Johannesburg | G107: Non-Profit | H107: Online | I107: M. Rossi | J107: Components | K107: CMP-8101 | L107: 1157.51 | M107: 1394.3 | N107: 0.278 | O107: 12
A108: ORD-2023-251563 | B108: 45057 | C108: 45084 | D108: Africa | E108: Kenya | F108: Mombasa | G108: Corporate | H108: Online | I108: J. Njeri | J108: Phones | K108: PHN-8970 | L108: 12.85 | M108: 15.41 | N108: 0.137 | O108: 39
A109: ORD-2024-286833 | B109: 45518 | C109: 45539 | D109: Europe | E109: United Kingdom | F109: Manchester | G109: Non-Profit | H109: Online | I109: J. Njeri | J109: Phones | K109: PHN-2341 | L109: 1138.8 | M109: 2250.81 | N109: 0.123 | O109: 12
A110: ORD-2024-792558 | B110: 45581 | C110: 45604 | D110: Asia | E110: Japan | F110: Osaka | G110: Small Business | H110: Retail | I110: J. Njeri | J110: Networking | K110: NET-6387 | L110: 82.14 | M110: 166.04 | N110: 0 | O110: 10
... A121: ORD-2025-956101 | B121: 45847 | C121: 45856 | D121: Americas | E121: Canada | F121: Vancouver | G121: Education | H121: Distributor | I121: I. Johnson | J121: Laptops | K121: LAP-2218 | L121: 57.96 | M121: 88.51 | N121: 0.043 | O121: 7
A122: ORD-2025-184082 | B122: 45827 | C122: 45850 | D122: Europe | E122: United Kingdom | G122: Non-Profit | H122: Direct | J122: Networking | K122: NET-6370 | L122: 801.24 | M122: 1959.09 | N122: 0.123 | O122: 23
A123: ORD-2023-576840 | B123: 45249 | C123: 45273 | D123: Europe | E123: France | F123: Lyon | G123: Non-Profit | H123: Direct | I123: H. Kim | J123: Monitors | K123: MON-3745 | L123: 1297.42 | M123: 2742.97 | N123: 0.069 | O123: 9
A124: ORD-2023-178249 | B124: 45289 | C124: 45311 | D124: Africa | E124: Kenya | F124: Kisumu | G124: Corporate | H124: Direct | I124: L. Okafor | J124: Phones | K124: PHN-7924 | L124: 1395.49 | M124: 1679.42 | N124: 0.203 | O124: 12
A125: ORD-2024-588972 | B125: 45598 | C125: 45625 | D125: Americas | E125: Brazil | F125: Brasília | G125: Small Business | H125: Direct | I125: I. Johnson | J125: Networking | K125: NET-8561 | L125: 1363.51 | M125: 1433.9 | N125: 0.057 | O125: 8
A126: ORD-2023-603238 | B126: 45159 | C126: 45173 | D126: Americas | E126: Canada | F126: Montreal | G126: Education | H126: Distributor | I126: F. Müller | J126: Components | K126: CMP-2136 | L126: 178.19 | M126: 284.43 | N126: 0.089 | O126: 8
A127: ORD-2023-883066 | B127: 45150 | C127: 45175 | D127: Asia | E127: China | F127: Shanghai | G127: Small Business | H127: Retail | I127: B. Chen | J127: Components | K127: CMP-6352 | L127: 950.77 | M127: 694.78 | N127: 0.084 | O127: 14
A128: ORD-2024-584090 | B128: 45450 | C128: 45469 | D128: Europe | E128: Germany | F128: Berlin | G128: Non-Profit | H128: Marketplace | I128: M. Rossi | J128: Components | K128: CMP-2040 | L128: 1064.32 | M128: 1848.39 | N128: 0.073 | O128: 38
A129: ORD-2025-537785 | B129: 45874 | C129: 45883 | D129: Europe | E129: United Kingdom | F129: London | G129: Non-Profit | H129: Direct | I129: E. Garcia | J129: Components | K129: CMP-6346 | L129: 41.76 | M129: 45.19 | N129: 0.179 | O129: 23
A130: ORD-2024-605518 | B130: 45442 | C130: 45456 | D130: Americas | E130: USA | F130: San Francisco | G130: Small Business | H130: Retail | I130: F. Müller | J130: Phones | K130: PHN-4356 | L130: 157.78 | M130: 361.1 | N130: 0.187 | O130: 9
A131: ORD-2023-521818 | B131: 44948 | C131: 44956 | D131: Americas | E131: USA | F131: San Francisco | G131: Small Business | H131: Online | I131: A. Patel | J131: Networking | K131: NET-4155 | L131: 413.52 | M131: 1004.34 | N131: 0.111 | O131: 18
A132: ORD-2025-650719 | B132: 45700 | C132: 45716 | D132: Americas | E132: Brazil | F132: São Paulo | G132: Non-Profit | H132: Direct | I132: B. Chen | J132: Monitors | K132: MON-5179 | L132: 414.95 | M132: 1027.73 | N132: 0.063 | O132: 8
A133: ORD-2025-501927 | B133: 45719 | C133: 45740 | D133: Africa | E133: Nigeria | F133: Abuja | G133: Enterprise | H133: Direct | I133: H. Kim | J133: Accessories | K133: ACC-4056 | L133: 555.95 | M133: 468.09 | N133: 0.142 | O133: 11
A134: ORD-2023-430904 | B134: 44953 | C134: 44957 | D134: Europe | E134: United Kingdom | F134: Manchester | G134: Enterprise | H134: Online | I134: N. Brown | J134: Laptops | K134: LAP-9782 | L134: 941.2 | M134: 668.02 | N134: 0.22 | O134: 16
... A187: ORD-2023-399631 | B187: 45099 | C187: 45128 | D187: Europe | E187: France | F187: Lyon | G187: Corporate | H187: Retail | I187: J. Njeri | J187: Accessories | K187: ACC-3385 | L187: 734.34 | M187: 887.9 | N187: 0.025 | O187: 12
A188: ORD-2025-542939 | B188: 45670 | C188: 45696 | D188: Europe | E188: France | F188: Paris | G188: Non-Profit | I188: E. Garcia | J188: Monitors | K188: MON-1593 | L188: 594.74 | M188: 1020.69 | N188: 0.211 | O188: 6
A189: ORD-2023-521818 | B189: 44955 | C189: 44985 | D189: Asia | E189: India | F189: Bengaluru | G189: Non-Profit | H189: Retail | I189: B. Chen | J189: Accessories | K189: ACC-4631 | L189: 1262.1 | M189: 1395.53 | N189: 0.233 | O189: 25
A190: ORD-2023-825836 | B190: 45126 | C190: 45138 | D190: Americas | E190: Brazil | F190: Rio de Janeiro | G190: Corporate | H190: Retail | I190: C. Otieno | J190: Monitors | K190: MON-7869 | L190: 1334.64 | M190: 2273.42 | N190: 0.118 | O190: 14
A191: ORD-2024-503082 | B191: 45431 | C191: 45451 | D191: Americas | E191: Brazil | F191: Brasília | G191: Small Business | H191: Retail | I191: E. Garcia | J191: Monitors | K191: MON-4271 | L191: 1075.9 | M191: 1242.15 | N191: 0.012 | O191: 7
A192: ORD-2024-760799 | B192: 45325 | C192: 45341 | D192: Asia | E192: China | F192: Shenzhen | G192: Small Business | H192: Online | I192: H. Kim | J192: Laptops | K192: LAP-5531 | L192: 993.75 | M192: 1310.29 | N192: 0.215 | O192: 19
A193: ORD-2023-197661 | B193: 45146 | C193: 45160 | D193: Europe | E193: United Kingdom | F193: Birmingham | G193: Non-Profit | H193: Direct | I193: N. Brown | J193: Monitors | K193: MON-7511 | L193: 446.69 | M193: 967.25 | N193: 0.094 | O193: 10
A194: ORD-2024-212990 | B194: 45516 | C194: 45538 | D194: Americas | E194: USA | F194: Austin | G194: Consumer | H194: Distributor | I194: I. Johnson | J194: Laptops | K194: LAP-7979 | L194: 797.8 | M194: 886.22 | N194: 0.236 | O194: 36
A195: ORD-2023-925146 | B195: 45214 | C195: 45243 | D195: Asia | E195: China | F195: Shenzhen | G195: Non-Profit | H195: Distributor | I195: J. Njeri | J195: Printers | K195: PRN-4983 | L195: 986.44 | M195: 790.61 | N195: 0.072 | O195: 6
A196: ORD-2023-177794 | B196: 45050 | C196: 45072 | D196: Americas | E196: USA | F196: San Francisco | G196: Enterprise | H196: Online | I196: J. Njeri | J196: Networking | K196: NET-5941 | L196: 249.71 | M196: 361.33 | N196: 0.094 | O196: 12
A197: ORD-2024-444710 | B197: 45557 | C197: 45566 | D197: Americas | E197: Brazil | F197: São Paulo | G197: Non-Profit | H197: Online | I197: K. Singh | J197: Monitors | K197: MON-6341 | L197: 1378.8 | M197: 1952.04 | N197: 0.159 | O197: 19
A198: ORD-2024-668926 | B198: 45588 | C198: 45610 | D198: Asia | E198: Japan | F198: Osaka | G198: Non-Profit | H198: Direct | I198: B. Chen | J198: Phones | K198: PHN-9789 | L198: 1406.4 | M198: 1564.76 | N198: 0.185 | O198: 17
A199: ORD-2024-968374 | B199: 45333 | C199: 45354 | D199: Africa | E199: Kenya | F199: Kisumu | G199: Enterprise | H199: Online | I199: B. Chen | J199: Phones | K199: PHN-5082 | L199: 516.86 | M199: 852.54 | N199: 0.051 | O199: 14
A200: ORD-2023-575584 | B200: 44956 | C200: 44978 | D200: Europe | E200: Germany | F200: Munich | G200: Small Business | H200: Marketplace | I200: G. Dubois | J200: Networking | K200: NET-3460 | L200: 1142.88 | M200: 1465.29 | N200: 0.186 | O200: 7
... A236: ORD-2023-946143 | B236: 44999 | C236: 45015 | D236: Africa | E236: South Africa | F236: Cape Town | G236: Consumer | H236: Distributor | I236: K. Singh | J236: Components | K236: CMP-8230 | L236: 1309.77 | M236: 1589.07 | N236: 0.102 | O236: 10
A237: ORD-2024-281211 | B237: 45302 | C237: 45324 | D237: Asia | E237: Japan | F237: Nagoya | G237: Small Business | H237: Online | J237: Printers | K237: PRN-7816 | L237: 1237.68 | M237: 1432.8 | N237: 0.068 | O237: 13
A238: ORD-2024-805860 | B238: 45548 | C238: 45567 | D238: Africa | E238: Kenya | F238: Mombasa | G238: Small Business | H238: Retail | I238: M. Rossi | J238: Phones | K238: PHN-8804 | L238: 1338.99 | M238: 1765.76 | N238: 0.126 | O238: 24
A239: ORD-2025-132174 | B239: 45855 | C239: 45861 | D239: Americas | E239: Canada | F239: Vancouver | G239: Consumer | H239: Online | I239: H. Kim | J239: Components | K239: CMP-8851 | L239: 1364.89 | M239: 2757.54 | N239: 0.172 | O239: 61
A240: ORD-2023-964434 | B240: 45258 | C240: 45267 | D240: Asia | E240: India | F240: Delhi | G240: Enterprise | H240: Marketplace | I240: L. Okafor | J240: Phones | K240: PHN-2447 | L240: 699.33 | M240: 873.75 | N240: 0.235 | O240: 10
A241: ORD-2024-897622 | B241: 45381 | C241: 45406 | D241: Americas | E241: USA | F241: Austin | G241: Non-Profit | H241: Online | I241: G. Dubois | J241: Laptops | K241: LAP-2846 | L241: 160.82 | M241: 258.52 | N241: 0.13 | O241: 17
A242: ORD-2023-517216 | B242: 45188 | C242: 45207 | D242: Asia | E242: India | F242: Bengaluru | G242: Education | H242: Direct | I242: J. Njeri | J242: Printers | K242: PRN-5005 | L242: 385.32 | M242: 606.76 | N242: 0.086 | O242: 8
A243: ORD-2025-509940 | B243: 45793 | C243: 45804 | D243: Asia | E243: China | F243: Beijing | G243: Enterprise | H243: Online | I243: F. Müller | J243: Phones | K243: PHN-3800 | L243: 918.12 | M243: 1337.69 | N243: 0.095 | O243: 8
A244: ORD-2025-646342 | B244: 45871 | C244: 45877 | D244: Asia | E244: Japan | F244: Osaka | G244: Consumer | H244: Direct | I244: N. Brown | J244: Laptops | K244: LAP-4828 | L244: 1225.94 | M244: 1793.08 | N244: 0.136 | O244: 22
A245: ORD-2024-866535 | B245: 45630 | C245: 45638 | D245: Europe | E245: Germany | F245: Frankfurt | G245: Enterprise | H245: Marketplace | I245: B. Chen | J245: Printers | K245: PRN-5492 | L245: 72.06 | M245: 122.74 | N245: 0.238 | O245: 8
A246: ORD-2023-747341 | B246: 45035 | C246: 45044 | D246: Americas | E246: Brazil | F246: Rio de Janeiro | G246: Corporate | H246: Distributor | I246: M. Rossi | J246: Phones | K246: PHN-7132 | L246: 1013.54 | M246: 927.93 | N246: 0.175 | O246: 16
...

Sheet Working Sheet
A1: OrderID | B1: OrderDate | C1: RequiredDate | D1: CorrectedRequiredDate | E1: LeadTimeDays | F1: CorrectedLeadTimeDays | G1: OnTimeFlag | H1: MonthOrderDate | I1: Quarter | J1: FirstYearMonth | K1: CountryFirstMonth | L1: Region | M1: Country | N1: City | O1: CustomerSegment | P1: Channel | Q1: Salesperson | R1: MonthsSinceFirstSale | S1: ProductCategory | T1: SKU | U1: UnitCost | V1: ScenarioUnitCost | W1: CostofGoods | X1: ScenarioCostOfGoods | Y1: UnitPrice | Z1: GrossRevenue | AA1: ScenarioRev | AB1: GrossProfit | AC1: ScenarioProfit | AD1: DiscountPct | AE1: ScenarioDiscPct | AF1: HighDiscPct | AG1: Priceband | AH1: MarginPct | AI1: Quantity | AJ1: ScenarioQuanity
A2: ORD-2025-874124 | B2: 45791 | C2: 45789 | D2: =IF(C2<B2, B2+14, C2) -> 45805 | E2: =C2-B2 -> -2 | F2: =D2-B2 -> 14 | G2: =IF(Table1[[#This Row],[CorrectedLeadTimeDays]]<=7, 1, 0) -> 0 | H2: =TEXT(B2, "mmmm") -> May | I2: ="Q"&ROUNDUP(MONTH(B2)/3,0)&"-"&YEAR(B2) -> Q2-2025 | J2: =TEXT(K2, "yyyy-mm") -> 2023-01 | K2: =_xlfn.MINIFS($B:$B,$M:$M,M2) -> 44928 | L2: Americas | M2: Canada | N2: Vancouver | O2: Non-Profit | P2: Distributor | Q2: F. Müller | R2: =DATEDIF(K2,B2,"m") -> 28 | S2: Printers | T2: PRN-2407 | U2: 883.5 | V2: =Table1[[#This Row],[UnitCost]]*(1+WhatIf!$B$3) -> 927.675 | W2: =U2*AI2 -> 23854.5 | X2: =Table1[[#This Row],[ScenarioRev]]-Table1[[#This Row],[ScenarioUnitCost]] -> 54672.176 | Y2: 1978.91 | Z2: =Y2*AI2*(1-AD2) -> 50545.319 | AA2: =Table1[[#This Row],[ScenarioQuanity]]*Table1[[#This Row],[UnitPrice]]*(1-Table1[[#This Row],[ScenarioDiscPct]]) -> 55599.851 | AB2: =Z2-W2 -> 26690.819 | AC2: =Table1[[#This Row],[ScenarioRev]] - Table1[[#This Row],[ScenarioCostOfGoods]] -> 927.675 | AD2: 0.054 | AE2: =MIN(Table1[[#This Row],[DiscountPct]], WhatIf!$B$2) -> 0.054 | AF2: =IF(Table1[[#This Row],[DiscountPct]]>0.2, 1, 0) -> 0 | AG2: =IF(Y2<=_xlfn.PERCENTILE.INC($Y:$Y,0.33),"Low", IF(D2<=_xlfn.PERCENTILE.INC($Y:$Y,0.66),"Medium", "High")) -> High | AH2: =IF(Z2=0, 0, AB2/Z2) -> 0.52805719 | AI2: 27 | AJ2: =Table1[[#This Row],[Quantity]]*(1+WhatIf!$B$4) -> 29.7
A3: ORD-2024-585443 | B3: 45521 | C3: 45519 | D3: =IF(C3<B3, B3+14, C3) -> 45535 | E3: =C3-B3 -> -2 | F3: =D3-B3 -> 14 | G3: =IF(Table1[[#This Row],[CorrectedLeadTimeDays]]<=7, 1, 0) -> 0 | H3: =TEXT(B3, "mmmm") -> August | I3: ="Q"&ROUNDUP(MONTH(B3)/3,0)&"-"&YEAR(B3) -> Q3-2024 | J3: =TEXT(K3, "yyyy-mm") -> 2023-01 | K3: =_xlfn.MINIFS($B:$B,$M:$M,M3) -> 44955 | L3: Americas | M3: Brazil | N3: Rio de Janeiro | O3: Consumer | P3: Direct | Q3: M. Rossi | R3: =DATEDIF(K3,B3,"m") -> 18 | S3: Monitors | T3: MON-2849 | U3: 165.3 | V3: =Table1[[#This Row],[UnitCost]]*(1+WhatIf!$B$3) -> 173.565 | W3: =U3*AI3 -> 4132.5 | X3: =Table1[[#This Row],[ScenarioRev]]-Table1[[#This Row],[ScenarioUnitCost]] -> 6384.7915 | Y3: 275.07 | Z3: =Y3*AI3*(1-AD3) -> 5962.1422 | AA3: =Table1[[#This Row],[ScenarioQuanity]]*Table1[[#This Row],[UnitPrice]]*(1-Table1[[#This Row],[ScenarioDiscPct]]) -> 6558.3565 | AB3: =Z3-W3 -> 1829.6422 | AC3: =Table1[[#This Row],[ScenarioRev]] - Table1[[#This Row],[ScenarioCostOfGoods]] -> 173.565 | AD3: 0.133 | AE3: =MIN(Table1[[#This Row],[DiscountPct]], WhatIf!$B$2) -> 0.133 | AF3: =IF(Table1[[#This Row],[DiscountPct]]>0.2, 1, 0) -> 0 | AG3: =IF(Y3<=_xlfn.PERCENTILE.INC($Y:$Y,0.33),"Low", IF(D3<=_xlfn.PERCENTILE.INC($Y:$Y,0.66),"Medium", "High")) -> Low | AH3: =IF(Z3=0, 0, AB3/Z3) -> 0.30687665 | AI3: 25 | AJ3: =Table1[[#This Row],[Quantity]]*(1+WhatIf!$B$4) -> 27.5
A4: ORD-2023-766015 | B4: 45029 | C4: 45027 | D4: =IF(C4<B4, B4+14, C4) -> 45043 | E4: =C4-B4 -> -2 | F4: =D4-B4 -> 14 | G4: =IF(Table1[[#This Row],[CorrectedLeadTimeDays]]<=7, 1, 0) -> 0 | H4: =TEXT(B4, "mmmm") -> April | I4: ="Q"&ROUNDUP(MONTH(B4)/3,0)&"-"&YEAR(B4) -> Q2-2023 | J4: =TEXT(K4, "yyyy-mm") -> 2023-01 | K4: =_xlfn.MINIFS($B:$B,$M:$M,M4) -> 44939 | L4: Americas | M4: USA | N4: San Francisco | O4: Education | P4: Marketplace | Q4: G. Dubois | R4: =DATEDIF(K4,B4,"m") -> 3 | S4: Networking | T4: NET-1816 | U4: 32.1 | V4: =Table1[[#This Row],[UnitCost]]*(1+WhatIf!$B$3) -> 33.705 | W4: =U4*AI4 -> 706.2 | X4: =Table1[[#This Row],[ScenarioRev]]-Table1[[#This Row],[ScenarioUnitCost]] -> 1333.111 | Y4: 70.6 | Z4: =Y4*AI4*(1-AD4) -> 1115.1976 | AA4: =Table1[[#This Row],[ScenarioQuanity]]*Table1[[#This Row],[UnitPrice]]*(1-Table1[[#This Row],[ScenarioDiscPct]]) -> 1366.816 | AB4: =Z4-W4 -> 408.9976 | AC4: =Table1[[#This Row],[ScenarioRev]] - Table1[[#This Row],[ScenarioCostOfGoods]] -> 33.705 | AD4: 0.282 | AE4: =MIN(Table1[[#This Row],[DiscountPct]], WhatIf!$B$2) -> 0.2 | AF4: =IF(Table1[[#This Row],[DiscountPct]]>0.2, 1, 0) -> 1 | AG4: =IF(Y4<=_xlfn.PERCENTILE.INC($Y:$Y,0.33),"Low", IF(D4<=_xlfn.PERCENTILE.INC($Y:$Y,0.66),"Medium", "High")) -> Low | AH4: =IF(Z4=0, 0, AB4/Z4) -> 0.366749 | AI4: 22 | AJ4: =Table1[[#This Row],[Quantity]]*(1+WhatIf!$B$4) -> 24.2
A5: ORD-2024-594527 | B5: 45541 | C5: 45539 | D5: =IF(C5<B5, B5+14, C5) -> 45555 | E5: =C5-B5 -> -2 | F5: =D5-B5 -> 14 | G5: =IF(Table1[[#This Row],[CorrectedLeadTimeDays]]<=7, 1, 0) -> 0 | H5: =TEXT(B5, "mmmm") -> September | I5: ="Q"&ROUNDUP(MONTH(B5)/3,0)&"-"&YEAR(B5) -> Q3-2024 | J5: =TEXT(K5, "yyyy-mm") -> 2023-03 | K5: =_xlfn.MINIFS($B:$B,$M:$M,M5) -> 44988 | L5: Asia | M5: Japan | N5: Osaka | O5: Corporate | P5: Direct | Q5: A. Patel | R5: =DATEDIF(K5,B5,"m") -> 18 | S5: Laptops | T5: LAP-4483 | U5: 1368.17 | V5: =Table1[[#This Row],[UnitCost]]*(1+WhatIf!$B$3) -> 1436.5785 | W5: =U5*AI5 -> 28731.57 | X5: =Table1[[#This Row],[ScenarioRev]]-Table1[[#This Row],[ScenarioUnitCost]] -> 43183.075 | Y5: 2307.75 | Z5: =Y5*AI5*(1-AD5) -> 40563.322 | AA5: =Table1[[#This Row],[ScenarioQuanity]]*Table1[[#This Row],[UnitPrice]]*(1-Table1[[#This Row],[ScenarioDiscPct]]) -> 44619.654 | AB5: =Z5-W5 -> 11831.752 | AC5: =Table1[[#This Row],[ScenarioRev]] - Table1[[#This Row],[ScenarioCostOfGoods]] -> 1436.5785 | AD5: 0.163 | AE5: =MIN(Table1[[#This Row],[DiscountPct]], WhatIf!$B$2) -> 0.163 | AF5: =IF(Table1[[#This Row],[DiscountPct]]>0.2, 1, 0) -> 0 | AG5: =IF(Y5<=_xlfn.PERCENTILE.INC($Y:$Y,0.33),"Low", IF(D5<=_xlfn.PERCENTILE.INC($Y:$Y,0.66),"Medium", "High")) -> High | AH5: =IF(Z5=0, 0, AB5/Z5) -> 0.29168597 | AI5: 21 | AJ5: =Table1[[#This Row],[Quantity]]*(1+WhatIf!$B$4) -> 23.1
A6: ORD-2025-745263 | B6: 45798 | C6: 45796 | D6: =IF(C6<B6, B6+14, C6) -> 45812 | E6: =C6-B6 -> -2 | F6: =D6-B6 -> 14 | G6: =IF(Table1[[#This Row],[CorrectedLeadTimeDays]]<=7, 1, 0) -> 0 | H6: =TEXT(B6, "mmmm") -> May | I6: ="Q"&ROUNDUP(MONTH(B6)/3,0)&"-"&YEAR(B6) -> Q2-2025 | J6: =TEXT(K6, "yyyy-mm") -> 2023-01 | K6: =_xlfn.MINIFS($B:$B,$M:$M,M6) -> 44945 | L6: Europe | M6: United Kingdom | N6: Birmingham | O6: Enterprise | P6: Online | Q6: M. Rossi | R6: =DATEDIF(K6,B6,"m") -> 28 | S6: Laptops | T6: LAP-3385 | U6: 1015.16 | V6: =Table1[[#This Row],[UnitCost]]*(1+WhatIf!$B$3) -> 1065.918 | W6: =U6*AI6 -> 19288.04 | X6: =Table1[[#This Row],[ScenarioRev]]-Table1[[#This Row],[ScenarioUnitCost]] -> 42124.155 | Y6: 2148.14 | Z6: =Y6*AI6*(1-AD6) -> 39263.703 | AA6: =Table1[[#This Row],[ScenarioQuanity]]*Table1[[#This Row],[UnitPrice]]*(1-Table1[[#This Row],[ScenarioDiscPct]]) -> 43190.073 | AB6: =Z6-W6 -> 19975.663 | AC6: =Table1[[#This Row],[ScenarioRev]] - Table1[[#This Row],[ScenarioCostOfGoods]] -> 1065.918 | AD6: 0.038 | AE6: =MIN(Table1[[#This Row],[DiscountPct]], WhatIf!$B$2) -> 0.038 | AF6: =IF(Table1[[#This Row],[DiscountPct]]>0.2, 1, 0) -> 0 | AG6: =IF(Y6<=_xlfn.PERCENTILE.INC($Y:$Y,0.33),"Low", IF(D6<=_xlfn.PERCENTILE.INC($Y:$Y,0.66),"Medium", "High")) -> High | AH6: =IF(Z6=0, 0, AB6/Z6) -> 0.50875647 | AI6: 19 | AJ6: =Table1[[#This Row],[Quantity]]*(1+WhatIf!$B$4) -> 20.9
A7: ORD-2024-638884 | B7: 45440 | C7: 45438 | D7: =IF(C7<B7, B7+14, C7) -> 45454 | E7: =C7-B7 -> -2 | F7: =D7-B7 -> 14 | G7: =IF(Table1[[#This Row],[CorrectedLeadTimeDays]]<=7, 1, 0) -> 0 | H7: =TEXT(B7, "mmmm") -> May | I7: ="Q"&ROUNDUP(MONTH(B7)/3,0)&"-"&YEAR(B7) -> Q2-2024 | J7: =TEXT(K7, "yyyy-mm") -> 2023-01 | K7: =_xlfn.MINIFS($B:$B,$M:$M,M7) -> 44941 | L7: Africa | M7: Nigeria | N7: Abuja | O7: Enterprise | P7: Online | Q7: F. Müller | R7: =DATEDIF(K7,B7,"m") -> 16 | S7: Accessories | T7: ACC-5177 | U7: 1227.08 | V7: =Table1[[#This Row],[UnitCost]]*(1+WhatIf!$B$3) -> 1288.434 | W7: =U7*AI7 -> 22087.44 | X7: =Table1[[#This Row],[ScenarioRev]]-Table1[[#This Row],[ScenarioUnitCost]] -> 36264.642 | Y7: 1896.62 | Z7: =Y7*AI7*(1-AD7) -> 34139.16 | AA7: =Table1[[#This Row],[ScenarioQuanity]]*Table1[[#This Row],[UnitPrice]]*(1-Table1[[#This Row],[ScenarioDiscPct]]) -> 37553.076 | AB7: =Z7-W7 -> 12051.72 | AC7: =Table1[[#This Row],[ScenarioRev]] - Table1[[#This Row],[ScenarioCostOfGoods]] -> 1288.434 | AD7: 0 | AE7: =MIN(Table1[[#This Row],[DiscountPct]], WhatIf!$B$2) -> 0 | AF7: =IF(Table1[[#This Row],[DiscountPct]]>0.2, 1, 0) -> 0 | AG7: =IF(Y7<=_xlfn.PERCENTILE.INC($Y:$Y,0.33),"Low", IF(D7<=_xlfn.PERCENTILE.INC($Y:$Y,0.66),"Medium", "High")) -> High | AH7: =IF(Z7=0, 0, AB7/Z7) -> 0.35301747 | AI7: 18 | AJ7: =Table1[[#This Row],[Quantity]]*(1+WhatIf!$B$4) -> 19.8
A8: ORD-2025-922513 | B8: 45897 | C8: 45895 | D8: =IF(C8<B8, B8+14, C8) -> 45911 | E8: =C8-B8 -> -2 | F8: =D8-B8 -> 14 | G8: =IF(Table1[[#This Row],[CorrectedLeadTimeDays]]<=7, 1, 0) -> 0 | H8: =TEXT(B8, "mmmm") -> August | I8: ="Q"&ROUNDUP(MONTH(B8)/3,0)&"-"&YEAR(B8) -> Q3-2025 | J8: =TEXT(K8, "yyyy-mm") -> 2023-01 | K8: =_xlfn.MINIFS($B:$B,$M:$M,M8) -> 44941 | L8: Africa | M8: Nigeria | N8: Port Harcourt | O8: Small Business | P8: Retail | Q8: A. Patel | R8: =DATEDIF(K8,B8,"m") -> 31 | S8: Accessories | T8: ACC-4483 | U8: 521.06 | V8: =Table1[[#This Row],[UnitCost]]*(1+WhatIf!$B$3) -> 547.113 | W8: =U8*AI8 -> 9379.08 | X8: =Table1[[#This Row],[ScenarioRev]]-Table1[[#This Row],[ScenarioUnitCost]] -> 20425.537 | Y8: 1240.31 | Z8: =Y8*AI8*(1-AD8) -> 19066.045 | AA8: =Table1[[#This Row],[ScenarioQuanity]]*Table1[[#This Row],[UnitPrice]]*(1-Table1[[#This Row],[ScenarioDiscPct]]) -> 20972.65 | AB8: =Z8-W8 -> 9686.9653 | AC8: =Table1[[#This Row],[ScenarioRev]] - Table1[[#This Row],[ScenarioCostOfGoods]] -> 547.113 | AD8: 0.146 | AE8: =MIN(Table1[[#This Row],[DiscountPct]], WhatIf!$B$2) -> 0.146 | AF8: =IF(Table1[[#This Row],[DiscountPct]]>0.2, 1, 0) -> 0 | AG8: =IF(Y8<=_xlfn.PERCENTILE.INC($Y:$Y,0.33),"Low", IF(D8<=_xlfn.PERCENTILE.INC($Y:$Y,0.66),"Medium", "High")) -> High | AH8: =IF(Z8=0, 0, AB8/Z8) -> 0.50807418 | AI8: 18 | AJ8: =Table1[[#This Row],[Quantity]]*(1+WhatIf!$B$4) -> 19.8
A9: ORD-2023-112666 | B9: 44941 | C9: 44939 | D9: =IF(C9<B9, B9+14, C9) -> 44955 | E9: =C9-B9 -> -2 | F9: =D9-B9 -> 14 | G9: =IF(Table1[[#This Row],[CorrectedLeadTimeDays]]<=7, 1, 0) -> 0 | H9: =TEXT(B9, "mmmm") -> January | I9: ="Q"&ROUNDUP(MONTH(B9)/3,0)&"-"&YEAR(B9) -> Q1-2023 | J9: =TEXT(K9, "yyyy-mm") -> 2023-01 | K9: =_xlfn.MINIFS($B:$B,$M:$M,M9) -> 44941 | L9: Africa | M9: Nigeria | N9: Abuja | O9: Education | P9: Online | Q9: O. Wang | R9: =DATEDIF(K9,B9,"m") -> 0 | S9: Printers | T9: PRN-6276 | U9: 28.38 | V9: =Table1[[#This Row],[UnitCost]]*(1+WhatIf!$B$3) -> 29.799 | W9: =U9*AI9 -> 510.84 | X9: =Table1[[#This Row],[ScenarioRev]]-Table1[[#This Row],[ScenarioUnitCost]] -> 723.77554 | Y9: 47.22 | Z9: =Y9*AI9*(1-AD9) -> 685.06776 | AA9: =Table1[[#This Row],[ScenarioQuanity]]*Table1[[#This Row],[UnitPrice]]*(1-Table1[[#This Row],[ScenarioDiscPct]]) -> 753.57454 | AB9: =Z9-W9 -> 174.22776 | AC9: =Table1[[#This Row],[ScenarioRev]] - Table1[[#This Row],[ScenarioCostOfGoods]] -> 29.799 | AD9: 0.194 | AE9: =MIN(Table1[[#This Row],[DiscountPct]], WhatIf!$B$2) -> 0.194 | AF9: =IF(Table1[[#This Row],[DiscountPct]]>0.2, 1, 0) -> 0 | AG9: =IF(Y9<=_xlfn.PERCENTILE.INC($Y:$Y,0.33),"Low", IF(D9<=_xlfn.PERCENTILE.INC($Y:$Y,0.66),"Medium", "High")) -> Low | AH9: =IF(Z9=0, 0, AB9/Z9) -> 0.25432194 | AI9: 18 | AJ9: =Table1[[#This Row],[Quantity]]*(1+WhatIf!$B$4) -> 19.8
A10: ORD-2024-451005 | B10: 45473 | C10: 45471 | D10: =IF(C10<B10, B10+14, C10) -> 45487 | E10: =C10-B10 -> -2 | F10: =D10-B10 -> 14 | G10: =IF(Table1[[#This Row],[CorrectedLeadTimeDays]]<=7, 1, 0) -> 0 | H10: =TEXT(B10, "mmmm") -> June | I10: ="Q"&ROUNDUP(MONTH(B10)/3,0)&"-"&YEAR(B10) -> Q2-2024 | J10: =TEXT(K10, "yyyy-mm") -> 2023-01 | K10: =_xlfn.MINIFS($B:$B,$M:$M,M10) -> 44955 | L10: Americas | M10: Brazil | N10: Rio de Janeiro | O10: Small Business | P10: Direct | Q10: L. Okafor | R10: =DATEDIF(K10,B10,"m") -> 17 | S10: Accessories | T10: ACC-9162 | U10: 1112.98 | V10: =Table1[[#This Row],[UnitCost]]*(1+WhatIf!$B$3) -> 1168.629 | W10: =U10*AI10 -> 18920.66 | X10: =Table1[[#This Row],[ScenarioRev]]-Table1[[#This Row],[ScenarioUnitCost]] -> 35199.831 | Y10: 2095.73 | Z10: =Y10*AI10*(1-AD10) -> 33062.236 | AA10: =Table1[[#This Row],[ScenarioQuanity]]*Table1[[#This Row],[UnitPrice]]*(1-Table1[[#This Row],[ScenarioDiscPct]]) -> 36368.46 | AB10: =Z10-W10 -> 14141.576 | AC10: =Table1[[#This Row],[ScenarioRev]] - Table1[[#This Row],[ScenarioCostOfGoods]] -> 1168.629 | AD10: 0.072 | AE10: =MIN(Table1[[#This Row],[DiscountPct]], WhatIf!$B$2) -> 0.072 | AF10: =IF(Table1[[#This Row],[DiscountPct]]>0.2, 1, 0) -> 0 | AG10: =IF(Y10<=_xlfn.PERCENTILE.INC($Y:$Y,0.33),"Low", IF(D10<=_xlfn.PERCENTILE.INC($Y:$Y,0.66),"Medium", "High")) -> High | AH10: =IF(Z10=0, 0, AB10/Z10) -> 0.42772595 | AI10: 17 | AJ10: =Table1[[#This Row],[Quantity]]*(1+WhatIf!$B$4) -> 18.7
A11: ORD-2025-700847 | B11: 45798 | C11: 45796 | D11: =IF(C11<B11, B11+14, C11) -> 45812 | E11: =C11-B11 -> -2 | F11: =D11-B11 -> 14 | G11: =IF(Table1[[#This Row],[CorrectedLeadTimeDays]]<=7, 1, 0) -> 0 | H11: =TEXT(B11, "mmmm") -> May | I11: ="Q"&ROUNDUP(MONTH(B11)/3,0)&"-"&YEAR(B11) -> Q2-2025 | J11: =TEXT(K11, "yyyy-mm") -> 2023-01 | K11: =_xlfn.MINIFS($B:$B,$M:$M,M11) -> 44933 | L11: Africa | M11: South Africa | N11: Johannesburg | O11: Non-Profit | P11: Distributor | Q11: O. Wang | R11: =DATEDIF(K11,B11,"m") -> 28 | S11: Laptops | T11: LAP-7099 | U11: 1263.84 | V11: =Table1[[#This Row],[UnitCost]]*(1+WhatIf!$B$3) -> 1327.032 | W11: =U11*AI11 -> 18957.6 | X11: =Table1[[#This Row],[ScenarioRev]]-Table1[[#This Row],[ScenarioUnitCost]] -> 33384.774 | Y11: 2281.72 | Z11: =Y11*AI11*(1-AD11) -> 31556.188 | AA11: =Table1[[#This Row],[ScenarioQuanity]]*Table1[[#This Row],[UnitPrice]]*(1-Table1[[#This Row],[ScenarioDiscPct]]) -> 34711.806 | AB11: =Z11-W11 -> 12598.588 | AC11: =Table1[[#This Row],[ScenarioRev]] - Table1[[#This Row],[ScenarioCostOfGoods]] -> 1327.032 | AD11: 0.078 | AE11: =MIN(Table1[[#This Row],[DiscountPct]], WhatIf!$B$2) -> 0.078 | AF11: =IF(Table1[[#This Row],[DiscountPct]]>0.2, 1, 0) -> 0 | AG11: =IF(Y11<=_xlfn.PERCENTILE.INC($Y:$Y,0.33),"Low", IF(D11<=_xlfn.PERCENTILE.INC($Y:$Y,0.66),"Medium", "High")) -> High | AH11: =IF(Z11=0, 0, AB11/Z11) -> 0.39924302 | AI11: 15 | AJ11: =Table1[[#This Row],[Quantity]]*(1+WhatIf!$B$4) -> 16.5
A12: ORD-2023-890605 | B12: 45101 | C12: 45099 | D12: =IF(C12<B12, B12+14, C12) -> 45115 | E12: =C12-B12 -> -2 | F12: =D12-B12 -> 14 | G12: =IF(Table1[[#This Row],[CorrectedLeadTimeDays]]<=7, 1, 0) -> 0 | H12: =TEXT(B12, "mmmm") -> June | I12: ="Q"&ROUNDUP(MONTH(B12)/3,0)&"-"&YEAR(B12) -> Q2-2023 | J12: =TEXT(K12, "yyyy-mm") -> 2023-01 | K12: =_xlfn.MINIFS($B:$B,$M:$M,M12) -> 44928 | L12: Americas | M12: Canada | N12: Toronto | O12: Non-Profit | P12: Retail | Q12: M. Rossi | R12: =DATEDIF(K12,B12,"m") -> 5 | S12: Accessories | T12: ACC-2903 | U12: 471.42 | V12: =Table1[[#This Row],[UnitCost]]*(1+WhatIf!$B$3) -> 494.991 | W12: =U12*AI12 -> 7071.3 | X12: =Table1[[#This Row],[ScenarioRev]]-Table1[[#This Row],[ScenarioUnitCost]] -> 11916.75 | Y12: 824.81 | Z12: =Y12*AI12*(1-AD12) -> 11283.401 | AA12: =Table1[[#This Row],[ScenarioQuanity]]*Table1[[#This Row],[UnitPrice]]*(1-Table1[[#This Row],[ScenarioDiscPct]]) -> 12411.741 | AB12: =Z12-W12 -> 4212.1008 | AC12: =Table1[[#This Row],[ScenarioRev]] - Table1[[#This Row],[ScenarioCostOfGoods]] -> 494.991 | AD12: 0.088 | AE12: =MIN(Table1[[#This Row],[DiscountPct]], WhatIf!$B$2) -> 0.088 | AF12: =IF(Table1[[#This Row],[DiscountPct]]>0.2, 1, 0) -> 0 | AG12: =IF(Y12<=_xlfn.PERCENTILE.INC($Y:$Y,0.33),"Low", IF(D12<=_xlfn.PERCENTILE.INC($Y:$Y,0.66),"Medium", "High")) -> High | AH12: =IF(Z12=0, 0, AB12/Z12) -> 0.37330065 | AI12: 15 | AJ12: =Table1[[#This Row],[Quantity]]*(1+WhatIf!$B$4) -> 16.5
A13: ORD-2024-567435 | B13: 45408 | C13: 45406 | D13: =IF(C13<B13, B13+14, C13) -> 45422 | E13: =C13-B13 -> -2 | F13: =D13-B13 -> 14 | G13: =IF(Table1[[#This Row],[CorrectedLeadTimeDays]]<=7, 1, 0) -> 0 | H13: =TEXT(B13, "mmmm") -> April | I13: ="Q"&ROUNDUP(MONTH(B13)/3,0)&"-"&YEAR(B13) -> Q2-2024 | J13: =TEXT(K13, "yyyy-mm") -> 2023-01 | K13: =_xlfn.MINIFS($B:$B,$M:$M,M13) -> 44945 | L13: Europe | M13: United Kingdom | N13: London | O13: Non-Profit | P13: Distributor | Q13: N. Brown | R13: =DATEDIF(K13,B13,"m") -> 15 | S13: Phones | T13: PHN-9107 | U13: 1232.77 | V13: =Table1[[#This Row],[UnitCost]]*(1+WhatIf!$B$3) -> 1294.4085 | W13: =U13*AI13 -> 12327.7 | X13: =Table1[[#This Row],[ScenarioRev]]-Table1[[#This Row],[ScenarioUnitCost]] -> 6876.5135 | Y13: 891.73 | Z13: =Y13*AI13*(1-AD13) -> 7428.1109 | AA13: =Table1[[#This Row],[ScenarioQuanity]]*Table1[[#This Row],[UnitPrice]]*(1-Table1[[#This Row],[ScenarioDiscPct]]) -> 8170.922 | AB13: =Z13-W13 -> -4899.5891 | AC13: =Table1[[#This Row],[ScenarioRev]] - Table1[[#This Row],[ScenarioCostOfGoods]] -> 1294.4085 | AD13: 0.167 | AE13: =MIN(Table1[[#This Row],[DiscountPct]], WhatIf!$B$2) -> 0.167 | AF13: =IF(Table1[[#This Row],[DiscountPct]]>0.2, 1, 0) -> 0 | AG13: =IF(Y13<=_xlfn.PERCENTILE.INC($Y:$Y,0.33),"Low", IF(D13<=_xlfn.PERCENTILE.INC($Y:$Y,0.66),"Medium", "High")) -> High | AH13: =IF(Z13=0, 0, AB13/Z13) -> -0.65960096 | AI13: 10 | AJ13: =Table1[[#This Row],[Quantity]]*(1+WhatIf!$B$4) -> 11
... A79: ORD-2024-301260 | B79: 45502 | C79: 45504 | D79: =IF(C79<B79, B79+14, C79) -> 45504 | E79: =C79-B79 -> 2 | F79: =D79-B79 -> 2 | G79: =IF(Table1[[#This Row],[CorrectedLeadTimeDays]]<=7, 1, 0) -> 1 | H79: =TEXT(B79, "mmmm") -> July | I79: ="Q"&ROUNDUP(MONTH(B79)/3,0)&"-"&YEAR(B79) -> Q3-2024 | J79: =TEXT(K79, "yyyy-mm") -> 2023-01 | K79: =_xlfn.MINIFS($B:$B,$M:$M,M79) -> 44939 | L79: Americas | M79: USA | N79: New York | O79: Education | P79: Marketplace | Q79: I. Johnson | R79: =DATEDIF(K79,B79,"m") -> 18 | S79: Printers | T79: PRN-2829 | U79: 798.97 | V79: =Table1[[#This Row],[UnitCost]]*(1+WhatIf!$B$3) -> 838.9185 | W79: =U79*AI79 -> 12783.52 | X79: =Table1[[#This Row],[ScenarioRev]]-Table1[[#This Row],[ScenarioUnitCost]] -> 27193.388 | Y79: 1814.06 | Z79: =Y79*AI79*(1-AD79) -> 25483.915 | AA79: =Table1[[#This Row],[ScenarioQuanity]]*Table1[[#This Row],[UnitPrice]]*(1-Table1[[#This Row],[ScenarioDiscPct]]) -> 28032.306 | AB79: =Z79-W79 -> 12700.395 | AC79: =Table1[[#This Row],[ScenarioRev]] - Table1[[#This Row],[ScenarioCostOfGoods]] -> 838.9185 | AD79: 0.122 | AE79: =MIN(Table1[[#This Row],[DiscountPct]], WhatIf!$B$2) -> 0.122 | AF79: =IF(Table1[[#This Row],[DiscountPct]]>0.2, 1, 0) -> 0 | AG79: =IF(Y79<=_xlfn.PERCENTILE.INC($Y:$Y,0.33),"Low", IF(D79<=_xlfn.PERCENTILE.INC($Y:$Y,0.66),"Medium", "High")) -> High | AH79: =IF(Z79=0, 0, AB79/Z79) -> 0.49836907 | AI79: 16 | AJ79: =Table1[[#This Row],[Quantity]]*(1+WhatIf!$B$4) -> 17.6
A80: ORD-2023-888140 | B80: 45210 | C80: 45212 | D80: =IF(C80<B80, B80+14, C80) -> 45212 | E80: =C80-B80 -> 2 | F80: =D80-B80 -> 2 | G80: =IF(Table1[[#This Row],[CorrectedLeadTimeDays]]<=7, 1, 0) -> 1 | H80: =TEXT(B80, "mmmm") -> October | I80: ="Q"&ROUNDUP(MONTH(B80)/3,0)&"-"&YEAR(B80) -> Q4-2023 | J80: =TEXT(K80, "yyyy-mm") -> 2023-01 | K80: =_xlfn.MINIFS($B:$B,$M:$M,M80) -> 44955 | L80: Americas | M80: Brazil | N80: Brasília | O80: Consumer | P80: Distributor | R80: =DATEDIF(K80,B80,"m") -> 8 | S80: Accessories | T80: ACC-3567 | U80: 715.94 | V80: =Table1[[#This Row],[UnitCost]]*(1+WhatIf!$B$3) -> 751.737 | W80: =U80*AI80 -> 11455.04 | X80: =Table1[[#This Row],[ScenarioRev]]-Table1[[#This Row],[ScenarioUnitCost]] -> 7574.1225 | Y80: 550.07 | Z80: =Y80*AI80*(1-AD80) -> 7568.9632 | AA80: =Table1[[#This Row],[ScenarioQuanity]]*Table1[[#This Row],[UnitPrice]]*(1-Table1[[#This Row],[ScenarioDiscPct]]) -> 8325.8595 | AB80: =Z80-W80 -> -3886.0768 | AC80: =Table1[[#This Row],[ScenarioRev]] - Table1[[#This Row],[ScenarioCostOfGoods]] -> 751.737 | AD80: 0.14 | AE80: =MIN(Table1[[#This Row],[DiscountPct]], WhatIf!$B$2) -> 0.14 | AF80: =IF(Table1[[#This Row],[DiscountPct]]>0.2, 1, 0) -> 0 | AG80: =IF(Y80<=_xlfn.PERCENTILE.INC($Y:$Y,0.33),"Low", IF(D80<=_xlfn.PERCENTILE.INC($Y:$Y,0.66),"Medium", "High")) -> Low | AH80: =IF(Z80=0, 0, AB80/Z80) -> -0.5134226 | AI80: 16 | AJ80: =Table1[[#This Row],[Quantity]]*(1+WhatIf!$B$4) -> 17.6
A81: ORD-2025-779574 | B81: 45910 | C81: 45912 | D81: =IF(C81<B81, B81+14, C81) -> 45912 | E81: =C81-B81 -> 2 | F81: =D81-B81 -> 2 | G81: =IF(Table1[[#This Row],[CorrectedLeadTimeDays]]<=7, 1, 0) -> 1 | H81: =TEXT(B81, "mmmm") -> September | I81: ="Q"&ROUNDUP(MONTH(B81)/3,0)&"-"&YEAR(B81) -> Q3-2025 | J81: =TEXT(K81, "yyyy-mm") -> 2023-03 | K81: =_xlfn.MINIFS($B:$B,$M:$M,M81) -> 44988 | L81: Asia | M81: Japan | N81: Tokyo | O81: Consumer | P81: Online | Q81: O. Wang | R81: =DATEDIF(K81,B81,"m") -> 30 | S81: Components | T81: CMP-6971 | U81: 1470.15 | V81: =Table1[[#This Row],[UnitCost]]*(1+WhatIf!$B$3) -> 1543.6575 | W81: =U81*AI81 -> 17641.8 | X81: =Table1[[#This Row],[ScenarioRev]]-Table1[[#This Row],[ScenarioUnitCost]] -> 28928.07 | Y81: 2593.78 | Z81: =Y81*AI81*(1-AD81) -> 27701.57 | AA81: =Table1[[#This Row],[ScenarioQuanity]]*Table1[[#This Row],[UnitPrice]]*(1-Table1[[#This Row],[ScenarioDiscPct]]) -> 30471.727 | AB81: =Z81-W81 -> 10059.77 | AC81: =Table1[[#This Row],[ScenarioRev]] - Table1[[#This Row],[ScenarioCostOfGoods]] -> 1543.6575 | AD81: 0.11 | AE81: =MIN(Table1[[#This Row],[DiscountPct]], WhatIf!$B$2) -> 0.11 | AF81: =IF(Table1[[#This Row],[DiscountPct]]>0.2, 1, 0) -> 0 | AG81: =IF(Y81<=_xlfn.PERCENTILE.INC($Y:$Y,0.33),"Low", IF(D81<=_xlfn.PERCENTILE.INC($Y:$Y,0.66),"Medium", "High")) -> High | AH81: =IF(Z81=0, 0, AB81/Z81) -> 0.36314802 | AI81: 12 | AJ81: =Table1[[#This Row],[Quantity]]*(1+WhatIf!$B$4) -> 13.2
A82: ORD-2023-502205 | B82: 45208 | C82: 45210 | D82: =IF(C82<B82, B82+14, C82) -> 45210 | E82: =C82-B82 -> 2 | F82: =D82-B82 -> 2 | G82: =IF(Table1[[#This Row],[CorrectedLeadTimeDays]]<=7, 1, 0) -> 1 | H82: =TEXT(B82, "mmmm") -> October | I82: ="Q"&ROUNDUP(MONTH(B82)/3,0)&"-"&YEAR(B82) -> Q4-2023 | J82: =TEXT(K82, "yyyy-mm") -> 2023-01 | K82: =_xlfn.MINIFS($B:$B,$M:$M,M82) -> 44941 | L82: Africa | M82: Nigeria | N82: Port Harcourt | O82: Education | P82: Marketplace | Q82: K. Singh | R82: =DATEDIF(K82,B82,"m") -> 8 | S82: Networking | T82: NET-8856 | U82: 391.16 | V82: =Table1[[#This Row],[UnitCost]]*(1+WhatIf!$B$3) -> 410.718 | W82: =U82*AI82 -> 4693.92 | X82: =Table1[[#This Row],[ScenarioRev]]-Table1[[#This Row],[ScenarioUnitCost]] -> 11454.236 | Y82: 902.47 | Z82: =Y82*AI82*(1-AD82) -> 10786.321 | AA82: =Table1[[#This Row],[ScenarioQuanity]]*Table1[[#This Row],[UnitPrice]]*(1-Table1[[#This Row],[ScenarioDiscPct]]) -> 11864.954 | AB82: =Z82-W82 -> 6092.4014 | AC82: =Table1[[#This Row],[ScenarioRev]] - Table1[[#This Row],[ScenarioCostOfGoods]] -> 410.718 | AD82: 0.004 | AE82: =MIN(Table1[[#This Row],[DiscountPct]], WhatIf!$B$2) -> 0.004 | AF82: =IF(Table1[[#This Row],[DiscountPct]]>0.2, 1, 0) -> 0 | AG82: =IF(Y82<=_xlfn.PERCENTILE.INC($Y:$Y,0.33),"Low", IF(D82<=_xlfn.PERCENTILE.INC($Y:$Y,0.66),"Medium", "High")) -> High | AH82: =IF(Z82=0, 0, AB82/Z82) -> 0.56482662 | AI82: 12 | AJ82: =Table1[[#This Row],[Quantity]]*(1+WhatIf!$B$4) -> 13.2
A83: ORD-2023-842488 | B83: 45230 | C83: 45232 | D83: =IF(C83<B83, B83+14, C83) -> 45232 | E83: =C83-B83 -> 2 | F83: =D83-B83 -> 2 | G83: =IF(Table1[[#This Row],[CorrectedLeadTimeDays]]<=7, 1, 0) -> 1 | H83: =TEXT(B83, "mmmm") -> October | I83: ="Q"&ROUNDUP(MONTH(B83)/3,0)&"-"&YEAR(B83) -> Q4-2023 | J83: =TEXT(K83, "yyyy-mm") -> 2023-01 | K83: =_xlfn.MINIFS($B:$B,$M:$M,M83) -> 44946 | L83: Africa | M83: Kenya | N83: Kisumu | O83: Education | P83: Retail | Q83: O. Wang | R83: =DATEDIF(K83,B83,"m") -> 9 | S83: Accessories | T83: ACC-4124 | U83: 867.89 | V83: =Table1[[#This Row],[UnitCost]]*(1+WhatIf!$B$3) -> 911.2845 | W83: =U83*AI83 -> 8678.9 | X83: =Table1[[#This Row],[ScenarioRev]]-Table1[[#This Row],[ScenarioUnitCost]] -> 11205.777 | Y83: 1349.94 | Z83: =Y83*AI83*(1-AD83) -> 11015.51 | AA83: =Table1[[#This Row],[ScenarioQuanity]]*Table1[[#This Row],[UnitPrice]]*(1-Table1[[#This Row],[ScenarioDiscPct]]) -> 12117.061 | AB83: =Z83-W83 -> 2336.6104 | AC83: =Table1[[#This Row],[ScenarioRev]] - Table1[[#This Row],[ScenarioCostOfGoods]] -> 911.2845 | AD83: 0.184 | AE83: =MIN(Table1[[#This Row],[DiscountPct]], WhatIf!$B$2) -> 0.184 | AF83: =IF(Table1[[#This Row],[DiscountPct]]>0.2, 1, 0) -> 0 | AG83: =IF(Y83<=_xlfn.PERCENTILE.INC($Y:$Y,0.33),"Low", IF(D83<=_xlfn.PERCENTILE.INC($Y:$Y,0.66),"Medium", "High")) -> High | AH83: =IF(Z83=0, 0, AB83/Z83) -> 0.21212003 | AI83: 10 | AJ83: =Table1[[#This Row],[Quantity]]*(1+WhatIf!$B$4) -> 11
A84: ORD-2025-262434 | B84: 45827 | C84: 45829 | D84: =IF(C84<B84, B84+14, C84) -> 45829 | E84: =C84-B84 -> 2 | F84: =D84-B84 -> 2 | G84: =IF(Table1[[#This Row],[CorrectedLeadTimeDays]]<=7, 1, 0) -> 1 | H84: =TEXT(B84, "mmmm") -> June | I84: ="Q"&ROUNDUP(MONTH(B84)/3,0)&"-"&YEAR(B84) -> Q2-2025 | J84: =TEXT(K84, "yyyy-mm") -> 2023-01 | K84: =_xlfn.MINIFS($B:$B,$M:$M,M84) -> 44933 | L84: Africa | M84: South Africa | N84: Johannesburg | O84: Small Business | Q84: H. Kim | R84: =DATEDIF(K84,B84,"m") -> 29 | S84: Phones | T84: PHN-7379 | U84: 1466.27 | V84: =Table1[[#This Row],[UnitCost]]*(1+WhatIf!$B$3) -> 1539.5835 | W84: =U84*AI84 -> 13196.43 | X84: =Table1[[#This Row],[ScenarioRev]]-Table1[[#This Row],[ScenarioUnitCost]] -> 30552.956 | Y84: 3589.89 | Z84: =Y84*AI84*(1-AD84) -> 29175.036 | AA84: =Table1[[#This Row],[ScenarioQuanity]]*Table1[[#This Row],[UnitPrice]]*(1-Table1[[#This Row],[ScenarioDiscPct]]) -> 32092.54 | AB84: =Z84-W84 -> 15978.606 | AC84: =Table1[[#This Row],[ScenarioRev]] - Table1[[#This Row],[ScenarioCostOfGoods]] -> 1539.5835 | AD84: 0.097 | AE84: =MIN(Table1[[#This Row],[DiscountPct]], WhatIf!$B$2) -> 0.097 | AF84: =IF(Table1[[#This Row],[DiscountPct]]>0.2, 1, 0) -> 0 | AG84: =IF(Y84<=_xlfn.PERCENTILE.INC($Y:$Y,0.33),"Low", IF(D84<=_xlfn.PERCENTILE.INC($Y:$Y,0.66),"Medium", "High")) -> High | AH84: =IF(Z84=0, 0, AB84/Z84) -> 0.54768076 | AI84: 9 | AJ84: =Table1[[#This Row],[Quantity]]*(1+WhatIf!$B$4) -> 9.9
A85: ORD-2024-257550 | B85: 45653 | C85: 45655 | D85: =IF(C85<B85, B85+14, C85) -> 45655 | E85: =C85-B85 -> 2 | F85: =D85-B85 -> 2 | G85: =IF(Table1[[#This Row],[CorrectedLeadTimeDays]]<=7, 1, 0) -> 1 | H85: =TEXT(B85, "mmmm") -> December | I85: ="Q"&ROUNDUP(MONTH(B85)/3,0)&"-"&YEAR(B85) -> Q4-2024 | J85: =TEXT(K85, "yyyy-mm") -> 2023-01 | K85: =_xlfn.MINIFS($B:$B,$M:$M,M85) -> 44928 | L85: Americas | M85: Canada | N85: Vancouver | O85: Enterprise | P85: Marketplace | Q85: C. Otieno | R85: =DATEDIF(K85,B85,"m") -> 23 | S85: Accessories | T85: ACC-8620 | U85: 1146.72 | V85: =Table1[[#This Row],[UnitCost]]*(1+WhatIf!$B$3) -> 1204.056 | W85: =U85*AI85 -> 9173.76 | X85: =Table1[[#This Row],[ScenarioRev]]-Table1[[#This Row],[ScenarioUnitCost]] -> 15023.921 | Y85: 2074.34 | Z85: =Y85*AI85*(1-AD85) -> 14752.706 | AA85: =Table1[[#This Row],[ScenarioQuanity]]*Table1[[#This Row],[UnitPrice]]*(1-Table1[[#This Row],[ScenarioDiscPct]]) -> 16227.977 | AB85: =Z85-W85 -> 5578.9461 | AC85: =Table1[[#This Row],[ScenarioRev]] - Table1[[#This Row],[ScenarioCostOfGoods]] -> 1204.056 | AD85: 0.111 | AE85: =MIN(Table1[[#This Row],[DiscountPct]], WhatIf!$B$2) -> 0.111 | AF85: =IF(Table1[[#This Row],[DiscountPct]]>0.2, 1, 0) -> 0 | AG85: =IF(Y85<=_xlfn.PERCENTILE.INC($Y:$Y,0.33),"Low", IF(D85<=_xlfn.PERCENTILE.INC($Y:$Y,0.66),"Medium", "High")) -> High | AH85: =IF(Z85=0, 0, AB85/Z85) -> 0.37816425 | AI85: 8 | AJ85: =Table1[[#This Row],[Quantity]]*(1+WhatIf!$B$4) -> 8.8
A86: ORD-2024-499009 | B86: 45316 | C86: 45318 | D86: =IF(C86<B86, B86+14, C86) -> 45318 | E86: =C86-B86 -> 2 | F86: =D86-B86 -> 2 | G86: =IF(Table1[[#This Row],[CorrectedLeadTimeDays]]<=7, 1, 0) -> 1 | H86: =TEXT(B86, "mmmm") -> January | I86: ="Q"&ROUNDUP(MONTH(B86)/3,0)&"-"&YEAR(B86) -> Q1-2024 | J86: =TEXT(K86, "yyyy-mm") -> 2023-01 | K86: =_xlfn.MINIFS($B:$B,$M:$M,M86) -> 44955 | L86: Americas | M86: Brazil | N86: São Paulo | O86: Non-Profit | P86: Marketplace | Q86: N. Brown | R86: =DATEDIF(K86,B86,"m") -> 11 | S86: Laptops | T86: LAP-7056 | U86: 1410.97 | V86: =Table1[[#This Row],[UnitCost]]*(1+WhatIf!$B$3) -> 1481.5185 | W86: =U86*AI86 -> 8465.82 | X86: =Table1[[#This Row],[ScenarioRev]]-Table1[[#This Row],[ScenarioUnitCost]] -> 7942.6133 | Y86: 1650.75 | Z86: =Y86*AI86*(1-AD86) -> 8567.3925 | AA86: =Table1[[#This Row],[ScenarioQuanity]]*Table1[[#This Row],[UnitPrice]]*(1-Table1[[#This Row],[ScenarioDiscPct]]) -> 9424.1318 | AB86: =Z86-W86 -> 101.5725 | AC86: =Table1[[#This Row],[ScenarioRev]] - Table1[[#This Row],[ScenarioCostOfGoods]] -> 1481.5185 | AD86: 0.135 | AE86: =MIN(Table1[[#This Row],[DiscountPct]], WhatIf!$B$2) -> 0.135 | AF86: =IF(Table1[[#This Row],[DiscountPct]]>0.2, 1, 0) -> 0 | AG86: =IF(Y86<=_xlfn.PERCENTILE.INC($Y:$Y,0.33),"Low", IF(D86<=_xlfn.PERCENTILE.INC($Y:$Y,0.66),"Medium", "High")) -> High | AH86: =IF(Z86=0, 0, AB86/Z86) -> 0.011855708 | AI86: 6 | AJ86: =Table1[[#This Row],[Quantity]]*(1+WhatIf!$B$4) -> 6.6
A87: ORD-2023-235230 | B87: 45168 | C87: 45170 | D87: =IF(C87<B87, B87+14, C87) -> 45170 | E87: =C87-B87 -> 2 | F87: =D87-B87 -> 2 | G87: =IF(Table1[[#This Row],[CorrectedLeadTimeDays]]<=7, 1, 0) -> 1 | H87: =TEXT(B87, "mmmm") -> August | I87: ="Q"&ROUNDUP(MONTH(B87)/3,0)&"-"&YEAR(B87) -> Q3-2023 | J87: =TEXT(K87, "yyyy-mm") -> 2023-01 | K87: =_xlfn.MINIFS($B:$B,$M:$M,M87) -> 44948 | L87: Europe | M87: Germany | N87: Munich | O87: Corporate | P87: Direct | Q87: N. Brown | R87: =DATEDIF(K87,B87,"m") -> 7 | S87: Networking | T87: NET-9989 | U87: 44.42 | V87: =Table1[[#This Row],[UnitCost]]*(1+WhatIf!$B$3) -> 46.641 | W87: =U87*AI87 -> 266.52 | X87: =Table1[[#This Row],[ScenarioRev]]-Table1[[#This Row],[ScenarioUnitCost]] -> 190.07724 | Y87: 41.9 | Z87: =Y87*AI87*(1-AD87) -> 215.1984 | AA87: =Table1[[#This Row],[ScenarioQuanity]]*Table1[[#This Row],[UnitPrice]]*(1-Table1[[#This Row],[ScenarioDiscPct]]) -> 236.71824 | AB87: =Z87-W87 -> -51.3216 | AC87: =Table1[[#This Row],[ScenarioRev]] - Table1[[#This Row],[ScenarioCostOfGoods]] -> 46.641 | AD87: 0.144 | AE87: =MIN(Table1[[#This Row],[DiscountPct]], WhatIf!$B$2) -> 0.144 | AF87: =IF(Table1[[#This Row],[DiscountPct]]>0.2, 1, 0) -> 0 | AG87: =IF(Y87<=_xlfn.PERCENTILE.INC($Y:$Y,0.33),"Low", IF(D87<=_xlfn.PERCENTILE.INC($Y:$Y,0.66),"Medium", "High")) -> Low | AH87: =IF(Z87=0, 0, AB87/Z87) -> -0.23848504 | AI87: 6 | AJ87: =Table1[[#This Row],[Quantity]]*(1+WhatIf!$B$4) -> 6.6
A88: ORD-2024-206311 | B88: 45304 | C88: 45306 | D88: =IF(C88<B88, B88+14, C88) -> 45306 | E88: =C88-B88 -> 2 | F88: =D88-B88 -> 2 | G88: =IF(Table1[[#This Row],[CorrectedLeadTimeDays]]<=7, 1, 0) -> 1 | H88: =TEXT(B88, "mmmm") -> January | I88: ="Q"&ROUNDUP(MONTH(B88)/3,0)&"-"&YEAR(B88) -> Q1-2024 | J88: =TEXT(K88, "yyyy-mm") -> 2023-01 | K88: =_xlfn.MINIFS($B:$B,$M:$M,M88) -> 44939 | L88: Americas | M88: USA | N88: San Francisco | O88: Non-Profit | P88: Direct | Q88: E. Garcia | R88: =DATEDIF(K88,B88,"m") -> 12 | S88: Components | T88: CMP-2410 | U88: 1061.37 | V88: =Table1[[#This Row],[UnitCost]]*(1+WhatIf!$B$3) -> 1114.4385 | W88: =U88*AI88 -> 4245.48 | X88: =Table1[[#This Row],[ScenarioRev]]-Table1[[#This Row],[ScenarioUnitCost]] -> 5964.3427 | Y88: 1938.33 | Z88: =Y88*AI88*(1-AD88) -> 6435.2556 | AA88: =Table1[[#This Row],[ScenarioQuanity]]*Table1[[#This Row],[UnitPrice]]*(1-Table1[[#This Row],[ScenarioDiscPct]]) -> 7078.7812 | AB88: =Z88-W88 -> 2189.7756 | AC88: =Table1[[#This Row],[ScenarioRev]] - Table1[[#This Row],[ScenarioCostOfGoods]] -> 1114.4385 | AD88: 0.17 | AE88: =MIN(Table1[[#This Row],[DiscountPct]], WhatIf!$B$2) -> 0.17 | AF88: =IF(Table1[[#This Row],[DiscountPct]]>0.2, 1, 0) -> 0 | AG88: =IF(Y88<=_xlfn.PERCENTILE.INC($Y:$Y,0.33),"Low", IF(D88<=_xlfn.PERCENTILE.INC($Y:$Y,0.66),"Medium", "High")) -> High | AH88: =IF(Z88=0, 0, AB88/Z88) -> 0.34027795 | AI88: 4 | AJ88: =Table1[[#This Row],[Quantity]]*(1+WhatIf!$B$4) -> 4.4
A89: ORD-2025-650841 | B89: 45841 | C89: 45844 | D89: =IF(C89<B89, B89+14, C89) -> 45844 | E89: =C89-B89 -> 3 | F89: =D89-B89 -> 3 | G89: =IF(Table1[[#This Row],[CorrectedLeadTimeDays]]<=7, 1, 0) -> 1 | H89: =TEXT(B89, "mmmm") -> July | I89: ="Q"&ROUNDUP(MONTH(B89)/3,0)&"-"&YEAR(B89) -> Q3-2025 | J89: =TEXT(K89, "yyyy-mm") -> 2023-01 | K89: =_xlfn.MINIFS($B:$B,$M:$M,M89) -> 44941 | L89: Africa | M89: Nigeria | N89: Lagos | O89: Consumer | P89: Online | R89: =DATEDIF(K89,B89,"m") -> 29 | S89: Laptops | T89: LAP-8910 | U89: 1313.3 | V89: =Table1[[#This Row],[UnitCost]]*(1+WhatIf!$B$3) -> 1378.965 | W89: =U89*AI89 -> 55158.6 | X89: =Table1[[#This Row],[ScenarioRev]]-Table1[[#This Row],[ScenarioUnitCost]] -> 110956.27 | Y89: 2884.34 | Z89: =Y89*AI89*(1-AD89) -> 102122.94 | AA89: =Table1[[#This Row],[ScenarioQuanity]]*Table1[[#This Row],[UnitPrice]]*(1-Table1[[#This Row],[ScenarioDiscPct]]) -> 112335.24 | AB89: =Z89-W89 -> 46964.342 | AC89: =Table1[[#This Row],[ScenarioRev]] - Table1[[#This Row],[ScenarioCostOfGoods]] -> 1378.965 | AD89: 0.157 | AE89: =MIN(Table1[[#This Row],[DiscountPct]], WhatIf!$B$2) -> 0.157 | AF89: =IF(Table1[[#This Row],[DiscountPct]]>0.2, 1, 0) -> 0 | AG89: =IF(Y89<=_xlfn.PERCENTILE.INC($Y:$Y,0.33),"Low", IF(D89<=_xlfn.PERCENTILE.INC($Y:$Y,0.66),"Medium", "High")) -> High | AH89: =IF(Z89=0, 0, AB89/Z89) -> 0.45988043 | AI89: 42 | AJ89: =Table1[[#This Row],[Quantity]]*(1+WhatIf!$B$4) -> 46.2
A90: ORD-2023-609394 | B90: 45032 | C90: 45035 | D90: =IF(C90<B90, B90+14, C90) -> 45035 | E90: =C90-B90 -> 3 | F90: =D90-B90 -> 3 | G90: =IF(Table1[[#This Row],[CorrectedLeadTimeDays]]<=7, 1, 0) -> 1 | H90: =TEXT(B90, "mmmm") -> April | I90: ="Q"&ROUNDUP(MONTH(B90)/3,0)&"-"&YEAR(B90) -> Q2-2023 | J90: =TEXT(K90, "yyyy-mm") -> 2023-01 | K90: =_xlfn.MINIFS($B:$B,$M:$M,M90) -> 44948 | L90: Europe | M90: Germany | N90: Munich | O90: Corporate | P90: Direct | Q90: B. Chen | R90: =DATEDIF(K90,B90,"m") -> 2 | S90: Accessories | T90: ACC-1731 | U90: 553.61 | V90: =Table1[[#This Row],[UnitCost]]*(1+WhatIf!$B$3) -> 581.2905 | W90: =U90*AI90 -> 18269.13 | X90: =Table1[[#This Row],[ScenarioRev]]-Table1[[#This Row],[ScenarioUnitCost]] -> 24301.655 | Y90: 699.47 | Z90: =Y90*AI90*(1-AD90) -> 22620.86 | AA90: =Table1[[#This Row],[ScenarioQuanity]]*Table1[[#This Row],[UnitPrice]]*(1-Table1[[#This Row],[ScenarioDiscPct]]) -> 24882.946 | AB90: =Z90-W90 -> 4351.7298 | AC90: =Table1[[#This Row],[ScenarioRev]] - Table1[[#This Row],[ScenarioCostOfGoods]] -> 581.2905 | AD90: 0.02 | AE90: =MIN(Table1[[#This Row],[DiscountPct]], WhatIf!$B$2) -> 0.02 | AF90: =IF(Table1[[#This Row],[DiscountPct]]>0.2, 1, 0) -> 0 | AG90: =IF(Y90<=_xlfn.PERCENTILE.INC($Y:$Y,0.33),"Low", IF(D90<=_xlfn.PERCENTILE.INC($Y:$Y,0.66),"Medium", "High")) -> Low | AH90: =IF(Z90=0, 0, AB90/Z90) -> 0.19237685 | AI90: 33 | AJ90: =Table1[[#This Row],[Quantity]]*(1+WhatIf!$B$4) -> 36.3
A91: ORD-2023-159379 | B91: 44965 | C91: 44968 | D91: =IF(C91<B91, B91+14, C91) -> 44968 | E91: =C91-B91 -> 3 | F91: =D91-B91 -> 3 | G91: =IF(Table1[[#This Row],[CorrectedLeadTimeDays]]<=7, 1, 0) -> 1 | H91: =TEXT(B91, "mmmm") -> February | I91: ="Q"&ROUNDUP(MONTH(B91)/3,0)&"-"&YEAR(B91) -> Q1-2023 | J91: =TEXT(K91, "yyyy-mm") -> 2023-01 | K91: =_xlfn.MINIFS($B:$B,$M:$M,M91) -> 44933 | L91: Africa | M91: South Africa | N91: Cape Town | O91: Corporate | P91: Direct | Q91: M. Rossi | R91: =DATEDIF(K91,B91,"m") -> 1 | S91: Networking | T91: NET-5018 | U91: 1410.05 | V91: =Table1[[#This Row],[UnitCost]]*(1+WhatIf!$B$3) -> 1480.5525 | W91: =U91*AI91 -> 36661.3 | X91: =Table1[[#This Row],[ScenarioRev]]-Table1[[#This Row],[ScenarioUnitCost]] -> 64841.533 | Y91: 2763.95 | Z91: =Y91*AI91*(1-AD91) -> 60292.805 | AA91: =Table1[[#This Row],[ScenarioQuanity]]*Table1[[#This Row],[UnitPrice]]*(1-Table1[[#This Row],[ScenarioDiscPct]]) -> 66322.086 | AB91: =Z91-W91 -> 23631.505 | AC91: =Table1[[#This Row],[ScenarioRev]] - Table1[[#This Row],[ScenarioCostOfGoods]] -> 1480.5525 | AD91: 0.161 | AE91: =MIN(Table1[[#This Row],[DiscountPct]], WhatIf!$B$2) -> 0.161 | AF91: =IF(Table1[[#This Row],[DiscountPct]]>0.2, 1, 0) -> 0 | AG91: =IF(Y91<=_xlfn.PERCENTILE.INC($Y:$Y,0.33),"Low", IF(D91<=_xlfn.PERCENTILE.INC($Y:$Y,0.66),"Medium", "High")) -> High | AH91: =IF(Z91=0, 0, AB91/Z91) -> 0.39194569 | AI91: 26 | AJ91: =Table1[[#This Row],[Quantity]]*(1+WhatIf!$B$4) -> 28.6
A92: ORD-2024-446030 | B92: 45374 | C92: 45377 | D92: =IF(C92<B92, B92+14, C92) -> 45377 | E92: =C92-B92 -> 3 | F92: =D92-B92 -> 3 | G92: =IF(Table1[[#This Row],[CorrectedLeadTimeDays]]<=7, 1, 0) -> 1 | H92: =TEXT(B92, "mmmm") -> March | I92: ="Q"&ROUNDUP(MONTH(B92)/3,0)&"-"&YEAR(B92) -> Q1-2024 | J92: =TEXT(K92, "yyyy-mm") -> 2023-01 | K92: =_xlfn.MINIFS($B:$B,$M:$M,M92) -> 44955 | L92: Asia | M92: India | N92: Bengaluru | O92: Education | P92: Direct | Q92: G. Dubois | R92: =DATEDIF(K92,B92,"m") -> 13 | S92: Phones | T92: PHN-4346 | U92: 382.21 | V92: =Table1[[#This Row],[UnitCost]]*(1+WhatIf!$B$3) -> 401.3205 | W92: =U92*AI92 -> 9937.46 | X92: =Table1[[#This Row],[ScenarioRev]]-Table1[[#This Row],[ScenarioUnitCost]] -> 13534.038 | Y92: 571.89 | Z92: =Y92*AI92*(1-AD92) -> 12668.507 | AA92: =Table1[[#This Row],[ScenarioQuanity]]*Table1[[#This Row],[UnitPrice]]*(1-Table1[[#This Row],[ScenarioDiscPct]]) -> 13935.358 | AB92: =Z92-W92 -> 2731.0473 | AC92: =Table1[[#This Row],[ScenarioRev]] - Table1[[#This Row],[ScenarioCostOfGoods]] -> 401.3205 | AD92: 0.148 | AE92: =MIN(Table1[[#This Row],[DiscountPct]], WhatIf!$B$2) -> 0.148 | AF92: =IF(Table1[[#This Row],[DiscountPct]]>0.2, 1, 0) -> 0 | AG92: =IF(Y92<=_xlfn.PERCENTILE.INC($Y:$Y,0.33),"Low", IF(D92<=_xlfn.PERCENTILE.INC($Y:$Y,0.66),"Medium", "High")) -> Low | AH92: =IF(Z92=0, 0, AB92/Z92) -> 0.21557767 | AI92: 26 | AJ92: =Table1[[#This Row],[Quantity]]*(1+WhatIf!$B$4) -> 28.6
A93: ORD-2024-468615 | B93: 45482 | C93: 45485 | D93: =IF(C93<B93, B93+14, C93) -> 45485 | E93: =C93-B93 -> 3 | F93: =D93-B93 -> 3 | G93: =IF(Table1[[#This Row],[CorrectedLeadTimeDays]]<=7, 1, 0) -> 1 | H93: =TEXT(B93, "mmmm") -> July | I93: ="Q"&ROUNDUP(MONTH(B93)/3,0)&"-"&YEAR(B93) -> Q3-2024 | J93: =TEXT(K93, "yyyy-mm") -> 2023-01 | K93: =_xlfn.MINIFS($B:$B,$M:$M,M93) -> 44938 | L93: Asia | M93: China | N93: Shanghai | O93: Small Business | P93: Retail | Q93: D. Smith | R93: =DATEDIF(K93,B93,"m") -> 17 | S93: Accessories | T93: ACC-3721 | U93: 748.39 | V93: =Table1[[#This Row],[UnitCost]]*(1+WhatIf!$B$3) -> 785.8095 | W93: =U93*AI93 -> 17212.97 | X93: =Table1[[#This Row],[ScenarioRev]]-Table1[[#This Row],[ScenarioUnitCost]] -> 23993.517 | Y93: 979.42 | Z93: =Y93*AI93*(1-AD93) -> 22526.66 | AA93: =Table1[[#This Row],[ScenarioQuanity]]*Table1[[#This Row],[UnitPrice]]*(1-Table1[[#This Row],[ScenarioDiscPct]]) -> 24779.326 | AB93: =Z93-W93 -> 5313.69 | AC93: =Table1[[#This Row],[ScenarioRev]] - Table1[[#This Row],[ScenarioCostOfGoods]] -> 785.8095 | AD93: 0 | AE93: =MIN(Table1[[#This Row],[DiscountPct]], WhatIf!$B$2) -> 0 | AF93: =IF(Table1[[#This Row],[DiscountPct]]>0.2, 1, 0) -> 0 | AG93: =IF(Y93<=_xlfn.PERCENTILE.INC($Y:$Y,0.33),"Low", IF(D93<=_xlfn.PERCENTILE.INC($Y:$Y,0.66),"Medium", "High")) -> High | AH93: =IF(Z93=0, 0, AB93/Z93) -> 0.2358845 | AI93: 23 | AJ93: =Table1[[#This Row],[Quantity]]*(1+WhatIf!$B$4) -> 25.3
A94: ORD-2024-626750 | B94: 45516 | C94: 45519 | D94: =IF(C94<B94, B94+14, C94) -> 45519 | E94: =C94-B94 -> 3 | F94: =D94-B94 -> 3 | G94: =IF(Table1[[#This Row],[CorrectedLeadTimeDays]]<=7, 1, 0) -> 1 | H94: =TEXT(B94, "mmmm") -> August | I94: ="Q"&ROUNDUP(MONTH(B94)/3,0)&"-"&YEAR(B94) -> Q3-2024 | J94: =TEXT(K94, "yyyy-mm") -> 2023-01 | K94: =_xlfn.MINIFS($B:$B,$M:$M,M94) -> 44939 | L94: Americas | M94: USA | N94: Chicago | O94: Corporate | P94: Marketplace | Q94: D. Smith | R94: =DATEDIF(K94,B94,"m") -> 18 | S94: Printers | T94: PRN-5591 | U94: 850.7 | V94: =Table1[[#This Row],[UnitCost]]*(1+WhatIf!$B$3) -> 893.235 | W94: =U94*AI94 -> 16163.3 | X94: =Table1[[#This Row],[ScenarioRev]]-Table1[[#This Row],[ScenarioUnitCost]] -> 18276.646 | Y94: 1118.56 | Z94: =Y94*AI94*(1-AD94) -> 17427.165 | AA94: =Table1[[#This Row],[ScenarioQuanity]]*Table1[[#This Row],[UnitPrice]]*(1-Table1[[#This Row],[ScenarioDiscPct]]) -> 19169.881 | AB94: =Z94-W94 -> 1263.8648 | AC94: =Table1[[#This Row],[ScenarioRev]] - Table1[[#This Row],[ScenarioCostOfGoods]] -> 893.235 | AD94: 0.18 | AE94: =MIN(Table1[[#This Row],[DiscountPct]], WhatIf!$B$2) -> 0.18 | AF94: =IF(Table1[[#This Row],[DiscountPct]]>0.2, 1, 0) -> 0 | AG94: =IF(Y94<=_xlfn.PERCENTILE.INC($Y:$Y,0.33),"Low", IF(D94<=_xlfn.PERCENTILE.INC($Y:$Y,0.66),"Medium", "High")) -> High | AH94: =IF(Z94=0, 0, AB94/Z94) -> 0.072522686 | AI94: 19 | AJ94: =Table1[[#This Row],[Quantity]]*(1+WhatIf!$B$4) -> 20.9
A95: ORD-2023-619385 | B95: 45199 | C95: 45202 | D95: =IF(C95<B95, B95+14, C95) -> 45202 | E95: =C95-B95 -> 3 | F95: =D95-B95 -> 3 | G95: =IF(Table1[[#This Row],[CorrectedLeadTimeDays]]<=7, 1, 0) -> 1 | H95: =TEXT(B95, "mmmm") -> September | I95: ="Q"&ROUNDUP(MONTH(B95)/3,0)&"-"&YEAR(B95) -> Q3-2023 | J95: =TEXT(K95, "yyyy-mm") -> 2023-01 | K95: =_xlfn.MINIFS($B:$B,$M:$M,M95) -> 44938 | L95: Asia | M95: China | N95: Beijing | O95: Non-Profit | P95: Retail | Q95: J. Njeri | R95: =DATEDIF(K95,B95,"m") -> 8 | S95: Laptops | T95: LAP-5763 | U95: 1019.36 | V95: =Table1[[#This Row],[UnitCost]]*(1+WhatIf!$B$3) -> 1070.328 | W95: =U95*AI95 -> 17329.12 | X95: =Table1[[#This Row],[ScenarioRev]]-Table1[[#This Row],[ScenarioUnitCost]] -> 14448.657 | Y95: 972.91 | Z95: =Y95*AI95*(1-AD95) -> 14108.168 | AA95: =Table1[[#This Row],[ScenarioQuanity]]*Table1[[#This Row],[UnitPrice]]*(1-Table1[[#This Row],[ScenarioDiscPct]]) -> 15518.985 | AB95: =Z95-W95 -> -3220.9521 | AC95: =Table1[[#This Row],[ScenarioRev]] - Table1[[#This Row],[ScenarioCostOfGoods]] -> 1070.328 | AD95: 0.147 | AE95: =MIN(Table1[[#This Row],[DiscountPct]], WhatIf!$B$2) -> 0.147 | AF95: =IF(Table1[[#This Row],[DiscountPct]]>0.2, 1, 0) -> 0 | AG95: =IF(Y95<=_xlfn.PERCENTILE.INC($Y:$Y,0.33),"Low", IF(D95<=_xlfn.PERCENTILE.INC($Y:$Y,0.66),"Medium", "High")) -> High | AH95: =IF(Z95=0, 0, AB95/Z95) -> -0.22830407 | AI95: 17 | AJ95: =Table1[[#This Row],[Quantity]]*(1+WhatIf!$B$4) -> 18.7
A96: ORD-2024-766980 | B96: 45600 | C96: 45603 | D96: =IF(C96<B96, B96+14, C96) -> 45603 | E96: =C96-B96 -> 3 | F96: =D96-B96 -> 3 | G96: =IF(Table1[[#This Row],[CorrectedLeadTimeDays]]<=7, 1, 0) -> 1 | H96: =TEXT(B96, "mmmm") -> November | I96: ="Q"&ROUNDUP(MONTH(B96)/3,0)&"-"&YEAR(B96) -> Q4-2024 | J96: =TEXT(K96, "yyyy-mm") -> 2023-01 | K96: =_xlfn.MINIFS($B:$B,$M:$M,M96) -> 44936 | L96: Europe | M96: France | N96: Lyon | O96: Corporate | P96: Online | Q96: O. Wang | R96: =DATEDIF(K96,B96,"m") -> 21 | S96: Monitors | T96: MON-1118 | U96: 740.68 | V96: =Table1[[#This Row],[UnitCost]]*(1+WhatIf!$B$3) -> 777.714 | W96: =U96*AI96 -> 12591.56 | X96: =Table1[[#This Row],[ScenarioRev]]-Table1[[#This Row],[ScenarioUnitCost]] -> 26809.715 | Y96: 1837.19 | Z96: =Y96*AI96*(1-AD96) -> 25079.481 | AA96: =Table1[[#This Row],[ScenarioQuanity]]*Table1[[#This Row],[UnitPrice]]*(1-Table1[[#This Row],[ScenarioDiscPct]]) -> 27587.429 | AB96: =Z96-W96 -> 12487.921 | AC96: =Table1[[#This Row],[ScenarioRev]] - Table1[[#This Row],[ScenarioCostOfGoods]] -> 777.714 | AD96: 0.197 | AE96: =MIN(Table1[[#This Row],[DiscountPct]], WhatIf!$B$2) -> 0.197 | AF96: =IF(Table1[[#This Row],[DiscountPct]]>0.2, 1, 0) -> 0 | AG96: =IF(Y96<=_xlfn.PERCENTILE.INC($Y:$Y,0.33),"Low", IF(D96<=_xlfn.PERCENTILE.INC($Y:$Y,0.66),"Medium", "High")) -> High | AH96: =IF(Z96=0, 0, AB96/Z96) -> 0.49793378 | AI96: 17 | AJ96: =Table1[[#This Row],[Quantity]]*(1+WhatIf!$B$4) -> 18.7
A97: ORD-2024-170021 | B97: 45601 | C97: 45604 | D97: =IF(C97<B97, B97+14, C97) -> 45604 | E97: =C97-B97 -> 3 | F97: =D97-B97 -> 3 | G97: =IF(Table1[[#This Row],[CorrectedLeadTimeDays]]<=7, 1, 0) -> 1 | H97: =TEXT(B97, "mmmm") -> November | I97: ="Q"&ROUNDUP(MONTH(B97)/3,0)&"-"&YEAR(B97) -> Q4-2024 | J97: =TEXT(K97, "yyyy-mm") -> 2023-01 | K97: =_xlfn.MINIFS($B:$B,$M:$M,M97) -> 44928 | L97: Americas | M97: Canada | N97: Toronto | O97: Education | P97: Marketplace | Q97: O. Wang | R97: =DATEDIF(K97,B97,"m") -> 22 | S97: Components | T97: CMP-2015 | U97: 1020.4 | V97: =Table1[[#This Row],[UnitCost]]*(1+WhatIf!$B$3) -> 1071.42 | W97: =U97*AI97 -> 16326.4 | X97: =Table1[[#This Row],[ScenarioRev]]-Table1[[#This Row],[ScenarioUnitCost]] -> 17569.281 | Y97: 1184.71 | Z97: =Y97*AI97*(1-AD97) -> 16946.092 | AA97: =Table1[[#This Row],[ScenarioQuanity]]*Table1[[#This Row],[UnitPrice]]*(1-Table1[[#This Row],[ScenarioDiscPct]]) -> 18640.701 | AB97: =Z97-W97 -> 619.69184 | AC97: =Table1[[#This Row],[ScenarioRev]] - Table1[[#This Row],[ScenarioCostOfGoods]] -> 1071.42 | AD97: 0.106 | AE97: =MIN(Table1[[#This Row],[DiscountPct]], WhatIf!$B$2) -> 0.106 | AF97: =IF(Table1[[#This Row],[DiscountPct]]>0.2, 1, 0) -> 0 | AG97: =IF(Y97<=_xlfn.PERCENTILE.INC($Y:$Y,0.33),"Low", IF(D97<=_xlfn.PERCENTILE.INC($Y:$Y,0.66),"Medium", "High")) -> High | AH97: =IF(Z97=0, 0, AB97/Z97) -> 0.036568422 | AI97: 16 | AJ97: =Table1[[#This Row],[Quantity]]*(1+WhatIf!$B$4) -> 17.6
A98: ORD-2023-674887 | B98: 45276 | C98: 45279 | D98: =IF(C98<B98, B98+14, C98) -> 45279 | E98: =C98-B98 -> 3 | F98: =D98-B98 -> 3 | G98: =IF(Table1[[#This Row],[CorrectedLeadTimeDays]]<=7, 1, 0) -> 1 | H98: =TEXT(B98, "mmmm") -> December | I98: ="Q"&ROUNDUP(MONTH(B98)/3,0)&"-"&YEAR(B98) -> Q4-2023 | J98: =TEXT(K98, "yyyy-mm") -> 2023-01 | K98: =_xlfn.MINIFS($B:$B,$M:$M,M98) -> 44938 | L98: Asia | M98: China | N98: Beijing | O98: Education | P98: Retail | Q98: A. Patel | R98: =DATEDIF(K98,B98,"m") -> 11 | S98: Accessories | T98: ACC-9644 | U98: 1415.05 | V98: =Table1[[#This Row],[UnitCost]]*(1+WhatIf!$B$3) -> 1485.8025 | W98: =U98*AI98 -> 16980.6 | X98: =Table1[[#This Row],[ScenarioRev]]-Table1[[#This Row],[ScenarioUnitCost]] -> 24549.614 | Y98: 1972.38 | Z98: =Y98*AI98*(1-AD98) -> 23668.56 | AA98: =Table1[[#This Row],[ScenarioQuanity]]*Table1[[#This Row],[UnitPrice]]*(1-Table1[[#This Row],[ScenarioDiscPct]]) -> 26035.416 | AB98: =Z98-W98 -> 6687.96 | AC98: =Table1[[#This Row],[ScenarioRev]] - Table1[[#This Row],[ScenarioCostOfGoods]] -> 1485.8025 | AD98: 0 | AE98: =MIN(Table1[[#This Row],[DiscountPct]], WhatIf!$B$2) -> 0 | AF98: =IF(Table1[[#This Row],[DiscountPct]]>0.2, 1, 0) -> 0 | AG98: =IF(Y98<=_xlfn.PERCENTILE.INC($Y:$Y,0.33),"Low", IF(D98<=_xlfn.PERCENTILE.INC($Y:$Y,0.66),"Medium", "High")) -> High | AH98: =IF(Z98=0, 0, AB98/Z98) -> 0.28256725 | AI98: 12 | AJ98: =Table1[[#This Row],[Quantity]]*(1+WhatIf!$B$4) -> 13.2
A99: ORD-2024-375848 | B99: 45430 | C99: 45433 | D99: =IF(C99<B99, B99+14, C99) -> 45433 | E99: =C99-B99 -> 3 | F99: =D99-B99 -> 3 | G99: =IF(Table1[[#This Row],[CorrectedLeadTimeDays]]<=7, 1, 0) -> 1 | H99: =TEXT(B99, "mmmm") -> May | I99: ="Q"&ROUNDUP(MONTH(B99)/3,0)&"-"&YEAR(B99) -> Q2-2024 | J99: =TEXT(K99, "yyyy-mm") -> 2023-01 | K99: =_xlfn.MINIFS($B:$B,$M:$M,M99) -> 44936 | L99: Europe | M99: France | N99: Marseille | O99: Non-Profit | P99: Marketplace | Q99: D. Smith | R99: =DATEDIF(K99,B99,"m") -> 16 | S99: Printers | T99: PRN-1725 | U99: 663.66 | V99: =Table1[[#This Row],[UnitCost]]*(1+WhatIf!$B$3) -> 696.843 | W99: =U99*AI99 -> 7300.26 | X99: =Table1[[#This Row],[ScenarioRev]]-Table1[[#This Row],[ScenarioUnitCost]] -> 7281.9938 | Y99: 824.26 | Z99: =Y99*AI99*(1-AD99) -> 6899.8805 | AA99: =Table1[[#This Row],[ScenarioQuanity]]*Table1[[#This Row],[UnitPrice]]*(1-Table1[[#This Row],[ScenarioDiscPct]]) -> 7978.8368 | AB99: =Z99-W99 -> -400.37954 | AC99: =Table1[[#This Row],[ScenarioRev]] - Table1[[#This Row],[ScenarioCostOfGoods]] -> 696.843 | AD99: 0.239 | AE99: =MIN(Table1[[#This Row],[DiscountPct]], WhatIf!$B$2) -> 0.2 | AF99: =IF(Table1[[#This Row],[DiscountPct]]>0.2, 1, 0) -> 1 | AG99: =IF(Y99<=_xlfn.PERCENTILE.INC($Y:$Y,0.33),"Low", IF(D99<=_xlfn.PERCENTILE.INC($Y:$Y,0.66),"Medium", "High")) -> High | AH99: =IF(Z99=0, 0, AB99/Z99) -> -0.058027026 | AI99: 11 | AJ99: =Table1[[#This Row],[Quantity]]*(1+WhatIf!$B$4) -> 12.1
A100: ORD-2024-287210 | B100: 45369 | C100: 45372 | D100: =IF(C100<B100, B100+14, C100) -> 45372 | E100: =C100-B100 -> 3 | F100: =D100-B100 -> 3 | G100: =IF(Table1[[#This Row],[CorrectedLeadTimeDays]]<=7, 1, 0) -> 1 | H100: =TEXT(B100, "mmmm") -> March | I100: ="Q"&ROUNDUP(MONTH(B100)/3,0)&"-"&YEAR(B100) -> Q1-2024 | J100: =TEXT(K100, "yyyy-mm") -> 2023-01 | K100: =_xlfn.MINIFS($B:$B,$M:$M,M100) -> 44948 | L100: Europe | M100: Germany | N100: Munich | O100: Small Business | P100: Online | Q100: M. Rossi | R100: =DATEDIF(K100,B100,"m") -> 13 | S100: Accessories | T100: ACC-2761 | U100: 910.63 | V100: =Table1[[#This Row],[UnitCost]]*(1+WhatIf!$B$3) -> 956.1615 | W100: =U100*AI100 -> 8195.67 | X100: =Table1[[#This Row],[ScenarioRev]]-Table1[[#This Row],[ScenarioUnitCost]] -> 10756.338 | Y100: 1269.4 | Z100: =Y100*AI100*(1-AD100) -> 10647.727 | AA100: =Table1[[#This Row],[ScenarioQuanity]]*Table1[[#This Row],[UnitPrice]]*(1-Table1[[#This Row],[ScenarioDiscPct]]) -> 11712.5 | AB100: =Z100-W100 -> 2452.0572 | AC100: =Table1[[#This Row],[ScenarioRev]] - Table1[[#This Row],[ScenarioCostOfGoods]] -> 956.1615 | AD100: 0.068 | AE100: =MIN(Table1[[#This Row],[DiscountPct]], WhatIf!$B$2) -> 0.068 | AF100: =IF(Table1[[#This Row],[DiscountPct]]>0.2, 1, 0) -> 0 | AG100: =IF(Y100<=_xlfn.PERCENTILE.INC($Y:$Y,0.33),"Low", IF(D100<=_xlfn.PERCENTILE.INC($Y:$Y,0.66),"Medium", "High")) -> High | AH100: =IF(Z100=0, 0, AB100/Z100) -> 0.23028926 | AI100: 9 | AJ100: =Table1[[#This Row],[Quantity]]*(1+WhatIf!$B$4) -> 9.9
A101: ORD-2023-869884 | B101: 44987 | C101: 44990 | D101: =IF(C101<B101, B101+14, C101) -> 44990 | E101: =C101-B101 -> 3 | F101: =D101-B101 -> 3 | G101: =IF(Table1[[#This Row],[CorrectedLeadTimeDays]]<=7, 1, 0) -> 1 | H101: =TEXT(B101, "mmmm") -> March | I101: ="Q"&ROUNDUP(MONTH(B101)/3,0)&"-"&YEAR(B101) -> Q1-2023 | J101: =TEXT(K101, "yyyy-mm") -> 2023-01 | K101: =_xlfn.MINIFS($B:$B,$M:$M,M101) -> 44955 | L101: Americas | M101: Brazil | N101: Brasília | O101: Enterprise | P101: Direct | Q101: G. Dubois | R101: =DATEDIF(K101,B101,"m") -> 1 | S101: Monitors | T101: MON-2828 | U101: 1473.58 | V101: =Table1[[#This Row],[UnitCost]]*(1+WhatIf!$B$3) -> 1547.259 | W101: =U101*AI101 -> 11788.64 | X101: =Table1[[#This Row],[ScenarioRev]]-Table1[[#This Row],[ScenarioUnitCost]] -> 25428.048 | Y101: 3436.52 | Z101: =Y101*AI101*(1-AD101) -> 24523.007 | AA101: =Table1[[#This Row],[ScenarioQuanity]]*Table1[[#This Row],[UnitPrice]]*(1-Table1[[#This Row],[ScenarioDiscPct]]) -> 26975.307 | AB101: =Z101-W101 -> 12734.367 | AC101: =Table1[[#This Row],[ScenarioRev]] - Table1[[#This Row],[ScenarioCostOfGoods]] -> 1547.259 | AD101: 0.108 | AE101: =MIN(Table1[[#This Row],[DiscountPct]], WhatIf!$B$2) -> 0.108 | AF101: =IF(Table1[[#This Row],[DiscountPct]]>0.2, 1, 0) -> 0 | AG101: =IF(Y101<=_xlfn.PERCENTILE.INC($Y:$Y,0.33),"Low", IF(D101<=_xlfn.PERCENTILE.INC($Y:$Y,0.66),"Medium", "High")) -> High | AH101: =IF(Z101=0, 0, AB101/Z101) -> 0.51928244 | AI101: 8 | AJ101: =Table1[[#This Row],[Quantity]]*(1+WhatIf!$B$4) -> 8.8
... A162: ORD-2023-581799 | B162: 45265 | C162: 45272 | D162: =IF(C162<B162, B162+14, C162) -> 45272 | E162: =C162-B162 -> 7 | F162: =D162-B162 -> 7 | G162: =IF(Table1[[#This Row],[CorrectedLeadTimeDays]]<=7, 1, 0) -> 1 | H162: =TEXT(B162, "mmmm") -> December | I162: ="Q"&ROUNDUP(MONTH(B162)/3,0)&"-"&YEAR(B162) -> Q4-2023 | J162: =TEXT(K162, "yyyy-mm") -> 2023-01 | K162: =_xlfn.MINIFS($B:$B,$M:$M,M162) -> 44955 | L162: Americas | M162: Brazil | N162: Brasília | O162: Corporate | P162: Direct | Q162: F. Müller | R162: =DATEDIF(K162,B162,"m") -> 10 | S162: Phones | T162: PHN-6506 | U162: 307.43 | V162: =Table1[[#This Row],[UnitCost]]*(1+WhatIf!$B$3) -> 322.8015 | W162: =U162*AI162 -> 12912.06 | X162: =Table1[[#This Row],[ScenarioRev]]-Table1[[#This Row],[ScenarioUnitCost]] -> 22554.977 | Y162: 495.19 | Z162: =Y162*AI162*(1-AD162) -> 20797.98 | AA162: =Table1[[#This Row],[ScenarioQuanity]]*Table1[[#This Row],[UnitPrice]]*(1-Table1[[#This Row],[ScenarioDiscPct]]) -> 22877.778 | AB162: =Z162-W162 -> 7885.92 | AC162: =Table1[[#This Row],[ScenarioRev]] - Table1[[#This Row],[ScenarioCostOfGoods]] -> 322.8015 | AD162: 0 | AE162: =MIN(Table1[[#This Row],[DiscountPct]], WhatIf!$B$2) -> 0 | AF162: =IF(Table1[[#This Row],[DiscountPct]]>0.2, 1, 0) -> 0 | AG162: =IF(Y162<=_xlfn.PERCENTILE.INC($Y:$Y,0.33),"Low", IF(D162<=_xlfn.PERCENTILE.INC($Y:$Y,0.66),"Medium", "High")) -> Low | AH162: =IF(Z162=0, 0, AB162/Z162) -> 0.37916759 | AI162: 42 | AJ162: =Table1[[#This Row],[Quantity]]*(1+WhatIf!$B$4) -> 46.2
A163: ORD-2023-825084 | B163: 45121 | C163: 45128 | D163: =IF(C163<B163, B163+14, C163) -> 45128 | E163: =C163-B163 -> 7 | F163: =D163-B163 -> 7 | G163: =IF(Table1[[#This Row],[CorrectedLeadTimeDays]]<=7, 1, 0) -> 1 | H163: =TEXT(B163, "mmmm") -> July | I163: ="Q"&ROUNDUP(MONTH(B163)/3,0)&"-"&YEAR(B163) -> Q3-2023 | J163: =TEXT(K163, "yyyy-mm") -> 2023-01 | K163: =_xlfn.MINIFS($B:$B,$M:$M,M163) -> 44933 | L163: Africa | M163: South Africa | N163: Durban | O163: Enterprise | P163: Marketplace | R163: =DATEDIF(K163,B163,"m") -> 6 | S163: Monitors | T163: MON-1018 | U163: 620.74 | V163: =Table1[[#This Row],[UnitCost]]*(1+WhatIf!$B$3) -> 651.777 | W163: =U163*AI163 -> 17380.72 | X163: =Table1[[#This Row],[ScenarioRev]]-Table1[[#This Row],[ScenarioUnitCost]] -> 32121.148 | Y163: 1330.07 | Z163: =Y163*AI163*(1-AD163) -> 26106.614 | AA163: =Table1[[#This Row],[ScenarioQuanity]]*Table1[[#This Row],[UnitPrice]]*(1-Table1[[#This Row],[ScenarioDiscPct]]) -> 32772.925 | AB163: =Z163-W163 -> 8725.894 | AC163: =Table1[[#This Row],[ScenarioRev]] - Table1[[#This Row],[ScenarioCostOfGoods]] -> 651.777 | AD163: 0.299 | AE163: =MIN(Table1[[#This Row],[DiscountPct]], WhatIf!$B$2) -> 0.2 | AF163: =IF(Table1[[#This Row],[DiscountPct]]>0.2, 1, 0) -> 1 | AG163: =IF(Y163<=_xlfn.PERCENTILE.INC($Y:$Y,0.33),"Low", IF(D163<=_xlfn.PERCENTILE.INC($Y:$Y,0.66),"Medium", "High")) -> High | AH163: =IF(Z163=0, 0, AB163/Z163) -> 0.33424074 | AI163: 28 | AJ163: =Table1[[#This Row],[Quantity]]*(1+WhatIf!$B$4) -> 30.8
A164: ORD-2024-640340 | B164: 45587 | C164: 45594 | D164: =IF(C164<B164, B164+14, C164) -> 45594 | E164: =C164-B164 -> 7 | F164: =D164-B164 -> 7 | G164: =IF(Table1[[#This Row],[CorrectedLeadTimeDays]]<=7, 1, 0) -> 1 | H164: =TEXT(B164, "mmmm") -> October | I164: ="Q"&ROUNDUP(MONTH(B164)/3,0)&"-"&YEAR(B164) -> Q4-2024 | J164: =TEXT(K164, "yyyy-mm") -> 2023-01 | K164: =_xlfn.MINIFS($B:$B,$M:$M,M164) -> 44941 | L164: Africa | M164: Nigeria | N164: Port Harcourt | O164: Enterprise | P164: Distributor | Q164: M. Rossi | R164: =DATEDIF(K164,B164,"m") -> 21 | S164: Monitors | T164: MON-8758 | U164: 1023.06 | V164: =Table1[[#This Row],[UnitCost]]*(1+WhatIf!$B$3) -> 1074.213 | W164: =U164*AI164 -> 23530.38 | X164: =Table1[[#This Row],[ScenarioRev]]-Table1[[#This Row],[ScenarioUnitCost]] -> 27975.289 | Y164: 1355.61 | Z164: =Y164*AI164*(1-AD164) -> 26408.638 | AA164: =Table1[[#This Row],[ScenarioQuanity]]*Table1[[#This Row],[UnitPrice]]*(1-Table1[[#This Row],[ScenarioDiscPct]]) -> 29049.502 | AB164: =Z164-W164 -> 2878.2584 | AC164: =Table1[[#This Row],[ScenarioRev]] - Table1[[#This Row],[ScenarioCostOfGoods]] -> 1074.213 | AD164: 0.153 | AE164: =MIN(Table1[[#This Row],[DiscountPct]], WhatIf!$B$2) -> 0.153 | AF164: =IF(Table1[[#This Row],[DiscountPct]]>0.2, 1, 0) -> 0 | AG164: =IF(Y164<=_xlfn.PERCENTILE.INC($Y:$Y,0.33),"Low", IF(D164<=_xlfn.PERCENTILE.INC($Y:$Y,0.66),"Medium", "High")) -> High | AH164: =IF(Z164=0, 0, AB164/Z164) -> 0.10898928 | AI164: 23 | AJ164: =Table1[[#This Row],[Quantity]]*(1+WhatIf!$B$4) -> 25.3
A165: ORD-2025-698069 | B165: 45811 | C165: 45818 | D165: =IF(C165<B165, B165+14, C165) -> 45818 | E165: =C165-B165 -> 7 | F165: =D165-B165 -> 7 | G165: =IF(Table1[[#This Row],[CorrectedLeadTimeDays]]<=7, 1, 0) -> 1 | H165: =TEXT(B165, "mmmm") -> June | I165: ="Q"&ROUNDUP(MONTH(B165)/3,0)&"-"&YEAR(B165) -> Q2-2025 | J165: =TEXT(K165, "yyyy-mm") -> 2023-01 | K165: =_xlfn.MINIFS($B:$B,$M:$M,M165) -> 44928 | L165: Americas | M165: Canada | N165: Toronto | O165: Consumer | P165: Distributor | Q165: O. Wang | R165: =DATEDIF(K165,B165,"m") -> 29 | S165: Printers | T165: PRN-6429 | U165: 75.18 | V165: =Table1[[#This Row],[UnitCost]]*(1+WhatIf!$B$3) -> 78.939 | W165: =U165*AI165 -> 1278.06 | X165: =Table1[[#This Row],[ScenarioRev]]-Table1[[#This Row],[ScenarioUnitCost]] -> 763.65215 | Y165: 53.45 | Z165: =Y165*AI165*(1-AD165) -> 765.99195 | AA165: =Table1[[#This Row],[ScenarioQuanity]]*Table1[[#This Row],[UnitPrice]]*(1-Table1[[#This Row],[ScenarioDiscPct]]) -> 842.59115 | AB165: =Z165-W165 -> -512.06805 | AC165: =Table1[[#This Row],[ScenarioRev]] - Table1[[#This Row],[ScenarioCostOfGoods]] -> 78.939 | AD165: 0.157 | AE165: =MIN(Table1[[#This Row],[DiscountPct]], WhatIf!$B$2) -> 0.157 | AF165: =IF(Table1[[#This Row],[DiscountPct]]>0.2, 1, 0) -> 0 | AG165: =IF(Y165<=_xlfn.PERCENTILE.INC($Y:$Y,0.33),"Low", IF(D165<=_xlfn.PERCENTILE.INC($Y:$Y,0.66),"Medium", "High")) -> Low | AH165: =IF(Z165=0, 0, AB165/Z165) -> -0.66850317 | AI165: 17 | AJ165: =Table1[[#This Row],[Quantity]]*(1+WhatIf!$B$4) -> 18.7
A166: ORD-2023-453699 | B166: 45108 | C166: 45115 | D166: =IF(C166<B166, B166+14, C166) -> 45115 | E166: =C166-B166 -> 7 | F166: =D166-B166 -> 7 | G166: =IF(Table1[[#This Row],[CorrectedLeadTimeDays]]<=7, 1, 0) -> 1 | H166: =TEXT(B166, "mmmm") -> July | I166: ="Q"&ROUNDUP(MONTH(B166)/3,0)&"-"&YEAR(B166) -> Q3-2023 | J166: =TEXT(K166, "yyyy-mm") -> 2023-01 | K166: =_xlfn.MINIFS($B:$B,$M:$M,M166) -> 44948 | L166: Europe | M166: Germany | N166: Frankfurt | O166: Small Business | P166: Distributor | Q166: N. Brown | R166: =DATEDIF(K166,B166,"m") -> 5 | S166: Laptops | T166: LAP-4666 | U166: 460.21 | V166: =Table1[[#This Row],[UnitCost]]*(1+WhatIf!$B$3) -> 483.2205 | W166: =U166*AI166 -> 6442.94 | X166: =Table1[[#This Row],[ScenarioRev]]-Table1[[#This Row],[ScenarioUnitCost]] -> 15042.255 | Y166: 1139.15 | Z166: =Y166*AI166*(1-AD166) -> 14114.069 | AA166: =Table1[[#This Row],[ScenarioQuanity]]*Table1[[#This Row],[UnitPrice]]*(1-Table1[[#This Row],[ScenarioDiscPct]]) -> 15525.475 | AB166: =Z166-W166 -> 7671.1285 | AC166: =Table1[[#This Row],[ScenarioRev]] - Table1[[#This Row],[ScenarioCostOfGoods]] -> 483.2205 | AD166: 0.115 | AE166: =MIN(Table1[[#This Row],[DiscountPct]], WhatIf!$B$2) -> 0.115 | AF166: =IF(Table1[[#This Row],[DiscountPct]]>0.2, 1, 0) -> 0 | AG166: =IF(Y166<=_xlfn.PERCENTILE.INC($Y:$Y,0.33),"Low", IF(D166<=_xlfn.PERCENTILE.INC($Y:$Y,0.66),"Medium", "High")) -> High | AH166: =IF(Z166=0, 0, AB166/Z166) -> 0.54350937 | AI166: 14 | AJ166: =Table1[[#This Row],[Quantity]]*(1+WhatIf!$B$4) -> 15.4
A167: ORD-2025-512310 | B167: 45724 | C167: 45731 | D167: =IF(C167<B167, B167+14, C167) -> 45731 | E167: =C167-B167 -> 7 | F167: =D167-B167 -> 7 | G167: =IF(Table1[[#This Row],[CorrectedLeadTimeDays]]<=7, 1, 0) -> 1 | H167: =TEXT(B167, "mmmm") -> March | I167: ="Q"&ROUNDUP(MONTH(B167)/3,0)&"-"&YEAR(B167) -> Q1-2025 | J167: =TEXT(K167, "yyyy-mm") -> 2023-01 | K167: =_xlfn.MINIFS($B:$B,$M:$M,M167) -> 44955 | L167: Asia | M167: India | N167: Bengaluru | O167: Corporate | P167: Distributor | Q167: K. Singh | R167: =DATEDIF(K167,B167,"m") -> 25 | S167: Laptops | T167: LAP-8119 | U167: 475.66 | V167: =Table1[[#This Row],[UnitCost]]*(1+WhatIf!$B$3) -> 499.443 | W167: =U167*AI167 -> 5232.26 | X167: =Table1[[#This Row],[ScenarioRev]]-Table1[[#This Row],[ScenarioUnitCost]] -> 4648.2426 | Y167: 529.14 | Z167: =Y167*AI167*(1-AD167) -> 4679.7142 | AA167: =Table1[[#This Row],[ScenarioQuanity]]*Table1[[#This Row],[UnitPrice]]*(1-Table1[[#This Row],[ScenarioDiscPct]]) -> 5147.6856 | AB167: =Z167-W167 -> -552.54584 | AC167: =Table1[[#This Row],[ScenarioRev]] - Table1[[#This Row],[ScenarioCostOfGoods]] -> 499.443 | AD167: 0.196 | AE167: =MIN(Table1[[#This Row],[DiscountPct]], WhatIf!$B$2) -> 0.196 | AF167: =IF(Table1[[#This Row],[DiscountPct]]>0.2, 1, 0) -> 0 | AG167: =IF(Y167<=_xlfn.PERCENTILE.INC($Y:$Y,0.33),"Low", IF(D167<=_xlfn.PERCENTILE.INC($Y:$Y,0.66),"Medium", "High")) -> Low | AH167: =IF(Z167=0, 0, AB167/Z167) -> -0.11807256 | AI167: 11 | AJ167: =Table1[[#This Row],[Quantity]]*(1+WhatIf!$B$4) -> 12.1
A168: ORD-2025-649239 | B168: 45674 | C168: 45681 | D168: =IF(C168<B168, B168+14, C168) -> 45681 | E168: =C168-B168 -> 7 | F168: =D168-B168 -> 7 | G168: =IF(Table1[[#This Row],[CorrectedLeadTimeDays]]<=7, 1, 0) -> 1 | H168: =TEXT(B168, "mmmm") -> January | I168: ="Q"&ROUNDUP(MONTH(B168)/3,0)&"-"&YEAR(B168) -> Q1-2025 | J168: =TEXT(K168, "yyyy-mm") -> 2023-01 | K168: =_xlfn.MINIFS($B:$B,$M:$M,M168) -> 44939 | L168: Americas | M168: USA | N168: Austin | O168: Enterprise | P168: Online | Q168: G. Dubois | R168: =DATEDIF(K168,B168,"m") -> 24 | S168: Accessories | T168: ACC-4511 | U168: 142.09 | V168: =Table1[[#This Row],[UnitCost]]*(1+WhatIf!$B$3) -> 149.1945 | W168: =U168*AI168 -> 1562.99 | X168: =Table1[[#This Row],[ScenarioRev]]-Table1[[#This Row],[ScenarioUnitCost]] -> 2180.0374 | Y168: 218.5 | Z168: =Y168*AI168*(1-AD168) -> 2117.4835 | AA168: =Table1[[#This Row],[ScenarioQuanity]]*Table1[[#This Row],[UnitPrice]]*(1-Table1[[#This Row],[ScenarioDiscPct]]) -> 2329.2319 | AB168: =Z168-W168 -> 554.4935 | AC168: =Table1[[#This Row],[ScenarioRev]] - Table1[[#This Row],[ScenarioCostOfGoods]] -> 149.1945 | AD168: 0.119 | AE168: =MIN(Table1[[#This Row],[DiscountPct]], WhatIf!$B$2) -> 0.119 | AF168: =IF(Table1[[#This Row],[DiscountPct]]>0.2, 1, 0) -> 0 | AG168: =IF(Y168<=_xlfn.PERCENTILE.INC($Y:$Y,0.33),"Low", IF(D168<=_xlfn.PERCENTILE.INC($Y:$Y,0.66),"Medium", "High")) -> Low | AH168: =IF(Z168=0, 0, AB168/Z168) -> 0.26186438 | AI168: 11 | AJ168: =Table1[[#This Row],[Quantity]]*(1+WhatIf!$B$4) -> 12.1
A169: ORD-2023-867166 | B169: 45029 | C169: 45036 | D169: =IF(C169<B169, B169+14, C169) -> 45036 | E169: =C169-B169 -> 7 | F169: =D169-B169 -> 7 | G169: =IF(Table1[[#This Row],[CorrectedLeadTimeDays]]<=7, 1, 0) -> 1 | H169: =TEXT(B169, "mmmm") -> April | I169: ="Q"&ROUNDUP(MONTH(B169)/3,0)&"-"&YEAR(B169) -> Q2-2023 | J169: =TEXT(K169, "yyyy-mm") -> 2023-01 | K169: =_xlfn.MINIFS($B:$B,$M:$M,M169) -> 44936 | L169: Europe | M169: France | N169: Lyon | O169: Small Business | P169: Online | Q169: A. Patel | R169: =DATEDIF(K169,B169,"m") -> 3 | S169: Laptops | T169: LAP-3565 | U169: 227.02 | V169: =Table1[[#This Row],[UnitCost]]*(1+WhatIf!$B$3) -> 238.371 | W169: =U169*AI169 -> 2270.2 | X169: =Table1[[#This Row],[ScenarioRev]]-Table1[[#This Row],[ScenarioUnitCost]] -> 4074.9208 | Y169: 434.72 | Z169: =Y169*AI169*(1-AD169) -> 3921.1744 | AA169: =Table1[[#This Row],[ScenarioQuanity]]*Table1[[#This Row],[UnitPrice]]*(1-Table1[[#This Row],[ScenarioDiscPct]]) -> 4313.2918 | AB169: =Z169-W169 -> 1650.9744 | AC169: =Table1[[#This Row],[ScenarioRev]] - Table1[[#This Row],[ScenarioCostOfGoods]] -> 238.371 | AD169: 0.098 | AE169: =MIN(Table1[[#This Row],[DiscountPct]], WhatIf!$B$2) -> 0.098 | AF169: =IF(Table1[[#This Row],[DiscountPct]]>0.2, 1, 0) -> 0 | AG169: =IF(Y169<=_xlfn.PERCENTILE.INC($Y:$Y,0.33),"Low", IF(D169<=_xlfn.PERCENTILE.INC($Y:$Y,0.66),"Medium", "High")) -> Low | AH169: =IF(Z169=0, 0, AB169/Z169) -> 0.4210408 | AI169: 10 | AJ169: =Table1[[#This Row],[Quantity]]*(1+WhatIf!$B$4) -> 11
A170: ORD-2023-651638 | B170: 45094 | C170: 45101 | D170: =IF(C170<B170, B170+14, C170) -> 45101 | E170: =C170-B170 -> 7 | F170: =D170-B170 -> 7 | G170: =IF(Table1[[#This Row],[CorrectedLeadTimeDays]]<=7, 1, 0) -> 1 | H170: =TEXT(B170, "mmmm") -> June | I170: ="Q"&ROUNDUP(MONTH(B170)/3,0)&"-"&YEAR(B170) -> Q2-2023 | J170: =TEXT(K170, "yyyy-mm") -> 2023-01 | K170: =_xlfn.MINIFS($B:$B,$M:$M,M170) -> 44939 | L170: Americas | M170: USA | N170: San Francisco | O170: Corporate | P170: Retail | Q170: I. Johnson | R170: =DATEDIF(K170,B170,"m") -> 5 | S170: Printers | T170: PRN-6536 | U170: 313.99 | V170: =Table1[[#This Row],[UnitCost]]*(1+WhatIf!$B$3) -> 329.6895 | W170: =U170*AI170 -> 2825.91 | X170: =Table1[[#This Row],[ScenarioRev]]-Table1[[#This Row],[ScenarioUnitCost]] -> 3588.7287 | Y170: 454.42 | Z170: =Y170*AI170*(1-AD170) -> 3562.1984 | AA170: =Table1[[#This Row],[ScenarioQuanity]]*Table1[[#This Row],[UnitPrice]]*(1-Table1[[#This Row],[ScenarioDiscPct]]) -> 3918.4182 | AB170: =Z170-W170 -> 736.28838 | AC170: =Table1[[#This Row],[ScenarioRev]] - Table1[[#This Row],[ScenarioCostOfGoods]] -> 329.6895 | AD170: 0.129 | AE170: =MIN(Table1[[#This Row],[DiscountPct]], WhatIf!$B$2) -> 0.129 | AF170: =IF(Table1[[#This Row],[DiscountPct]]>0.2, 1, 0) -> 0 | AG170: =IF(Y170<=_xlfn.PERCENTILE.INC($Y:$Y,0.33),"Low", IF(D170<=_xlfn.PERCENTILE.INC($Y:$Y,0.66),"Medium", "High")) -> Low | AH170: =IF(Z170=0, 0, AB170/Z170) -> 0.20669494 | AI170: 9 | AJ170: =Table1[[#This Row],[Quantity]]*(1+WhatIf!$B$4) -> 9.9
A171: ORD-2023-664790 | B171: 45032 | C171: 45039 | D171: =IF(C171<B171, B171+14, C171) -> 45039 | E171: =C171-B171 -> 7 | F171: =D171-B171 -> 7 | G171: =IF(Table1[[#This Row],[CorrectedLeadTimeDays]]<=7, 1, 0) -> 1 | H171: =TEXT(B171, "mmmm") -> April | I171: ="Q"&ROUNDUP(MONTH(B171)/3,0)&"-"&YEAR(B171) -> Q2-2023 | J171: =TEXT(K171, "yyyy-mm") -> 2023-01 | K171: =_xlfn.MINIFS($B:$B,$M:$M,M171) -> 44939 | L171: Americas | M171: USA | N171: Austin | O171: Corporate | P171: Distributor | Q171: O. Wang | R171: =DATEDIF(K171,B171,"m") -> 3 | S171: Printers | T171: PRN-9249 | U171: 1099.15 | V171: =Table1[[#This Row],[UnitCost]]*(1+WhatIf!$B$3) -> 1154.1075 | W171: =U171*AI171 -> 8793.2 | X171: =Table1[[#This Row],[ScenarioRev]]-Table1[[#This Row],[ScenarioUnitCost]] -> 10131.959 | Y171: 1431.37 | Z171: =Y171*AI171*(1-AD171) -> 10260.06 | AA171: =Table1[[#This Row],[ScenarioQuanity]]*Table1[[#This Row],[UnitPrice]]*(1-Table1[[#This Row],[ScenarioDiscPct]]) -> 11286.066 | AB171: =Z171-W171 -> 1466.8602 | AC171: =Table1[[#This Row],[ScenarioRev]] - Table1[[#This Row],[ScenarioCostOfGoods]] -> 1154.1075 | AD171: 0.104 | AE171: =MIN(Table1[[#This Row],[DiscountPct]], WhatIf!$B$2) -> 0.104 | AF171: =IF(Table1[[#This Row],[DiscountPct]]>0.2, 1, 0) -> 0 | AG171: =IF(Y171<=_xlfn.PERCENTILE.INC($Y:$Y,0.33),"Low", IF(D171<=_xlfn.PERCENTILE.INC($Y:$Y,0.66),"Medium", "High")) -> High | AH171: =IF(Z171=0, 0, AB171/Z171) -> 0.14296799 | AI171: 8 | AJ171: =Table1[[#This Row],[Quantity]]*(1+WhatIf!$B$4) -> 8.8
A172: ORD-2023-349264 | B172: 45078 | C172: 45085 | D172: =IF(C172<B172, B172+14, C172) -> 45085 | E172: =C172-B172 -> 7 | F172: =D172-B172 -> 7 | G172: =IF(Table1[[#This Row],[CorrectedLeadTimeDays]]<=7, 1, 0) -> 1 | H172: =TEXT(B172, "mmmm") -> June | I172: ="Q"&ROUNDUP(MONTH(B172)/3,0)&"-"&YEAR(B172) -> Q2-2023 | J172: =TEXT(K172, "yyyy-mm") -> 2023-01 | K172: =_xlfn.MINIFS($B:$B,$M:$M,M172) -> 44948 | L172: Europe | M172: Germany | N172: Frankfurt | O172: Consumer | P172: Online | Q172: A. Patel | R172: =DATEDIF(K172,B172,"m") -> 4 | S172: Phones | T172: PHN-1924 | U172: 804.17 | V172: =Table1[[#This Row],[UnitCost]]*(1+WhatIf!$B$3) -> 844.3785 | W172: =U172*AI172 -> 4020.85 | X172: =Table1[[#This Row],[ScenarioRev]]-Table1[[#This Row],[ScenarioUnitCost]] -> 4864.4935 | Y172: 1072.29 | Z172: =Y172*AI172*(1-AD172) -> 5189.8836 | AA172: =Table1[[#This Row],[ScenarioQuanity]]*Table1[[#This Row],[UnitPrice]]*(1-Table1[[#This Row],[ScenarioDiscPct]]) -> 5708.872 | AB172: =Z172-W172 -> 1169.0336 | AC172: =Table1[[#This Row],[ScenarioRev]] - Table1[[#This Row],[ScenarioCostOfGoods]] -> 844.3785 | AD172: 0.032 | AE172: =MIN(Table1[[#This Row],[DiscountPct]], WhatIf!$B$2) -> 0.032 | AF172: =IF(Table1[[#This Row],[DiscountPct]]>0.2, 1, 0) -> 0 | AG172: =IF(Y172<=_xlfn.PERCENTILE.INC($Y:$Y,0.33),"Low", IF(D172<=_xlfn.PERCENTILE.INC($Y:$Y,0.66),"Medium", "High")) -> High | AH172: =IF(Z172=0, 0, AB172/Z172) -> 0.22525237 | AI172: 5 | AJ172: =Table1[[#This Row],[Quantity]]*(1+WhatIf!$B$4) -> 5.5
A173: ORD-2023-271918 | B173: 45194 | C173: 45201 | D173: =IF(C173<B173, B173+14, C173) -> 45201 | E173: =C173-B173 -> 7 | F173: =D173-B173 -> 7 | G173: =IF(Table1[[#This Row],[CorrectedLeadTimeDays]]<=7, 1, 0) -> 1 | H173: =TEXT(B173, "mmmm") -> September | I173: ="Q"&ROUNDUP(MONTH(B173)/3,0)&"-"&YEAR(B173) -> Q3-2023 | J173: =TEXT(K173, "yyyy-mm") -> 2023-01 | K173: =_xlfn.MINIFS($B:$B,$M:$M,M173) -> 44939 | L173: Americas | M173: USA | N173: New York | O173: Education | P173: Marketplace | Q173: I. Johnson | R173: =DATEDIF(K173,B173,"m") -> 8 | S173: Accessories | T173: ACC-3551 | U173: 145.58 | V173: =Table1[[#This Row],[UnitCost]]*(1+WhatIf!$B$3) -> 152.859 | W173: =U173*AI173 -> 727.9 | X173: =Table1[[#This Row],[ScenarioRev]]-Table1[[#This Row],[ScenarioUnitCost]] -> 851.001 | Y173: 228.15 | Z173: =Y173*AI173*(1-AD173) -> 908.037 | AA173: =Table1[[#This Row],[ScenarioQuanity]]*Table1[[#This Row],[UnitPrice]]*(1-Table1[[#This Row],[ScenarioDiscPct]]) -> 1003.86 | AB173: =Z173-W173 -> 180.137 | AC173: =Table1[[#This Row],[ScenarioRev]] - Table1[[#This Row],[ScenarioCostOfGoods]] -> 152.859 | AD173: 0.204 | AE173: =MIN(Table1[[#This Row],[DiscountPct]], WhatIf!$B$2) -> 0.2 | AF173: =IF(Table1[[#This Row],[DiscountPct]]>0.2, 1, 0) -> 1 | AG173: =IF(Y173<=_xlfn.PERCENTILE.INC($Y:$Y,0.33),"Low", IF(D173<=_xlfn.PERCENTILE.INC($Y:$Y,0.66),"Medium", "High")) -> Low | AH173: =IF(Z173=0, 0, AB173/Z173) -> 0.19838068 | AI173: 5 | AJ173: =Table1[[#This Row],[Quantity]]*(1+WhatIf!$B$4) -> 5.5
A174: ORD-2024-901115 | B174: 45498 | C174: 45506 | D174: =IF(C174<B174, B174+14, C174) -> 45506 | E174: =C174-B174 -> 8 | F174: =D174-B174 -> 8 | G174: =IF(Table1[[#This Row],[CorrectedLeadTimeDays]]<=7, 1, 0) -> 0 | H174: =TEXT(B174, "mmmm") -> July | I174: ="Q"&ROUNDUP(MONTH(B174)/3,0)&"-"&YEAR(B174) -> Q3-2024 | J174: =TEXT(K174, "yyyy-mm") -> 2023-01 | K174: =_xlfn.MINIFS($B:$B,$M:$M,M174) -> 44928 | L174: Americas | M174: Canada | N174: Montreal | O174: Consumer | P174: Direct | Q174: J. Njeri | R174: =DATEDIF(K174,B174,"m") -> 18 | S174: Accessories | T174: ACC-6626 | U174: 986.81 | V174: =Table1[[#This Row],[UnitCost]]*(1+WhatIf!$B$3) -> 1036.1505 | W174: =U174*AI174 -> 42432.83 | X174: =Table1[[#This Row],[ScenarioRev]]-Table1[[#This Row],[ScenarioUnitCost]] -> 85954.607 | Y174: 2050.31 | Z174: =Y174*AI174*(1-AD174) -> 79082.507 | AA174: =Table1[[#This Row],[ScenarioQuanity]]*Table1[[#This Row],[UnitPrice]]*(1-Table1[[#This Row],[ScenarioDiscPct]]) -> 86990.758 | AB174: =Z174-W174 -> 36649.677 | AC174: =Table1[[#This Row],[ScenarioRev]] - Table1[[#This Row],[ScenarioCostOfGoods]] -> 1036.1505 | AD174: 0.103 | AE174: =MIN(Table1[[#This Row],[DiscountPct]], WhatIf!$B$2) -> 0.103 | AF174: =IF(Table1[[#This Row],[DiscountPct]]>0.2, 1, 0) -> 0 | AG174: =IF(Y174<=_xlfn.PERCENTILE.INC($Y:$Y,0.33),"Low", IF(D174<=_xlfn.PERCENTILE.INC($Y:$Y,0.66),"Medium", "High")) -> High | AH174: =IF(Z174=0, 0, AB174/Z174) -> 0.46343595 | AI174: 43 | AJ174: =Table1[[#This Row],[Quantity]]*(1+WhatIf!$B$4) -> 47.3
A175: ORD-2023-856322 | B175: 44955 | C175: 44963 | D175: =IF(C175<B175, B175+14, C175) -> 44963 | E175: =C175-B175 -> 8 | F175: =D175-B175 -> 8 | G175: =IF(Table1[[#This Row],[CorrectedLeadTimeDays]]<=7, 1, 0) -> 0 | H175: =TEXT(B175, "mmmm") -> January | I175: ="Q"&ROUNDUP(MONTH(B175)/3,0)&"-"&YEAR(B175) -> Q1-2023 | J175: =TEXT(K175, "yyyy-mm") -> 2023-01 | K175: =_xlfn.MINIFS($B:$B,$M:$M,M175) -> 44955 | L175: Americas | M175: Brazil | N175: Brasília | O175: Corporate | P175: Marketplace | Q175: D. Smith | R175: =DATEDIF(K175,B175,"m") -> 0 | S175: Monitors | T175: MON-7207 | U175: 41.84 | V175: =Table1[[#This Row],[UnitCost]]*(1+WhatIf!$B$3) -> 43.932 | W175: =U175*AI175 -> 1129.68 | X175: =Table1[[#This Row],[ScenarioRev]]-Table1[[#This Row],[ScenarioUnitCost]] -> 2004.18 | Y175: 86.2 | Z175: =Y175*AI175*(1-AD175) -> 1801.4076 | AA175: =Table1[[#This Row],[ScenarioQuanity]]*Table1[[#This Row],[UnitPrice]]*(1-Table1[[#This Row],[ScenarioDiscPct]]) -> 2048.112 | AB175: =Z175-W175 -> 671.7276 | AC175: =Table1[[#This Row],[ScenarioRev]] - Table1[[#This Row],[ScenarioCostOfGoods]] -> 43.932 | AD175: 0.226 | AE175: =MIN(Table1[[#This Row],[DiscountPct]], WhatIf!$B$2) -> 0.2 | AF175: =IF(Table1[[#This Row],[DiscountPct]]>0.2, 1, 0) -> 1 | AG175: =IF(Y175<=_xlfn.PERCENTILE.INC($Y:$Y,0.33),"Low", IF(D175<=_xlfn.PERCENTILE.INC($Y:$Y,0.66),"Medium", "High")) -> Low | AH175: =IF(Z175=0, 0, AB175/Z175) -> 0.3728904 | AI175: 27 | AJ175: =Table1[[#This Row],[Quantity]]*(1+WhatIf!$B$4) -> 29.7
... A185: ORD-2023-931633 | B185: 45060 | C185: 45068 | D185: =IF(C185<B185, B185+14, C185) -> 45068 | E185: =C185-B185 -> 8 | F185: =D185-B185 -> 8 | G185: =IF(Table1[[#This Row],[CorrectedLeadTimeDays]]<=7, 1, 0) -> 0 | H185: =TEXT(B185, "mmmm") -> May | I185: ="Q"&ROUNDUP(MONTH(B185)/3,0)&"-"&YEAR(B185) -> Q2-2023 | J185: =TEXT(K185, "yyyy-mm") -> 2023-01 | K185: =_xlfn.MINIFS($B:$B,$M:$M,M185) -> 44946 | L185: Africa | M185: Kenya | N185: Mombasa | O185: Small Business | P185: Distributor | Q185: F. Müller | R185: =DATEDIF(K185,B185,"m") -> 3 | S185: Printers | T185: PRN-9488 | U185: 432.01 | V185: =Table1[[#This Row],[UnitCost]]*(1+WhatIf!$B$3) -> 453.6105 | W185: =U185*AI185 -> 5184.12 | X185: =Table1[[#This Row],[ScenarioRev]]-Table1[[#This Row],[ScenarioUnitCost]] -> 11017.253 | Y185: 913.78 | Z185: =Y185*AI185*(1-AD185) -> 10428.057 | AA185: =Table1[[#This Row],[ScenarioQuanity]]*Table1[[#This Row],[UnitPrice]]*(1-Table1[[#This Row],[ScenarioDiscPct]]) -> 11470.863 | AB185: =Z185-W185 -> 5243.9374 | AC185: =Table1[[#This Row],[ScenarioRev]] - Table1[[#This Row],[ScenarioCostOfGoods]] -> 453.6105 | AD185: 0.049 | AE185: =MIN(Table1[[#This Row],[DiscountPct]], WhatIf!$B$2) -> 0.049 | AF185: =IF(Table1[[#This Row],[DiscountPct]]>0.2, 1, 0) -> 0 | AG185: =IF(Y185<=_xlfn.PERCENTILE.INC($Y:$Y,0.33),"Low", IF(D185<=_xlfn.PERCENTILE.INC($Y:$Y,0.66),"Medium", "High")) -> High | AH185: =IF(Z185=0, 0, AB185/Z185) -> 0.5028681 | AI185: 12 | AJ185: =Table1[[#This Row],[Quantity]]*(1+WhatIf!$B$4) -> 13.2
A186: ORD-2023-842820 | B186: 45189 | C186: 45197 | D186: =IF(C186<B186, B186+14, C186) -> 45197 | E186: =C186-B186 -> 8 | F186: =D186-B186 -> 8 | G186: =IF(Table1[[#This Row],[CorrectedLeadTimeDays]]<=7, 1, 0) -> 0 | H186: =TEXT(B186, "mmmm") -> September | I186: ="Q"&ROUNDUP(MONTH(B186)/3,0)&"-"&YEAR(B186) -> Q3-2023 | J186: =TEXT(K186, "yyyy-mm") -> 2023-01 | K186: =_xlfn.MINIFS($B:$B,$M:$M,M186) -> 44955 | L186: Asia | M186: India | O186: Corporate | Q186: B. Chen | R186: =DATEDIF(K186,B186,"m") -> 7 | S186: Accessories | T186: ACC-1375 | U186: 1362.06 | V186: =Table1[[#This Row],[UnitCost]]*(1+WhatIf!$B$3) -> 1430.163 | W186: =U186*AI186 -> 14982.66 | X186: =Table1[[#This Row],[ScenarioRev]]-Table1[[#This Row],[ScenarioUnitCost]] -> 33234.231 | Y186: 3398.37 | Z186: =Y186*AI186*(1-AD186) -> 31513.085 | AA186: =Table1[[#This Row],[ScenarioQuanity]]*Table1[[#This Row],[UnitPrice]]*(1-Table1[[#This Row],[ScenarioDiscPct]]) -> 34664.394 | AB186: =Z186-W186 -> 16530.425 | AC186: =Table1[[#This Row],[ScenarioRev]] - Table1[[#This Row],[ScenarioCostOfGoods]] -> 1430.163 | AD186: 0.157 | AE186: =MIN(Table1[[#This Row],[DiscountPct]], WhatIf!$B$2) -> 0.157 | AF186: =IF(Table1[[#This Row],[DiscountPct]]>0.2, 1, 0) -> 0 | AG186: =IF(Y186<=_xlfn.PERCENTILE.INC($Y:$Y,0.33),"Low", IF(D186<=_xlfn.PERCENTILE.INC($Y:$Y,0.66),"Medium", "High")) -> High | AH186: =IF(Z186=0, 0, AB186/Z186) -> 0.5245575 | AI186: 11 | AJ186: =Table1[[#This Row],[Quantity]]*(1+WhatIf!$B$4) -> 12.1
A187: ORD-2025-752845 | B187: 45746 | C187: 45754 | D187: =IF(C187<B187, B187+14, C187) -> 45754 | E187: =C187-B187 -> 8 | F187: =D187-B187 -> 8 | G187: =IF(Table1[[#This Row],[CorrectedLeadTimeDays]]<=7, 1, 0) -> 0 | H187: =TEXT(B187, "mmmm") -> March | I187: ="Q"&ROUNDUP(MONTH(B187)/3,0)&"-"&YEAR(B187) -> Q1-2025 | J187: =TEXT(K187, "yyyy-mm") -> 2023-01 | K187: =_xlfn.MINIFS($B:$B,$M:$M,M187) -> 44955 | L187: Americas | M187: Brazil | N187: São Paulo | O187: Non-Profit | P187: Direct | Q187: L. Okafor | R187: =DATEDIF(K187,B187,"m") -> 26 | S187: Printers | T187: PRN-8763 | U187: 71.62 | V187: =Table1[[#This Row],[UnitCost]]*(1+WhatIf!$B$3) -> 75.201 | W187: =U187*AI187 -> 787.82 | X187: =Table1[[#This Row],[ScenarioRev]]-Table1[[#This Row],[ScenarioUnitCost]] -> 1133.6408 | Y187: 118.37 | Z187: =Y187*AI187*(1-AD187) -> 1098.9471 | AA187: =Table1[[#This Row],[ScenarioQuanity]]*Table1[[#This Row],[UnitPrice]]*(1-Table1[[#This Row],[ScenarioDiscPct]]) -> 1208.8418 | AB187: =Z187-W187 -> 311.12708 | AC187: =Table1[[#This Row],[ScenarioRev]] - Table1[[#This Row],[ScenarioCostOfGoods]] -> 75.201 | AD187: 0.156 | AE187: =MIN(Table1[[#This Row],[DiscountPct]], WhatIf!$B$2) -> 0.156 | AF187: =IF(Table1[[#This Row],[DiscountPct]]>0.2, 1, 0) -> 0 | AG187: =IF(Y187<=_xlfn.PERCENTILE.INC($Y:$Y,0.33),"Low", IF(D187<=_xlfn.PERCENTILE.INC($Y:$Y,0.66),"Medium", "High")) -> Low | AH187: =IF(Z187=0, 0, AB187/Z187) -> 0.2831138 | AI187: 11 | AJ187: =Table1[[#This Row],[Quantity]]*(1+WhatIf!$B$4) -> 12.1
A188: ORD-2025-564184 | B188: 45686 | C188: 45694 | D188: =IF(C188<B188, B188+14, C188) -> 45694 | E188: =C188-B188 -> 8 | F188: =D188-B188 -> 8 | G188: =IF(Table1[[#This Row],[CorrectedLeadTimeDays]]<=7, 1, 0) -> 0 | H188: =TEXT(B188, "mmmm") -> January | I188: ="Q"&ROUNDUP(MONTH(B188)/3,0)&"-"&YEAR(B188) -> Q1-2025 | J188: =TEXT(K188, "yyyy-mm") -> 2023-01 | K188: =_xlfn.MINIFS($B:$B,$M:$M,M188) -> 44946 | L188: Africa | M188: Kenya | N188: Kisumu | O188: Education | P188: Retail | Q188: B. Chen | R188: =DATEDIF(K188,B188,"m") -> 24 | S188: Phones | T188: PHN-1671 | U188: 1445.27 | V188: =Table1[[#This Row],[UnitCost]]*(1+WhatIf!$B$3) -> 1517.5335 | W188: =U188*AI188 -> 13007.43 | X188: =Table1[[#This Row],[ScenarioRev]]-Table1[[#This Row],[ScenarioUnitCost]] -> 25127.821 | Y188: 2691.45 | Z188: =Y188*AI188*(1-AD188) -> 24223.05 | AA188: =Table1[[#This Row],[ScenarioQuanity]]*Table1[[#This Row],[UnitPrice]]*(1-Table1[[#This Row],[ScenarioDiscPct]]) -> 26645.355 | AB188: =Z188-W188 -> 11215.62 | AC188: =Table1[[#This Row],[ScenarioRev]] - Table1[[#This Row],[ScenarioCostOfGoods]] -> 1517.5335 | AD188: 0 | AE188: =MIN(Table1[[#This Row],[DiscountPct]], WhatIf!$B$2) -> 0 | AF188: =IF(Table1[[#This Row],[DiscountPct]]>0.2, 1, 0) -> 0 | AG188: =IF(Y188<=_xlfn.PERCENTILE.INC($Y:$Y,0.33),"Low", IF(D188<=_xlfn.PERCENTILE.INC($Y:$Y,0.66),"Medium", "High")) -> High | AH188: =IF(Z188=0, 0, AB188/Z188) -> 0.46301436 | AI188: 9 | AJ188: =Table1[[#This Row],[Quantity]]*(1+WhatIf!$B$4) -> 9.9
A189: ORD-2023-715175 | B189: 45092 | C189: 45100 | D189: =IF(C189<B189, B189+14, C189) -> 45100 | E189: =C189-B189 -> 8 | F189: =D189-B189 -> 8 | G189: =IF(Table1[[#This Row],[CorrectedLeadTimeDays]]<=7, 1, 0) -> 0 | H189: =TEXT(B189, "mmmm") -> June | I189: ="Q"&ROUNDUP(MONTH(B189)/3,0)&"-"&YEAR(B189) -> Q2-2023 | J189: =TEXT(K189, "yyyy-mm") -> 2023-01 | K189: =_xlfn.MINIFS($B:$B,$M:$M,M189) -> 44939 | L189: Americas | M189: USA | N189: San Francisco | O189: Consumer | P189: Distributor | Q189: O. Wang | R189: =DATEDIF(K189,B189,"m") -> 5 | S189: Monitors | T189: MON-5424 | U189: 1097.09 | V189: =Table1[[#This Row],[UnitCost]]*(1+WhatIf!$B$3) -> 1151.9445 | W189: =U189*AI189 -> 9873.81 | X189: =Table1[[#This Row],[ScenarioRev]]-Table1[[#This Row],[ScenarioUnitCost]] -> 18033.179 | Y189: 2182.31 | Z189: =Y189*AI189*(1-AD189) -> 17441.022 | AA189: =Table1[[#This Row],[ScenarioQuanity]]*Table1[[#This Row],[UnitPrice]]*(1-Table1[[#This Row],[ScenarioDiscPct]]) -> 19185.124 | AB189: =Z189-W189 -> 7567.2115 | AC189: =Table1[[#This Row],[ScenarioRev]] - Table1[[#This Row],[ScenarioCostOfGoods]] -> 1151.9445 | AD189: 0.112 | AE189: =MIN(Table1[[#This Row],[DiscountPct]], WhatIf!$B$2) -> 0.112 | AF189: =IF(Table1[[#This Row],[DiscountPct]]>0.2, 1, 0) -> 0 | AG189: =IF(Y189<=_xlfn.PERCENTILE.INC($Y:$Y,0.33),"Low", IF(D189<=_xlfn.PERCENTILE.INC($Y:$Y,0.66),"Medium", "High")) -> High | AH189: =IF(Z189=0, 0, AB189/Z189) -> 0.43387433 | AI189: 9 | AJ189: =Table1[[#This Row],[Quantity]]*(1+WhatIf!$B$4) -> 9.9
A190: ORD-2025-184754 | B190: 45835 | C190: 45843 | D190: =IF(C190<B190, B190+14, C190) -> 45843 | E190: =C190-B190 -> 8 | F190: =D190-B190 -> 8 | G190: =IF(Table1[[#This Row],[CorrectedLeadTimeDays]]<=7, 1, 0) -> 0 | H190: =TEXT(B190, "mmmm") -> June | I190: ="Q"&ROUNDUP(MONTH(B190)/3,0)&"-"&YEAR(B190) -> Q2-2025 | J190: =TEXT(K190, "yyyy-mm") -> 2023-01 | K190: =_xlfn.MINIFS($B:$B,$M:$M,M190) -> 44948 | L190: Europe | M190: Germany | N190: Munich | O190: Small Business | P190: Direct | Q190: G. Dubois | R190: =DATEDIF(K190,B190,"m") -> 29 | S190: Monitors | T190: MON-7626 | U190: 314.93 | V190: =Table1[[#This Row],[UnitCost]]*(1+WhatIf!$B$3) -> 330.6765 | W190: =U190*AI190 -> 2519.44 | X190: =Table1[[#This Row],[ScenarioRev]]-Table1[[#This Row],[ScenarioUnitCost]] -> 4512.4915 | Y190: 687.95 | Z190: =Y190*AI190*(1-AD190) -> 4375.362 | AA190: =Table1[[#This Row],[ScenarioQuanity]]*Table1[[#This Row],[UnitPrice]]*(1-Table1[[#This Row],[ScenarioDiscPct]]) -> 4843.168 | AB190: =Z190-W190 -> 1855.922 | AC190: =Table1[[#This Row],[ScenarioRev]] - Table1[[#This Row],[ScenarioCostOfGoods]] -> 330.6765 | AD190: 0.205 | AE190: =MIN(Table1[[#This Row],[DiscountPct]], WhatIf!$B$2) -> 0.2 | AF190: =IF(Table1[[#This Row],[DiscountPct]]>0.2, 1, 0) -> 1 | AG190: =IF(Y190<=_xlfn.PERCENTILE.INC($Y:$Y,0.33),"Low", IF(D190<=_xlfn.PERCENTILE.INC($Y:$Y,0.66),"Medium", "High")) -> Low | AH190: =IF(Z190=0, 0, AB190/Z190) -> 0.42417565 | AI190: 8 | AJ190: =Table1[[#This Row],[Quantity]]*(1+WhatIf!$B$4) -> 8.8
A191: ORD-2024-866535 | B191: 45630 | C191: 45638 | D191: =IF(C191<B191, B191+14, C191) -> 45638 | E191: =C191-B191 -> 8 | F191: =D191-B191 -> 8 | G191: =IF(Table1[[#This Row],[CorrectedLeadTimeDays]]<=7, 1, 0) -> 0 | H191: =TEXT(B191, "mmmm") -> December | I191: ="Q"&ROUNDUP(MONTH(B191)/3,0)&"-"&YEAR(B191) -> Q4-2024 | J191: =TEXT(K191, "yyyy-mm") -> 2023-01 | K191: =_xlfn.MINIFS($B:$B,$M:$M,M191) -> 44948 | L191: Europe | M191: Germany | N191: Frankfurt | O191: Enterprise | P191: Marketplace | Q191: B. Chen | R191: =DATEDIF(K191,B191,"m") -> 22 | S191: Printers | T191: PRN-5492 | U191: 72.06 | V191: =Table1[[#This Row],[UnitCost]]*(1+WhatIf!$B$3) -> 75.663 | W191: =U191*AI191 -> 576.48 | X191: =Table1[[#This Row],[ScenarioRev]]-Table1[[#This Row],[ScenarioUnitCost]] -> 788.4266 | Y191: 122.74 | Z191: =Y191*AI191*(1-AD191) -> 748.22304 | AA191: =Table1[[#This Row],[ScenarioQuanity]]*Table1[[#This Row],[UnitPrice]]*(1-Table1[[#This Row],[ScenarioDiscPct]]) -> 864.0896 | AB191: =Z191-W191 -> 171.74304 | AC191: =Table1[[#This Row],[ScenarioRev]] - Table1[[#This Row],[ScenarioCostOfGoods]] -> 75.663 | AD191: 0.238 | AE191: =MIN(Table1[[#This Row],[DiscountPct]], WhatIf!$B$2) -> 0.2 | AF191: =IF(Table1[[#This Row],[DiscountPct]]>0.2, 1, 0) -> 1 | AG191: =IF(Y191<=_xlfn.PERCENTILE.INC($Y:$Y,0.33),"Low", IF(D191<=_xlfn.PERCENTILE.INC($Y:$Y,0.66),"Medium", "High")) -> Low | AH191: =IF(Z191=0, 0, AB191/Z191) -> 0.22953455 | AI191: 8 | AJ191: =Table1[[#This Row],[Quantity]]*(1+WhatIf!$B$4) -> 8.8
A192: ORD-2023-813340 | B192: 45286 | C192: 45294 | D192: =IF(C192<B192, B192+14, C192) -> 45294 | E192: =C192-B192 -> 8 | F192: =D192-B192 -> 8 | G192: =IF(Table1[[#This Row],[CorrectedLeadTimeDays]]<=7, 1, 0) -> 0 | H192: =TEXT(B192, "mmmm") -> December | I192: ="Q"&ROUNDUP(MONTH(B192)/3,0)&"-"&YEAR(B192) -> Q4-2023 | J192: =TEXT(K192, "yyyy-mm") -> 2023-01 | K192: =_xlfn.MINIFS($B:$B,$M:$M,M192) -> 44936 | L192: Europe | M192: France | N192: Lyon | O192: Small Business | P192: Retail | Q192: M. Rossi | R192: =DATEDIF(K192,B192,"m") -> 11 | S192: Laptops | T192: LAP-2942 | U192: 492.75 | V192: =Table1[[#This Row],[UnitCost]]*(1+WhatIf!$B$3) -> 517.3875 | W192: =U192*AI192 -> 2956.5 | X192: =Table1[[#This Row],[ScenarioRev]]-Table1[[#This Row],[ScenarioUnitCost]] -> 4029.1887 | Y192: 731.29 | Z192: =Y192*AI192*(1-AD192) -> 4133.2511 | AA192: =Table1[[#This Row],[ScenarioQuanity]]*Table1[[#This Row],[UnitPrice]]*(1-Table1[[#This Row],[ScenarioDiscPct]]) -> 4546.5762 | AB192: =Z192-W192 -> 1176.7511 | AC192: =Table1[[#This Row],[ScenarioRev]] - Table1[[#This Row],[ScenarioCostOfGoods]] -> 517.3875 | AD192: 0.058 | AE192: =MIN(Table1[[#This Row],[DiscountPct]], WhatIf!$B$2) -> 0.058 | AF192: =IF(Table1[[#This Row],[DiscountPct]]>0.2, 1, 0) -> 0 | AG192: =IF(Y192<=_xlfn.PERCENTILE.INC($Y:$Y,0.33),"Low", IF(D192<=_xlfn.PERCENTILE.INC($Y:$Y,0.66),"Medium", "High")) -> Low | AH192: =IF(Z192=0, 0, AB192/Z192) -> 0.28470351 | AI192: 6 | AJ192: =Table1[[#This Row],[Quantity]]*(1+WhatIf!$B$4) -> 6.6
A193: ORD-2023-536542 | B193: 45087 | C193: 45095 | D193: =IF(C193<B193, B193+14, C193) -> 45095 | E193: =C193-B193 -> 8 | F193: =D193-B193 -> 8 | G193: =IF(Table1[[#This Row],[CorrectedLeadTimeDays]]<=7, 1, 0) -> 0 | H193: =TEXT(B193, "mmmm") -> June | I193: ="Q"&ROUNDUP(MONTH(B193)/3,0)&"-"&YEAR(B193) -> Q2-2023 | J193: =TEXT(K193, "yyyy-mm") -> 2023-01 | K193: =_xlfn.MINIFS($B:$B,$M:$M,M193) -> 44946 | L193: Africa | M193: Kenya | N193: Nakuru | O193: Enterprise | P193: Direct | Q193: H. Kim | R193: =DATEDIF(K193,B193,"m") -> 4 | S193: Phones | T193: PHN-2337 | U193: 894.23 | V193: =Table1[[#This Row],[UnitCost]]*(1+WhatIf!$B$3) -> 938.9415 | W193: =U193*AI193 -> 2682.69 | X193: =Table1[[#This Row],[ScenarioRev]]-Table1[[#This Row],[ScenarioUnitCost]] -> 3240.842 | Y193: 1421.55 | Z193: =Y193*AI193*(1-AD193) -> 3799.8031 | AA193: =Table1[[#This Row],[ScenarioQuanity]]*Table1[[#This Row],[UnitPrice]]*(1-Table1[[#This Row],[ScenarioDiscPct]]) -> 4179.7835 | AB193: =Z193-W193 -> 1117.1131 | AC193: =Table1[[#This Row],[ScenarioRev]] - Table1[[#This Row],[ScenarioCostOfGoods]] -> 938.9415 | AD193: 0.109 | AE193: =MIN(Table1[[#This Row],[DiscountPct]], WhatIf!$B$2) -> 0.109 | AF193: =IF(Table1[[#This Row],[DiscountPct]]>0.2, 1, 0) -> 0 | AG193: =IF(Y193<=_xlfn.PERCENTILE.INC($Y:$Y,0.33),"Low", IF(D193<=_xlfn.PERCENTILE.INC($Y:$Y,0.66),"Medium", "High")) -> High | AH193: =IF(Z193=0, 0, AB193/Z193) -> 0.29399237 | AI193: 3 | AJ193: =Table1[[#This Row],[Quantity]]*(1+WhatIf!$B$4) -> 3.3
A194: ORD-2025-639542 | B194: 45817 | C194: 45826 | D194: =IF(C194<B194, B194+14, C194) -> 45826 | E194: =C194-B194 -> 9 | F194: =D194-B194 -> 9 | G194: =IF(Table1[[#This Row],[CorrectedLeadTimeDays]]<=7, 1, 0) -> 0 | H194: =TEXT(B194, "mmmm") -> June | I194: ="Q"&ROUNDUP(MONTH(B194)/3,0)&"-"&YEAR(B194) -> Q2-2025 | J194: =TEXT(K194, "yyyy-mm") -> 2023-01 | K194: =_xlfn.MINIFS($B:$B,$M:$M,M194) -> 44936 | L194: Europe | M194: France | N194: Marseille | O194: Small Business | P194: Marketplace | Q194: H. Kim | R194: =DATEDIF(K194,B194,"m") -> 28 | S194: Accessories | T194: ACC-1770 | U194: 1225.5 | V194: =Table1[[#This Row],[UnitCost]]*(1+WhatIf!$B$3) -> 1286.775 | W194: =U194*AI194 -> 68628 | X194: =Table1[[#This Row],[ScenarioRev]]-Table1[[#This Row],[ScenarioUnitCost]] -> -986.4904 | Y194: 5.27 | Z194: =Y194*AI194*(1-AD194) -> 272.986 | AA194: =Table1[[#This Row],[ScenarioQuanity]]*Table1[[#This Row],[UnitPrice]]*(1-Table1[[#This Row],[ScenarioDiscPct]]) -> 300.2846 | AB194: =Z194-W194 -> -68355.014 | AC194: =Table1[[#This Row],[ScenarioRev]] - Table1[[#This Row],[ScenarioCostOfGoods]] -> 1286.775 | AD194: 0.075 | AE194: =MIN(Table1[[#This Row],[DiscountPct]], WhatIf!$B$2) -> 0.075 | AF194: =IF(Table1[[#This Row],[DiscountPct]]>0.2, 1, 0) -> 0 | AG194: =IF(Y194<=_xlfn.PERCENTILE.INC($Y:$Y,0.33),"Low", IF(D194<=_xlfn.PERCENTILE.INC($Y:$Y,0.66),"Medium", "High")) -> Low | AH194: =IF(Z194=0, 0, AB194/Z194) -> -250.39751 | AI194: 56 | AJ194: =Table1[[#This Row],[Quantity]]*(1+WhatIf!$B$4) -> 61.6
A195: ORD-2023-309373 | B195: 45112 | C195: 45121 | D195: =IF(C195<B195, B195+14, C195) -> 45121 | E195: =C195-B195 -> 9 | F195: =D195-B195 -> 9 | G195: =IF(Table1[[#This Row],[CorrectedLeadTimeDays]]<=7, 1, 0) -> 0 | H195: =TEXT(B195, "mmmm") -> July | I195: ="Q"&ROUNDUP(MONTH(B195)/3,0)&"-"&YEAR(B195) -> Q3-2023 | J195: =TEXT(K195, "yyyy-mm") -> 2023-01 | K195: =_xlfn.MINIFS($B:$B,$M:$M,M195) -> 44955 | L195: Americas | M195: Brazil | N195: Brasília | O195: Enterprise | P195: Direct | Q195: B. Chen | R195: =DATEDIF(K195,B195,"m") -> 5 | S195: Networking | T195: NET-2394 | U195: 578.85 | V195: =Table1[[#This Row],[UnitCost]]*(1+WhatIf!$B$3) -> 607.7925 | W195: =U195*AI195 -> 16207.8 | X195: =Table1[[#This Row],[ScenarioRev]]-Table1[[#This Row],[ScenarioUnitCost]] -> 27631.547 | Y195: 998.76 | Z195: =Y195*AI195*(1-AD195) -> 25672.127 | AA195: =Table1[[#This Row],[ScenarioQuanity]]*Table1[[#This Row],[UnitPrice]]*(1-Table1[[#This Row],[ScenarioDiscPct]]) -> 28239.34 | AB195: =Z195-W195 -> 9464.327 | AC195: =Table1[[#This Row],[ScenarioRev]] - Table1[[#This Row],[ScenarioCostOfGoods]] -> 607.7925 | AD195: 0.082 | AE195: =MIN(Table1[[#This Row],[DiscountPct]], WhatIf!$B$2) -> 0.082 | AF195: =IF(Table1[[#This Row],[DiscountPct]]>0.2, 1, 0) -> 0 | AG195: =IF(Y195<=_xlfn.PERCENTILE.INC($Y:$Y,0.33),"Low", IF(D195<=_xlfn.PERCENTILE.INC($Y:$Y,0.66),"Medium", "High")) -> High | AH195: =IF(Z195=0, 0, AB195/Z195) -> 0.36866158 | AI195: 28 | AJ195: =Table1[[#This Row],[Quantity]]*(1+WhatIf!$B$4) -> 30.8
A196: ORD-2023-808024 | B196: 45290 | C196: 45299 | D196: =IF(C196<B196, B196+14, C196) -> 45299 | E196: =C196-B196 -> 9 | F196: =D196-B196 -> 9 | G196: =IF(Table1[[#This Row],[CorrectedLeadTimeDays]]<=7, 1, 0) -> 0 | H196: =TEXT(B196, "mmmm") -> December | I196: ="Q"&ROUNDUP(MONTH(B196)/3,0)&"-"&YEAR(B196) -> Q4-2023 | J196: =TEXT(K196, "yyyy-mm") -> 2023-01 | K196: =_xlfn.MINIFS($B:$B,$M:$M,M196) -> 44936 | L196: Europe | M196: France | N196: Marseille | O196: Consumer | P196: Marketplace | Q196: L. Okafor | R196: =DATEDIF(K196,B196,"m") -> 11 | S196: Accessories | T196: ACC-6594 | U196: 861.1 | V196: =Table1[[#This Row],[UnitCost]]*(1+WhatIf!$B$3) -> 904.155 | W196: =U196*AI196 -> 20666.4 | X196: =Table1[[#This Row],[ScenarioRev]]-Table1[[#This Row],[ScenarioUnitCost]] -> 25802.579 | Y196: 1224.72 | Z196: =Y196*AI196*(1-AD196) -> 24278.849 | AA196: =Table1[[#This Row],[ScenarioQuanity]]*Table1[[#This Row],[UnitPrice]]*(1-Table1[[#This Row],[ScenarioDiscPct]]) -> 26706.734 | AB196: =Z196-W196 -> 3612.4493 | AC196: =Table1[[#This Row],[ScenarioRev]] - Table1[[#This Row],[ScenarioCostOfGoods]] -> 904.155 | AD196: 0.174 | AE196: =MIN(Table1[[#This Row],[DiscountPct]], WhatIf!$B$2) -> 0.174 | AF196: =IF(Table1[[#This Row],[DiscountPct]]>0.2, 1, 0) -> 0 | AG196: =IF(Y196<=_xlfn.PERCENTILE.INC($Y:$Y,0.33),"Low", IF(D196<=_xlfn.PERCENTILE.INC($Y:$Y,0.66),"Medium", "High")) -> High | AH196: =IF(Z196=0, 0, AB196/Z196) -> 0.14878997 | AI196: 24 | AJ196: =Table1[[#This Row],[Quantity]]*(1+WhatIf!$B$4) -> 26.4
A197: ORD-2025-537785 | B197: 45874 | C197: 45883 | D197: =IF(C197<B197, B197+14, C197) -> 45883 | E197: =C197-B197 -> 9 | F197: =D197-B197 -> 9 | G197: =IF(Table1[[#This Row],[CorrectedLeadTimeDays]]<=7, 1, 0) -> 0 | H197: =TEXT(B197, "mmmm") -> August | I197: ="Q"&ROUNDUP(MONTH(B197)/3,0)&"-"&YEAR(B197) -> Q3-2025 | J197: =TEXT(K197, "yyyy-mm") -> 2023-01 | K197: =_xlfn.MINIFS($B:$B,$M:$M,M197) -> 44945 | L197: Europe | M197: United Kingdom | N197: London | O197: Non-Profit | P197: Direct | Q197: E. Garcia | R197: =DATEDIF(K197,B197,"m") -> 30 | S197: Components | T197: CMP-6346 | U197: 41.76 | V197: =Table1[[#This Row],[UnitCost]]*(1+WhatIf!$B$3) -> 43.848 | W197: =U197*AI197 -> 960.48 | X197: =Table1[[#This Row],[ScenarioRev]]-Table1[[#This Row],[ScenarioUnitCost]] -> 894.80705 | Y197: 45.19 | Z197: =Y197*AI197*(1-AD197) -> 853.32277 | AA197: =Table1[[#This Row],[ScenarioQuanity]]*Table1[[#This Row],[UnitPrice]]*(1-Table1[[#This Row],[ScenarioDiscPct]]) -> 938.65505 | AB197: =Z197-W197 -> -107.15723 | AC197: =Table1[[#This Row],[ScenarioRev]] - Table1[[#This Row],[ScenarioCostOfGoods]] -> 43.848 | AD197: 0.179 | AE197: =MIN(Table1[[#This Row],[DiscountPct]], WhatIf!$B$2) -> 0.179 | AF197: =IF(Table1[[#This Row],[DiscountPct]]>0.2, 1, 0) -> 0 | AG197: =IF(Y197<=_xlfn.PERCENTILE.INC($Y:$Y,0.33),"Low", IF(D197<=_xlfn.PERCENTILE.INC($Y:$Y,0.66),"Medium", "High")) -> Low | AH197: =IF(Z197=0, 0, AB197/Z197) -> -0.12557643 | AI197: 23 | AJ197: =Table1[[#This Row],[Quantity]]*(1+WhatIf!$B$4) -> 25.3
A198: ORD-2024-851883 | B198: 45304 | C198: 45313 | D198: =IF(C198<B198, B198+14, C198) -> 45313 | E198: =C198-B198 -> 9 | F198: =D198-B198 -> 9 | G198: =IF(Table1[[#This Row],[CorrectedLeadTimeDays]]<=7, 1, 0) -> 0 | H198: =TEXT(B198, "mmmm") -> January | I198: ="Q"&ROUNDUP(MONTH(B198)/3,0)&"-"&YEAR(B198) -> Q1-2024 | J198: =TEXT(K198, "yyyy-mm") -> 2023-01 | K198: =_xlfn.MINIFS($B:$B,$M:$M,M198) -> 44955 | L198: Asia | M198: India | N198: Mumbai | O198: Enterprise | P198: Marketplace | Q198: J. Njeri | R198: =DATEDIF(K198,B198,"m") -> 11 | S198: Components | T198: CMP-8141 | U198: 313.6 | V198: =Table1[[#This Row],[UnitCost]]*(1+WhatIf!$B$3) -> 329.28 | W198: =U198*AI198 -> 6899.2 | X198: =Table1[[#This Row],[ScenarioRev]]-Table1[[#This Row],[ScenarioUnitCost]] -> 6627.7554 | Y198: 334.28 | Z198: =Y198*AI198*(1-AD198) -> 6324.5776 | AA198: =Table1[[#This Row],[ScenarioQuanity]]*Table1[[#This Row],[UnitPrice]]*(1-Table1[[#This Row],[ScenarioDiscPct]]) -> 6957.0354 | AB198: =Z198-W198 -> -574.6224 | AC198: =Table1[[#This Row],[ScenarioRev]] - Table1[[#This Row],[ScenarioCostOfGoods]] -> 329.28 | AD198: 0.14 | AE198: =MIN(Table1[[#This Row],[DiscountPct]], WhatIf!$B$2) -> 0.14 | AF198: =IF(Table1[[#This Row],[DiscountPct]]>0.2, 1, 0) -> 0 | AG198: =IF(Y198<=_xlfn.PERCENTILE.INC($Y:$Y,0.33),"Low", IF(D198<=_xlfn.PERCENTILE.INC($Y:$Y,0.66),"Medium", "High")) -> Low | AH198: =IF(Z198=0, 0, AB198/Z198) -> -0.090855459 | AI198: 22 | AJ198: =Table1[[#This Row],[Quantity]]*(1+WhatIf!$B$4) -> 24.2
... A205: ORD-2025-541048 | B205: 45751 | C205: 45760 | D205: =IF(C205<B205, B205+14, C205) -> 45760 | E205: =C205-B205 -> 9 | F205: =D205-B205 -> 9 | G205: =IF(Table1[[#This Row],[CorrectedLeadTimeDays]]<=7, 1, 0) -> 0 | H205: =TEXT(B205, "mmmm") -> April | I205: ="Q"&ROUNDUP(MONTH(B205)/3,0)&"-"&YEAR(B205) -> Q2-2025 | J205: =TEXT(K205, "yyyy-mm") -> 2023-01 | K205: =_xlfn.MINIFS($B:$B,$M:$M,M205) -> 44948 | L205: Europe | M205: Germany | N205: Munich | O205: Consumer | P205: Marketplace | Q205: F. Müller | R205: =DATEDIF(K205,B205,"m") -> 26 | S205: Phones | T205: PHN-3803 | U205: 7.02 | V205: =Table1[[#This Row],[UnitCost]]*(1+WhatIf!$B$3) -> 7.371 | W205: =U205*AI205 -> 98.28 | X205: =Table1[[#This Row],[ScenarioRev]]-Table1[[#This Row],[ScenarioUnitCost]] -> 76.381592 | Y205: 6.28 | Z205: =Y205*AI205*(1-AD205) -> 76.13872 | AA205: =Table1[[#This Row],[ScenarioQuanity]]*Table1[[#This Row],[UnitPrice]]*(1-Table1[[#This Row],[ScenarioDiscPct]]) -> 83.752592 | AB205: =Z205-W205 -> -22.14128 | AC205: =Table1[[#This Row],[ScenarioRev]] - Table1[[#This Row],[ScenarioCostOfGoods]] -> 7.371 | AD205: 0.134 | AE205: =MIN(Table1[[#This Row],[DiscountPct]], WhatIf!$B$2) -> 0.134 | AF205: =IF(Table1[[#This Row],[DiscountPct]]>0.2, 1, 0) -> 0 | AG205: =IF(Y205<=_xlfn.PERCENTILE.INC($Y:$Y,0.33),"Low", IF(D205<=_xlfn.PERCENTILE.INC($Y:$Y,0.66),"Medium", "High")) -> Low | AH205: =IF(Z205=0, 0, AB205/Z205) -> -0.29080184 | AI205: 14 | AJ205: =Table1[[#This Row],[Quantity]]*(1+WhatIf!$B$4) -> 15.4
A206: ORD-2025-306251 | B206: 45757 | C206: 45766 | D206: =IF(C206<B206, B206+14, C206) -> 45766 | E206: =C206-B206 -> 9 | F206: =D206-B206 -> 9 | G206: =IF(Table1[[#This Row],[CorrectedLeadTimeDays]]<=7, 1, 0) -> 0 | H206: =TEXT(B206, "mmmm") -> April | I206: ="Q"&ROUNDUP(MONTH(B206)/3,0)&"-"&YEAR(B206) -> Q2-2025 | J206: =TEXT(K206, "yyyy-mm") -> 2023-01 | K206: =_xlfn.MINIFS($B:$B,$M:$M,M206) -> 44933 | L206: Africa | M206: South Africa | N206: Durban | O206: Enterprise | Q206: G. Dubois | R206: =DATEDIF(K206,B206,"m") -> 27 | S206: Networking | T206: NET-5270 | U206: 113.74 | V206: =Table1[[#This Row],[UnitCost]]*(1+WhatIf!$B$3) -> 119.427 | W206: =U206*AI206 -> 1478.62 | X206: =Table1[[#This Row],[ScenarioRev]]-Table1[[#This Row],[ScenarioUnitCost]] -> 1956.2638 | Y206: 165.7 | Z206: =Y206*AI206*(1-AD206) -> 1886.9916 | AA206: =Table1[[#This Row],[ScenarioQuanity]]*Table1[[#This Row],[UnitPrice]]*(1-Table1[[#This Row],[ScenarioDiscPct]]) -> 2075.6908 | AB206: =Z206-W206 -> 408.3716 | AC206: =Table1[[#This Row],[ScenarioRev]] - Table1[[#This Row],[ScenarioCostOfGoods]] -> 119.427 | AD206: 0.124 | AE206: =MIN(Table1[[#This Row],[DiscountPct]], WhatIf!$B$2) -> 0.124 | AF206: =IF(Table1[[#This Row],[DiscountPct]]>0.2, 1, 0) -> 0 | AG206: =IF(Y206<=_xlfn.PERCENTILE.INC($Y:$Y,0.33),"Low", IF(D206<=_xlfn.PERCENTILE.INC($Y:$Y,0.66),"Medium", "High")) -> Low | AH206: =IF(Z206=0, 0, AB206/Z206) -> 0.21641411 | AI206: 13 | AJ206: =Table1[[#This Row],[Quantity]]*(1+WhatIf!$B$4) -> 14.3
A207: ORD-2023-390998 | B207: 45035 | C207: 45044 | D207: =IF(C207<B207, B207+14, C207) -> 45044 | E207: =C207-B207 -> 9 | F207: =D207-B207 -> 9 | G207: =IF(Table1[[#This Row],[CorrectedLeadTimeDays]]<=7, 1, 0) -> 0 | H207: =TEXT(B207, "mmmm") -> April | I207: ="Q"&ROUNDUP(MONTH(B207)/3,0)&"-"&YEAR(B207) -> Q2-2023 | J207: =TEXT(K207, "yyyy-mm") -> 2023-01 | K207: =_xlfn.MINIFS($B:$B,$M:$M,M207) -> 44948 | L207: Europe | M207: Germany | N207: Berlin | O207: Education | P207: Online | Q207: E. Garcia | R207: =DATEDIF(K207,B207,"m") -> 2 | S207: Monitors | T207: MON-1663 | U207: 1178.42 | V207: =Table1[[#This Row],[UnitCost]]*(1+WhatIf!$B$3) -> 1237.341 | W207: =U207*AI207 -> 12962.62 | X207: =Table1[[#This Row],[ScenarioRev]]-Table1[[#This Row],[ScenarioUnitCost]] -> 27507.537 | Y207: 2446.56 | Z207: =Y207*AI207*(1-AD207) -> 26131.707 | AA207: =Table1[[#This Row],[ScenarioQuanity]]*Table1[[#This Row],[UnitPrice]]*(1-Table1[[#This Row],[ScenarioDiscPct]]) -> 28744.878 | AB207: =Z207-W207 -> 13169.087 | AC207: =Table1[[#This Row],[ScenarioRev]] - Table1[[#This Row],[ScenarioCostOfGoods]] -> 1237.341 | AD207: 0.029 | AE207: =MIN(Table1[[#This Row],[DiscountPct]], WhatIf!$B$2) -> 0.029 | AF207: =IF(Table1[[#This Row],[DiscountPct]]>0.2, 1, 0) -> 0 | AG207: =IF(Y207<=_xlfn.PERCENTILE.INC($Y:$Y,0.33),"Low", IF(D207<=_xlfn.PERCENTILE.INC($Y:$Y,0.66),"Medium", "High")) -> High | AH207: =IF(Z207=0, 0, AB207/Z207) -> 0.50395051 | AI207: 11 | AJ207: =Table1[[#This Row],[Quantity]]*(1+WhatIf!$B$4) -> 12.1
A208: ORD-2025-411385 | B208: 45813 | C208: 45822 | D208: =IF(C208<B208, B208+14, C208) -> 45822 | E208: =C208-B208 -> 9 | F208: =D208-B208 -> 9 | G208: =IF(Table1[[#This Row],[CorrectedLeadTimeDays]]<=7, 1, 0) -> 0 | H208: =TEXT(B208, "mmmm") -> June | I208: ="Q"&ROUNDUP(MONTH(B208)/3,0)&"-"&YEAR(B208) -> Q2-2025 | J208: =TEXT(K208, "yyyy-mm") -> 2023-01 | K208: =_xlfn.MINIFS($B:$B,$M:$M,M208) -> 44955 | L208: Asia | M208: India | N208: Delhi | O208: Non-Profit | P208: Retail | Q208: A. Patel | R208: =DATEDIF(K208,B208,"m") -> 28 | S208: Accessories | T208: ACC-2902 | U208: 618.69 | V208: =Table1[[#This Row],[UnitCost]]*(1+WhatIf!$B$3) -> 649.6245 | W208: =U208*AI208 -> 6805.59 | X208: =Table1[[#This Row],[ScenarioRev]]-Table1[[#This Row],[ScenarioUnitCost]] -> 8116.7832 | Y208: 796.15 | Z208: =Y208*AI208*(1-AD208) -> 7969.4615 | AA208: =Table1[[#This Row],[ScenarioQuanity]]*Table1[[#This Row],[UnitPrice]]*(1-Table1[[#This Row],[ScenarioDiscPct]]) -> 8766.4077 | AB208: =Z208-W208 -> 1163.8715 | AC208: =Table1[[#This Row],[ScenarioRev]] - Table1[[#This Row],[ScenarioCostOfGoods]] -> 649.6245 | AD208: 0.09 | AE208: =MIN(Table1[[#This Row],[DiscountPct]], WhatIf!$B$2) -> 0.09 | AF208: =IF(Table1[[#This Row],[DiscountPct]]>0.2, 1, 0) -> 0 | AG208: =IF(Y208<=_xlfn.PERCENTILE.INC($Y:$Y,0.33),"Low", IF(D208<=_xlfn.PERCENTILE.INC($Y:$Y,0.66),"Medium", "High")) -> Low | AH208: =IF(Z208=0, 0, AB208/Z208) -> 0.14604142 | AI208: 11 | AJ208: =Table1[[#This Row],[Quantity]]*(1+WhatIf!$B$4) -> 12.1
A209: ORD-2023-964434 | B209: 45258 | C209: 45267 | D209: =IF(C209<B209, B209+14, C209) -> 45267 | E209: =C209-B209 -> 9 | F209: =D209-B209 -> 9 | G209: =IF(Table1[[#This Row],[CorrectedLeadTimeDays]]<=7, 1, 0) -> 0 | H209: =TEXT(B209, "mmmm") -> November | I209: ="Q"&ROUNDUP(MONTH(B209)/3,0)&"-"&YEAR(B209) -> Q4-2023 | J209: =TEXT(K209, "yyyy-mm") -> 2023-01 | K209: =_xlfn.MINIFS($B:$B,$M:$M,M209) -> 44955 | L209: Asia | M209: India | N209: Delhi | O209: Enterprise | P209: Marketplace | Q209: L. Okafor | R209: =DATEDIF(K209,B209,"m") -> 9 | S209: Phones | T209: PHN-2447 | U209: 699.33 | V209: =Table1[[#This Row],[UnitCost]]*(1+WhatIf!$B$3) -> 734.2965 | W209: =U209*AI209 -> 6993.3 | X209: =Table1[[#This Row],[ScenarioRev]]-Table1[[#This Row],[ScenarioUnitCost]] -> 6954.7035 | Y209: 873.75 | Z209: =Y209*AI209*(1-AD209) -> 6684.1875 | AA209: =Table1[[#This Row],[ScenarioQuanity]]*Table1[[#This Row],[UnitPrice]]*(1-Table1[[#This Row],[ScenarioDiscPct]]) -> 7689 | AB209: =Z209-W209 -> -309.1125 | AC209: =Table1[[#This Row],[ScenarioRev]] - Table1[[#This Row],[ScenarioCostOfGoods]] -> 734.2965 | AD209: 0.235 | AE209: =MIN(Table1[[#This Row],[DiscountPct]], WhatIf!$B$2) -> 0.2 | AF209: =IF(Table1[[#This Row],[DiscountPct]]>0.2, 1, 0) -> 1 | AG209: =IF(Y209<=_xlfn.PERCENTILE.INC($Y:$Y,0.33),"Low", IF(D209<=_xlfn.PERCENTILE.INC($Y:$Y,0.66),"Medium", "High")) -> High | AH209: =IF(Z209=0, 0, AB209/Z209) -> -0.046245336 | AI209: 10 | AJ209: =Table1[[#This Row],[Quantity]]*(1+WhatIf!$B$4) -> 11
A210: ORD-2024-332076 | B210: 45391 | C210: 45400 | D210: =IF(C210<B210, B210+14, C210) -> 45400 | E210: =C210-B210 -> 9 | F210: =D210-B210 -> 9 | G210: =IF(Table1[[#This Row],[CorrectedLeadTimeDays]]<=7, 1, 0) -> 0 | H210: =TEXT(B210, "mmmm") -> April | I210: ="Q"&ROUNDUP(MONTH(B210)/3,0)&"-"&YEAR(B210) -> Q2-2024 | J210: =TEXT(K210, "yyyy-mm") -> 2023-01 | K210: =_xlfn.MINIFS($B:$B,$M:$M,M210) -> 44936 | L210: Europe | M210: France | N210: Lyon | O210: Consumer | P210: Online | Q210: E. Garcia | R210: =DATEDIF(K210,B210,"m") -> 14 | S210: Printers | T210: PRN-1086 | U210: 1288.85 | V210: =Table1[[#This Row],[UnitCost]]*(1+WhatIf!$B$3) -> 1353.2925 | W210: =U210*AI210 -> 9021.95 | X210: =Table1[[#This Row],[ScenarioRev]]-Table1[[#This Row],[ScenarioUnitCost]] -> 16487.987 | Y210: 2751.84 | Z210: =Y210*AI210*(1-AD210) -> 16219.345 | AA210: =Table1[[#This Row],[ScenarioQuanity]]*Table1[[#This Row],[UnitPrice]]*(1-Table1[[#This Row],[ScenarioDiscPct]]) -> 17841.279 | AB210: =Z210-W210 -> 7197.395 | AC210: =Table1[[#This Row],[ScenarioRev]] - Table1[[#This Row],[ScenarioCostOfGoods]] -> 1353.2925 | AD210: 0.158 | AE210: =MIN(Table1[[#This Row],[DiscountPct]], WhatIf!$B$2) -> 0.158 | AF210: =IF(Table1[[#This Row],[DiscountPct]]>0.2, 1, 0) -> 0 | AG210: =IF(Y210<=_xlfn.PERCENTILE.INC($Y:$Y,0.33),"Low", IF(D210<=_xlfn.PERCENTILE.INC($Y:$Y,0.66),"Medium", "High")) -> High | AH210: =IF(Z210=0, 0, AB210/Z210) -> 0.44375374 | AI210: 7 | AJ210: =Table1[[#This Row],[Quantity]]*(1+WhatIf!$B$4) -> 7.7
A211: ORD-2025-956101 | B211: 45847 | C211: 45856 | D211: =IF(C211<B211, B211+14, C211) -> 45856 | E211: =C211-B211 -> 9 | F211: =D211-B211 -> 9 | G211: =IF(Table1[[#This Row],[CorrectedLeadTimeDays]]<=7, 1, 0) -> 0 | H211: =TEXT(B211, "mmmm") -> July | I211: ="Q"&ROUNDUP(MONTH(B211)/3,0)&"-"&YEAR(B211) -> Q3-2025 | J211: =TEXT(K211, "yyyy-mm") -> 2023-01 | K211: =_xlfn.MINIFS($B:$B,$M:$M,M211) -> 44928 | L211: Americas | M211: Canada | N211: Vancouver | O211: Education | P211: Distributor | Q211: I. Johnson | R211: =DATEDIF(K211,B211,"m") -> 30 | S211: Laptops | T211: LAP-2218 | U211: 57.96 | V211: =Table1[[#This Row],[UnitCost]]*(1+WhatIf!$B$3) -> 60.858 | W211: =U211*AI211 -> 405.72 | X211: =Table1[[#This Row],[ScenarioRev]]-Table1[[#This Row],[ScenarioUnitCost]] -> 591.36334 | Y211: 88.51 | Z211: =Y211*AI211*(1-AD211) -> 592.92849 | AA211: =Table1[[#This Row],[ScenarioQuanity]]*Table1[[#This Row],[UnitPrice]]*(1-Table1[[#This Row],[ScenarioDiscPct]]) -> 652.22134 | AB211: =Z211-W211 -> 187.20849 | AC211: =Table1[[#This Row],[ScenarioRev]] - Table1[[#This Row],[ScenarioCostOfGoods]] -> 60.858 | AD211: 0.043 | AE211: =MIN(Table1[[#This Row],[DiscountPct]], WhatIf!$B$2) -> 0.043 | AF211: =IF(Table1[[#This Row],[DiscountPct]]>0.2, 1, 0) -> 0 | AG211: =IF(Y211<=_xlfn.PERCENTILE.INC($Y:$Y,0.33),"Low", IF(D211<=_xlfn.PERCENTILE.INC($Y:$Y,0.66),"Medium", "High")) -> Low | AH211: =IF(Z211=0, 0, AB211/Z211) -> 0.31573536 | AI211: 7 | AJ211: =Table1[[#This Row],[Quantity]]*(1+WhatIf!$B$4) -> 7.7
A212: ORD-2025-588029 | B212: 45914 | C212: 45923 | D212: =IF(C212<B212, B212+14, C212) -> 45923 | E212: =C212-B212 -> 9 | F212: =D212-B212 -> 9 | G212: =IF(Table1[[#This Row],[CorrectedLeadTimeDays]]<=7, 1, 0) -> 0 | H212: =TEXT(B212, "mmmm") -> September | I212: ="Q"&ROUNDUP(MONTH(B212)/3,0)&"-"&YEAR(B212) -> Q3-2025 | J212: =TEXT(K212, "yyyy-mm") -> 2023-01 | K212: =_xlfn.MINIFS($B:$B,$M:$M,M212) -> 44933 | L212: Africa | M212: South Africa | N212: Durban | O212: Non-Profit | P212: Online | Q212: D. Smith | R212: =DATEDIF(K212,B212,"m") -> 32 | S212: Components | T212: CMP-6898 | U212: 1310.3 | V212: =Table1[[#This Row],[UnitCost]]*(1+WhatIf!$B$3) -> 1375.815 | W212: =U212*AI212 -> 6551.5 | X212: =Table1[[#This Row],[ScenarioRev]]-Table1[[#This Row],[ScenarioUnitCost]] -> 13128.282 | Y212: 2875.8 | Z212: =Y212*AI212*(1-AD212) -> 13185.543 | AA212: =Table1[[#This Row],[ScenarioQuanity]]*Table1[[#This Row],[UnitPrice]]*(1-Table1[[#This Row],[ScenarioDiscPct]]) -> 14504.097 | AB212: =Z212-W212 -> 6634.043 | AC212: =Table1[[#This Row],[ScenarioRev]] - Table1[[#This Row],[ScenarioCostOfGoods]] -> 1375.815 | AD212: 0.083 | AE212: =MIN(Table1[[#This Row],[DiscountPct]], WhatIf!$B$2) -> 0.083 | AF212: =IF(Table1[[#This Row],[DiscountPct]]>0.2, 1, 0) -> 0 | AG212: =IF(Y212<=_xlfn.PERCENTILE.INC($Y:$Y,0.33),"Low", IF(D212<=_xlfn.PERCENTILE.INC($Y:$Y,0.66),"Medium", "High")) -> High | AH212: =IF(Z212=0, 0, AB212/Z212) -> 0.50313006 | AI212: 5 | AJ212: =Table1[[#This Row],[Quantity]]*(1+WhatIf!$B$4) -> 5.5
A213: ORD-2024-776337 | B213: 45608 | C213: 45617 | D213: =IF(C213<B213, B213+14, C213) -> 45617 | E213: =C213-B213 -> 9 | F213: =D213-B213 -> 9 | G213: =IF(Table1[[#This Row],[CorrectedLeadTimeDays]]<=7, 1, 0) -> 0 | H213: =TEXT(B213, "mmmm") -> November | I213: ="Q"&ROUNDUP(MONTH(B213)/3,0)&"-"&YEAR(B213) -> Q4-2024 | J213: =TEXT(K213, "yyyy-mm") -> 2023-01 | K213: =_xlfn.MINIFS($B:$B,$M:$M,M213) -> 44955 | L213: Asia | M213: India | N213: Mumbai | O213: Corporate | P213: Direct | Q213: H. Kim | R213: =DATEDIF(K213,B213,"m") -> 21 | S213: Laptops | T213: LAP-5078 | U213: 903.41 | V213: =Table1[[#This Row],[UnitCost]]*(1+WhatIf!$B$3) -> 948.5805 | W213: =U213*AI213 -> 4517.05 | X213: =Table1[[#This Row],[ScenarioRev]]-Table1[[#This Row],[ScenarioUnitCost]] -> 8178.591 | Y213: 1860.41 | Z213: =Y213*AI213*(1-AD213) -> 8297.4286 | AA213: =Table1[[#This Row],[ScenarioQuanity]]*Table1[[#This Row],[UnitPrice]]*(1-Table1[[#This Row],[ScenarioDiscPct]]) -> 9127.1715 | AB213: =Z213-W213 -> 3780.3786 | AC213: =Table1[[#This Row],[ScenarioRev]] - Table1[[#This Row],[ScenarioCostOfGoods]] -> 948.5805 | AD213: 0.108 | AE213: =MIN(Table1[[#This Row],[DiscountPct]], WhatIf!$B$2) -> 0.108 | AF213: =IF(Table1[[#This Row],[DiscountPct]]>0.2, 1, 0) -> 0 | AG213: =IF(Y213<=_xlfn.PERCENTILE.INC($Y:$Y,0.33),"Low", IF(D213<=_xlfn.PERCENTILE.INC($Y:$Y,0.66),"Medium", "High")) -> High | AH213: =IF(Z213=0, 0, AB213/Z213) -> 0.45560845 | AI213: 5 | AJ213: =Table1[[#This Row],[Quantity]]*(1+WhatIf!$B$4) -> 5.5
A214: ORD-2025-831576 | B214: 45915 | C214: 45925 | D214: =IF(C214<B214, B214+14, C214) -> 45925 | E214: =C214-B214 -> 10 | F214: =D214-B214 -> 10 | G214: =IF(Table1[[#This Row],[CorrectedLeadTimeDays]]<=7, 1, 0) -> 0 | H214: =TEXT(B214, "mmmm") -> September | I214: ="Q"&ROUNDUP(MONTH(B214)/3,0)&"-"&YEAR(B214) -> Q3-2025 | J214: =TEXT(K214, "yyyy-mm") -> 2023-01 | K214: =_xlfn.MINIFS($B:$B,$M:$M,M214) -> 44955 | L214: Asia | M214: India | N214: Delhi | O214: Consumer | P214: Retail | Q214: A. Patel | R214: =DATEDIF(K214,B214,"m") -> 31 | S214: Phones | T214: PHN-2859 | U214: 1488.91 | V214: =Table1[[#This Row],[UnitCost]]*(1+WhatIf!$B$3) -> 1563.3555 | W214: =U214*AI214 -> 35733.84 | X214: =Table1[[#This Row],[ScenarioRev]]-Table1[[#This Row],[ScenarioUnitCost]] -> 31026.697 | Y214: 1483.74 | Z214: =Y214*AI214*(1-AD214) -> 29627.32 | AA214: =Table1[[#This Row],[ScenarioQuanity]]*Table1[[#This Row],[UnitPrice]]*(1-Table1[[#This Row],[ScenarioDiscPct]]) -> 32590.052 | AB214: =Z214-W214 -> -6106.5197 | AC214: =Table1[[#This Row],[ScenarioRev]] - Table1[[#This Row],[ScenarioCostOfGoods]] -> 1563.3555 | AD214: 0.168 | AE214: =MIN(Table1[[#This Row],[DiscountPct]], WhatIf!$B$2) -> 0.168 | AF214: =IF(Table1[[#This Row],[DiscountPct]]>0.2, 1, 0) -> 0 | AG214: =IF(Y214<=_xlfn.PERCENTILE.INC($Y:$Y,0.33),"Low", IF(D214<=_xlfn.PERCENTILE.INC($Y:$Y,0.66),"Medium", "High")) -> High | AH214: =IF(Z214=0, 0, AB214/Z214) -> -0.2061111 | AI214: 24 | AJ214: =Table1[[#This Row],[Quantity]]*(1+WhatIf!$B$4) -> 26.4
A215: ORD-2025-440093 | B215: 45763 | C215: 45773 | D215: =IF(C215<B215, B215+14, C215) -> 45773 | E215: =C215-B215 -> 10 | F215: =D215-B215 -> 10 | G215: =IF(Table1[[#This Row],[CorrectedLeadTimeDays]]<=7, 1, 0) -> 0 | H215: =TEXT(B215, "mmmm") -> April | I215: ="Q"&ROUNDUP(MONTH(B215)/3,0)&"-"&YEAR(B215) -> Q2-2025 | J215: =TEXT(K215, "yyyy-mm") -> 2023-01 | K215: =_xlfn.MINIFS($B:$B,$M:$M,M215) -> 44941 | L215: Africa | M215: Nigeria | N215: Port Harcourt | O215: Enterprise | P215: Marketplace | Q215: F. Müller | R215: =DATEDIF(K215,B215,"m") -> 27 | S215: Laptops | T215: LAP-3490 | U215: 1457.44 | V215: =Table1[[#This Row],[UnitCost]]*(1+WhatIf!$B$3) -> 1530.312 | W215: =U215*AI215 -> 33521.12 | X215: =Table1[[#This Row],[ScenarioRev]]-Table1[[#This Row],[ScenarioUnitCost]] -> 42623.55 | Y215: 1996.81 | Z215: =Y215*AI215*(1-AD215) -> 40139.875 | AA215: =Table1[[#This Row],[ScenarioQuanity]]*Table1[[#This Row],[UnitPrice]]*(1-Table1[[#This Row],[ScenarioDiscPct]]) -> 44153.862 | AB215: =Z215-W215 -> 6618.7546 | AC215: =Table1[[#This Row],[ScenarioRev]] - Table1[[#This Row],[ScenarioCostOfGoods]] -> 1530.312 | AD215: 0.126 | AE215: =MIN(Table1[[#This Row],[DiscountPct]], WhatIf!$B$2) -> 0.126 | AF215: =IF(Table1[[#This Row],[DiscountPct]]>0.2, 1, 0) -> 0 | AG215: =IF(Y215<=_xlfn.PERCENTILE.INC($Y:$Y,0.33),"Low", IF(D215<=_xlfn.PERCENTILE.INC($Y:$Y,0.66),"Medium", "High")) -> High | AH215: =IF(Z215=0, 0, AB215/Z215) -> 0.16489226 | AI215: 23 | AJ215: =Table1[[#This Row],[Quantity]]*(1+WhatIf!$B$4) -> 25.3
A216: ORD-2024-353078 | B216: 45520 | C216: 45530 | D216: =IF(C216<B216, B216+14, C216) -> 45530 | E216: =C216-B216 -> 10 | F216: =D216-B216 -> 10 | G216: =IF(Table1[[#This Row],[CorrectedLeadTimeDays]]<=7, 1, 0) -> 0 | H216: =TEXT(B216, "mmmm") -> August | I216: ="Q"&ROUNDUP(MONTH(B216)/3,0)&"-"&YEAR(B216) -> Q3-2024 | J216: =TEXT(K216, "yyyy-mm") -> 2023-01 | K216: =_xlfn.MINIFS($B:$B,$M:$M,M216) -> 44939 | L216: Americas | M216: USA | N216: Chicago | O216: Corporate | P216: Distributor | Q216: L. Okafor | R216: =DATEDIF(K216,B216,"m") -> 19 | S216: Laptops | T216: LAP-5763 | U216: 1291.7 | V216: =Table1[[#This Row],[UnitCost]]*(1+WhatIf!$B$3) -> 1356.285 | W216: =U216*AI216 -> 27125.7 | X216: =Table1[[#This Row],[ScenarioRev]]-Table1[[#This Row],[ScenarioUnitCost]] -> 54698.358 | Y216: 2657.84 | Z216: =Y216*AI216*(1-AD216) -> 50958.766 | AA216: =Table1[[#This Row],[ScenarioQuanity]]*Table1[[#This Row],[UnitPrice]]*(1-Table1[[#This Row],[ScenarioDiscPct]]) -> 56054.643 | AB216: =Z216-W216 -> 23833.066 | AC216: =Table1[[#This Row],[ScenarioRev]] - Table1[[#This Row],[ScenarioCostOfGoods]] -> 1356.285 | AD216: 0.087 | AE216: =MIN(Table1[[#This Row],[DiscountPct]], WhatIf!$B$2) -> 0.087 | AF216: =IF(Table1[[#This Row],[DiscountPct]]>0.2, 1, 0) -> 0 | AG216: =IF(Y216<=_xlfn.PERCENTILE.INC($Y:$Y,0.33),"Low", IF(D216<=_xlfn.PERCENTILE.INC($Y:$Y,0.66),"Medium", "High")) -> High | AH216: =IF(Z216=0, 0, AB216/Z216) -> 0.46769316 | AI216: 21 | AJ216: =Table1[[#This Row],[Quantity]]*(1+WhatIf!$B$4) -> 23.1
A217: ORD-2023-191563 | B217: 45260 | C217: 45270 | D217: =IF(C217<B217, B217+14, C217) -> 45270 | E217: =C217-B217 -> 10 | F217: =D217-B217 -> 10 | G217: =IF(Table1[[#This Row],[CorrectedLeadTimeDays]]<=7, 1, 0) -> 0 | H217: =TEXT(B217, "mmmm") -> November | I217: ="Q"&ROUNDUP(MONTH(B217)/3,0)&"-"&YEAR(B217) -> Q4-2023 | J217: =TEXT(K217, "yyyy-mm") -> 2023-01 | K217: =_xlfn.MINIFS($B:$B,$M:$M,M217) -> 44948 | L217: Europe | M217: Germany | N217: Munich | O217: Small Business | P217: Direct | Q217: F. Müller | R217: =DATEDIF(K217,B217,"m") -> 10 | S217: Laptops | T217: LAP-4899 | U217: 174.74 | V217: =Table1[[#This Row],[UnitCost]]*(1+WhatIf!$B$3) -> 183.477 | W217: =U217*AI217 -> 3669.54 | X217: =Table1[[#This Row],[ScenarioRev]]-Table1[[#This Row],[ScenarioUnitCost]] -> 8224.1145 | Y217: 415.96 | Z217: =Y217*AI217*(1-AD217) -> 7643.265 | AA217: =Table1[[#This Row],[ScenarioQuanity]]*Table1[[#This Row],[UnitPrice]]*(1-Table1[[#This Row],[ScenarioDiscPct]]) -> 8407.5915 | AB217: =Z217-W217 -> 3973.725 | AC217: =Table1[[#This Row],[ScenarioRev]] - Table1[[#This Row],[ScenarioCostOfGoods]] -> 183.477 | AD217: 0.125 | AE217: =MIN(Table1[[#This Row],[DiscountPct]], WhatIf!$B$2) -> 0.125 | AF217: =IF(Table1[[#This Row],[DiscountPct]]>0.2, 1, 0) -> 0 | AG217: =IF(Y217<=_xlfn.PERCENTILE.INC($Y:$Y,0.33),"Low", IF(D217<=_xlfn.PERCENTILE.INC($Y:$Y,0.66),"Medium", "High")) -> Low | AH217: =IF(Z217=0, 0, AB217/Z217) -> 0.51989889 | AI217: 21 | AJ217: =Table1[[#This Row],[Quantity]]*(1+WhatIf!$B$4) -> 23.1
A218: ORD-2024-136321 | B218: 45511 | C218: 45521 | D218: =IF(C218<B218, B218+14, C218) -> 45521 | E218: =C218-B218 -> 10 | F218: =D218-B218 -> 10 | G218: =IF(Table1[[#This Row],[CorrectedLeadTimeDays]]<=7, 1, 0) -> 0 | H218: =TEXT(B218, "mmmm") -> August | I218: ="Q"&ROUNDUP(MONTH(B218)/3,0)&"-"&YEAR(B218) -> Q3-2024 | J218: =TEXT(K218, "yyyy-mm") -> 2023-03 | K218: =_xlfn.MINIFS($B:$B,$M:$M,M218) -> 44988 | L218: Asia | M218: Japan | N218: Osaka | O218: Consumer | P218: Online | Q218: K. Singh | R218: =DATEDIF(K218,B218,"m") -> 17 | S218: Networking | T218: NET-7924 | U218: 436.58 | V218: =Table1[[#This Row],[UnitCost]]*(1+WhatIf!$B$3) -> 458.409 | W218: =U218*AI218 -> 8295.02 | X218: =Table1[[#This Row],[ScenarioRev]]-Table1[[#This Row],[ScenarioUnitCost]] -> 9342.2221 | Y218: 527.48 | Z218: =Y218*AI218*(1-AD218) -> 8909.6647 | AA218: =Table1[[#This Row],[ScenarioQuanity]]*Table1[[#This Row],[UnitPrice]]*(1-Table1[[#This Row],[ScenarioDiscPct]]) -> 9800.6311 | AB218: =Z218-W218 -> 614.64468 | AC218: =Table1[[#This Row],[ScenarioRev]] - Table1[[#This Row],[ScenarioCostOfGoods]] -> 458.409 | AD218: 0.111 | AE218: =MIN(Table1[[#This Row],[DiscountPct]], WhatIf!$B$2) -> 0.111 | AF218: =IF(Table1[[#This Row],[DiscountPct]]>0.2, 1, 0) -> 0 | AG218: =IF(Y218<=_xlfn.PERCENTILE.INC($Y:$Y,0.33),"Low", IF(D218<=_xlfn.PERCENTILE.INC($Y:$Y,0.66),"Medium", "High")) -> Low | AH218: =IF(Z218=0, 0, AB218/Z218) -> 0.068986286 | AI218: 19 | AJ218: =Table1[[#This Row],[Quantity]]*(1+WhatIf!$B$4) -> 20.9
... A237: ORD-2025-177994 | B237: 45740 | C237: 45751 | D237: =IF(C237<B237, B237+14, C237) -> 45751 | E237: =C237-B237 -> 11 | F237: =D237-B237 -> 11 | G237: =IF(Table1[[#This Row],[CorrectedLeadTimeDays]]<=7, 1, 0) -> 0 | H237: =TEXT(B237, "mmmm") -> March | I237: ="Q"&ROUNDUP(MONTH(B237)/3,0)&"-"&YEAR(B237) -> Q1-2025 | J237: =TEXT(K237, "yyyy-mm") -> 2023-01 | K237: =_xlfn.MINIFS($B:$B,$M:$M,M237) -> 44955 | L237: Asia | M237: India | N237: Mumbai | O237: Education | P237: Marketplace | Q237: J. Njeri | R237: =DATEDIF(K237,B237,"m") -> 25 | S237: Phones | T237: PHN-4395 | U237: 23.83 | V237: =Table1[[#This Row],[UnitCost]]*(1+WhatIf!$B$3) -> 25.0215 | W237: =U237*AI237 -> 452.77 | X237: =Table1[[#This Row],[ScenarioRev]]-Table1[[#This Row],[ScenarioUnitCost]] -> 900.0844 | Y237: 47.29 | Z237: =Y237*AI237*(1-AD237) -> 841.00536 | AA237: =Table1[[#This Row],[ScenarioQuanity]]*Table1[[#This Row],[UnitPrice]]*(1-Table1[[#This Row],[ScenarioDiscPct]]) -> 925.1059 | AB237: =Z237-W237 -> 388.23536 | AC237: =Table1[[#This Row],[ScenarioRev]] - Table1[[#This Row],[ScenarioCostOfGoods]] -> 25.0215 | AD237: 0.064 | AE237: =MIN(Table1[[#This Row],[DiscountPct]], WhatIf!$B$2) -> 0.064 | AF237: =IF(Table1[[#This Row],[DiscountPct]]>0.2, 1, 0) -> 0 | AG237: =IF(Y237<=_xlfn.PERCENTILE.INC($Y:$Y,0.33),"Low", IF(D237<=_xlfn.PERCENTILE.INC($Y:$Y,0.66),"Medium", "High")) -> Low | AH237: =IF(Z237=0, 0, AB237/Z237) -> 0.46163244 | AI237: 19 | AJ237: =Table1[[#This Row],[Quantity]]*(1+WhatIf!$B$4) -> 20.9
A238: ORD-2024-371409 | B238: 45613 | C238: 45624 | D238: =IF(C238<B238, B238+14, C238) -> 45624 | E238: =C238-B238 -> 11 | F238: =D238-B238 -> 11 | G238: =IF(Table1[[#This Row],[CorrectedLeadTimeDays]]<=7, 1, 0) -> 0 | H238: =TEXT(B238, "mmmm") -> November | I238: ="Q"&ROUNDUP(MONTH(B238)/3,0)&"-"&YEAR(B238) -> Q4-2024 | J238: =TEXT(K238, "yyyy-mm") -> 2023-01 | K238: =_xlfn.MINIFS($B:$B,$M:$M,M238) -> 44928 | L238: Americas | M238: Canada | O238: Consumer | P238: Distributor | Q238: A. Patel | R238: =DATEDIF(K238,B238,"m") -> 22 | S238: Printers | T238: PRN-1371 | U238: 1008.16 | V238: =Table1[[#This Row],[UnitCost]]*(1+WhatIf!$B$3) -> 1058.568 | W238: =U238*AI238 -> 15122.4 | X238: =Table1[[#This Row],[ScenarioRev]]-Table1[[#This Row],[ScenarioUnitCost]] -> 30683.555 | Y238: 2077.5 | Z238: =Y238*AI238*(1-AD238) -> 28856.475 | AA238: =Table1[[#This Row],[ScenarioQuanity]]*Table1[[#This Row],[UnitPrice]]*(1-Table1[[#This Row],[ScenarioDiscPct]]) -> 31742.123 | AB238: =Z238-W238 -> 13734.075 | AC238: =Table1[[#This Row],[ScenarioRev]] - Table1[[#This Row],[ScenarioCostOfGoods]] -> 1058.568 | AD238: 0.074 | AE238: =MIN(Table1[[#This Row],[DiscountPct]], WhatIf!$B$2) -> 0.074 | AF238: =IF(Table1[[#This Row],[DiscountPct]]>0.2, 1, 0) -> 0 | AG238: =IF(Y238<=_xlfn.PERCENTILE.INC($Y:$Y,0.33),"Low", IF(D238<=_xlfn.PERCENTILE.INC($Y:$Y,0.66),"Medium", "High")) -> High | AH238: =IF(Z238=0, 0, AB238/Z238) -> 0.47594431 | AI238: 15 | AJ238: =Table1[[#This Row],[Quantity]]*(1+WhatIf!$B$4) -> 16.5
A239: ORD-2024-250862 | B239: 45590 | C239: 45601 | D239: =IF(C239<B239, B239+14, C239) -> 45601 | E239: =C239-B239 -> 11 | F239: =D239-B239 -> 11 | G239: =IF(Table1[[#This Row],[CorrectedLeadTimeDays]]<=7, 1, 0) -> 0 | H239: =TEXT(B239, "mmmm") -> October | I239: ="Q"&ROUNDUP(MONTH(B239)/3,0)&"-"&YEAR(B239) -> Q4-2024 | J239: =TEXT(K239, "yyyy-mm") -> 2023-01 | K239: =_xlfn.MINIFS($B:$B,$M:$M,M239) -> 44939 | L239: Americas | M239: USA | N239: New York | O239: Corporate | P239: Distributor | Q239: N. Brown | R239: =DATEDIF(K239,B239,"m") -> 21 | S239: Components | T239: CMP-9498 | U239: 446.66 | V239: =Table1[[#This Row],[UnitCost]]*(1+WhatIf!$B$3) -> 468.993 | W239: =U239*AI239 -> 6699.9 | X239: =Table1[[#This Row],[ScenarioRev]]-Table1[[#This Row],[ScenarioUnitCost]] -> 6974.6883 | Y239: 527.64 | Z239: =Y239*AI239*(1-AD239) -> 6766.983 | AA239: =Table1[[#This Row],[ScenarioQuanity]]*Table1[[#This Row],[UnitPrice]]*(1-Table1[[#This Row],[ScenarioDiscPct]]) -> 7443.6813 | AB239: =Z239-W239 -> 67.083 | AC239: =Table1[[#This Row],[ScenarioRev]] - Table1[[#This Row],[ScenarioCostOfGoods]] -> 468.993 | AD239: 0.145 | AE239: =MIN(Table1[[#This Row],[DiscountPct]], WhatIf!$B$2) -> 0.145 | AF239: =IF(Table1[[#This Row],[DiscountPct]]>0.2, 1, 0) -> 0 | AG239: =IF(Y239<=_xlfn.PERCENTILE.INC($Y:$Y,0.33),"Low", IF(D239<=_xlfn.PERCENTILE.INC($Y:$Y,0.66),"Medium", "High")) -> Low | AH239: =IF(Z239=0, 0, AB239/Z239) -> 0.0099132804 | AI239: 15 | AJ239: =Table1[[#This Row],[Quantity]]*(1+WhatIf!$B$4) -> 16.5
A240: ORD-2023-987700 | B240: 45021 | C240: 45032 | D240: =IF(C240<B240, B240+14, C240) -> 45032 | E240: =C240-B240 -> 11 | F240: =D240-B240 -> 11 | G240: =IF(Table1[[#This Row],[CorrectedLeadTimeDays]]<=7, 1, 0) -> 0 | H240: =TEXT(B240, "mmmm") -> April | I240: ="Q"&ROUNDUP(MONTH(B240)/3,0)&"-"&YEAR(B240) -> Q2-2023 | J240: =TEXT(K240, "yyyy-mm") -> 2023-01 | K240: =_xlfn.MINIFS($B:$B,$M:$M,M240) -> 44928 | L240: Americas | M240: Canada | N240: Vancouver | O240: Non-Profit | P240: Online | Q240: O. Wang | R240: =DATEDIF(K240,B240,"m") -> 3 | S240: Monitors | T240: MON-5259 | U240: 213.1 | V240: =Table1[[#This Row],[UnitCost]]*(1+WhatIf!$B$3) -> 223.755 | W240: =U240*AI240 -> 3196.5 | X240: =Table1[[#This Row],[ScenarioRev]]-Table1[[#This Row],[ScenarioUnitCost]] -> 7584.6496 | Y240: 501.31 | Z240: =Y240*AI240*(1-AD240) -> 7098.5496 | AA240: =Table1[[#This Row],[ScenarioQuanity]]*Table1[[#This Row],[UnitPrice]]*(1-Table1[[#This Row],[ScenarioDiscPct]]) -> 7808.4046 | AB240: =Z240-W240 -> 3902.0496 | AC240: =Table1[[#This Row],[ScenarioRev]] - Table1[[#This Row],[ScenarioCostOfGoods]] -> 223.755 | AD240: 0.056 | AE240: =MIN(Table1[[#This Row],[DiscountPct]], WhatIf!$B$2) -> 0.056 | AF240: =IF(Table1[[#This Row],[DiscountPct]]>0.2, 1, 0) -> 0 | AG240: =IF(Y240<=_xlfn.PERCENTILE.INC($Y:$Y,0.33),"Low", IF(D240<=_xlfn.PERCENTILE.INC($Y:$Y,0.66),"Medium", "High")) -> Low | AH240: =IF(Z240=0, 0, AB240/Z240) -> 0.54969674 | AI240: 15 | AJ240: =Table1[[#This Row],[Quantity]]*(1+WhatIf!$B$4) -> 16.5
A241: ORD-2024-364080 | B241: 45398 | C241: 45409 | D241: =IF(C241<B241, B241+14, C241) -> 45409 | E241: =C241-B241 -> 11 | F241: =D241-B241 -> 11 | G241: =IF(Table1[[#This Row],[CorrectedLeadTimeDays]]<=7, 1, 0) -> 0 | H241: =TEXT(B241, "mmmm") -> April | I241: ="Q"&ROUNDUP(MONTH(B241)/3,0)&"-"&YEAR(B241) -> Q2-2024 | J241: =TEXT(K241, "yyyy-mm") -> 2023-01 | K241: =_xlfn.MINIFS($B:$B,$M:$M,M241) -> 44946 | L241: Africa | M241: Kenya | N241: Nakuru | O241: Enterprise | P241: Online | Q241: D. Smith | R241: =DATEDIF(K241,B241,"m") -> 14 | S241: Printers | T241: PRN-2641 | U241: 401.3 | V241: =Table1[[#This Row],[UnitCost]]*(1+WhatIf!$B$3) -> 421.365 | W241: =U241*AI241 -> 5216.9 | X241: =Table1[[#This Row],[ScenarioRev]]-Table1[[#This Row],[ScenarioUnitCost]] -> 9033.4518 | Y241: 826.47 | Z241: =Y241*AI241*(1-AD241) -> 8326.6853 | AA241: =Table1[[#This Row],[ScenarioQuanity]]*Table1[[#This Row],[UnitPrice]]*(1-Table1[[#This Row],[ScenarioDiscPct]]) -> 9454.8168 | AB241: =Z241-W241 -> 3109.7852 | AC241: =Table1[[#This Row],[ScenarioRev]] - Table1[[#This Row],[ScenarioCostOfGoods]] -> 421.365 | AD241: 0.225 | AE241: =MIN(Table1[[#This Row],[DiscountPct]], WhatIf!$B$2) -> 0.2 | AF241: =IF(Table1[[#This Row],[DiscountPct]]>0.2, 1, 0) -> 1 | AG241: =IF(Y241<=_xlfn.PERCENTILE.INC($Y:$Y,0.33),"Low", IF(D241<=_xlfn.PERCENTILE.INC($Y:$Y,0.66),"Medium", "High")) -> High | AH241: =IF(Z241=0, 0, AB241/Z241) -> 0.37347217 | AI241: 13 | AJ241: =Table1[[#This Row],[Quantity]]*(1+WhatIf!$B$4) -> 14.3
A242: ORD-2024-581530 | B242: 45542 | C242: 45553 | D242: =IF(C242<B242, B242+14, C242) -> 45553 | E242: =C242-B242 -> 11 | F242: =D242-B242 -> 11 | G242: =IF(Table1[[#This Row],[CorrectedLeadTimeDays]]<=7, 1, 0) -> 0 | H242: =TEXT(B242, "mmmm") -> September | I242: ="Q"&ROUNDUP(MONTH(B242)/3,0)&"-"&YEAR(B242) -> Q3-2024 | J242: =TEXT(K242, "yyyy-mm") -> 2023-01 | K242: =_xlfn.MINIFS($B:$B,$M:$M,M242) -> 44938 | L242: Asia | M242: China | N242: Beijing | O242: Consumer | P242: Distributor | Q242: O. Wang | R242: =DATEDIF(K242,B242,"m") -> 19 | S242: Networking | T242: NET-7998 | U242: 181.74 | V242: =Table1[[#This Row],[UnitCost]]*(1+WhatIf!$B$3) -> 190.827 | W242: =U242*AI242 -> 2362.62 | X242: =Table1[[#This Row],[ScenarioRev]]-Table1[[#This Row],[ScenarioUnitCost]] -> 1992.3826 | Y242: 190.84 | Z242: =Y242*AI242*(1-AD242) -> 1950.0031 | AA242: =Table1[[#This Row],[ScenarioQuanity]]*Table1[[#This Row],[UnitPrice]]*(1-Table1[[#This Row],[ScenarioDiscPct]]) -> 2183.2096 | AB242: =Z242-W242 -> -412.61688 | AC242: =Table1[[#This Row],[ScenarioRev]] - Table1[[#This Row],[ScenarioCostOfGoods]] -> 190.827 | AD242: 0.214 | AE242: =MIN(Table1[[#This Row],[DiscountPct]], WhatIf!$B$2) -> 0.2 | AF242: =IF(Table1[[#This Row],[DiscountPct]]>0.2, 1, 0) -> 1 | AG242: =IF(Y242<=_xlfn.PERCENTILE.INC($Y:$Y,0.33),"Low", IF(D242<=_xlfn.PERCENTILE.INC($Y:$Y,0.66),"Medium", "High")) -> Low | AH242: =IF(Z242=0, 0, AB242/Z242) -> -0.21159806 | AI242: 13 | AJ242: =Table1[[#This Row],[Quantity]]*(1+WhatIf!$B$4) -> 14.3
A243: ORD-2025-983096 | B243: 45794 | C243: 45805 | D243: =IF(C243<B243, B243+14, C243) -> 45805 | E243: =C243-B243 -> 11 | F243: =D243-B243 -> 11 | G243: =IF(Table1[[#This Row],[CorrectedLeadTimeDays]]<=7, 1, 0) -> 0 | H243: =TEXT(B243, "mmmm") -> May | I243: ="Q"&ROUNDUP(MONTH(B243)/3,0)&"-"&YEAR(B243) -> Q2-2025 | J243: =TEXT(K243, "yyyy-mm") -> 2023-01 | K243: =_xlfn.MINIFS($B:$B,$M:$M,M243) -> 44955 | L243: Asia | M243: India | N243: Bengaluru | O243: Corporate | P243: Distributor | Q243: B. Chen | R243: =DATEDIF(K243,B243,"m") -> 27 | S243: Laptops | T243: LAP-9016 | U243: 623.4 | V243: =Table1[[#This Row],[UnitCost]]*(1+WhatIf!$B$3) -> 654.57 | W243: =U243*AI243 -> 7480.8 | X243: =Table1[[#This Row],[ScenarioRev]]-Table1[[#This Row],[ScenarioUnitCost]] -> 12211.203 | Y243: 1100.09 | Z243: =Y243*AI243*(1-AD243) -> 11696.157 | AA243: =Table1[[#This Row],[ScenarioQuanity]]*Table1[[#This Row],[UnitPrice]]*(1-Table1[[#This Row],[ScenarioDiscPct]]) -> 12865.773 | AB243: =Z243-W243 -> 4215.3569 | AC243: =Table1[[#This Row],[ScenarioRev]] - Table1[[#This Row],[ScenarioCostOfGoods]] -> 654.57 | AD243: 0.114 | AE243: =MIN(Table1[[#This Row],[DiscountPct]], WhatIf!$B$2) -> 0.114 | AF243: =IF(Table1[[#This Row],[DiscountPct]]>0.2, 1, 0) -> 0 | AG243: =IF(Y243<=_xlfn.PERCENTILE.INC($Y:$Y,0.33),"Low", IF(D243<=_xlfn.PERCENTILE.INC($Y:$Y,0.66),"Medium", "High")) -> High | AH243: =IF(Z243=0, 0, AB243/Z243) -> 0.3604053 | AI243: 12 | AJ243: =Table1[[#This Row],[Quantity]]*(1+WhatIf!$B$4) -> 13.2
A244: ORD-2024-381197 | B244: 45597 | C244: 45608 | D244: =IF(C244<B244, B244+14, C244) -> 45608 | E244: =C244-B244 -> 11 | F244: =D244-B244 -> 11 | G244: =IF(Table1[[#This Row],[CorrectedLeadTimeDays]]<=7, 1, 0) -> 0 | H244: =TEXT(B244, "mmmm") -> November | I244: ="Q"&ROUNDUP(MONTH(B244)/3,0)&"-"&YEAR(B244) -> Q4-2024 | J244: =TEXT(K244, "yyyy-mm") -> 2023-01 | K244: =_xlfn.MINIFS($B:$B,$M:$M,M244) -> 44948 | L244: Europe | M244: Germany | N244: Frankfurt | O244: Consumer | P244: Online | Q244: B. Chen | R244: =DATEDIF(K244,B244,"m") -> 21 | S244: Printers | T244: PRN-2409 | U244: 599.84 | V244: =Table1[[#This Row],[UnitCost]]*(1+WhatIf!$B$3) -> 629.832 | W244: =U244*AI244 -> 6598.24 | X244: =Table1[[#This Row],[ScenarioRev]]-Table1[[#This Row],[ScenarioUnitCost]] -> 13621.575 | Y244: 1330.85 | Z244: =Y244*AI244*(1-AD244) -> 12955.825 | AA244: =Table1[[#This Row],[ScenarioQuanity]]*Table1[[#This Row],[UnitPrice]]*(1-Table1[[#This Row],[ScenarioDiscPct]]) -> 14251.407 | AB244: =Z244-W244 -> 6357.5847 | AC244: =Table1[[#This Row],[ScenarioRev]] - Table1[[#This Row],[ScenarioCostOfGoods]] -> 629.832 | AD244: 0.115 | AE244: =MIN(Table1[[#This Row],[DiscountPct]], WhatIf!$B$2) -> 0.115 | AF244: =IF(Table1[[#This Row],[DiscountPct]]>0.2, 1, 0) -> 0 | AG244: =IF(Y244<=_xlfn.PERCENTILE.INC($Y:$Y,0.33),"Low", IF(D244<=_xlfn.PERCENTILE.INC($Y:$Y,0.66),"Medium", "High")) -> High | AH244: =IF(Z244=0, 0, AB244/Z244) -> 0.49071247 | AI244: 11 | AJ244: =Table1[[#This Row],[Quantity]]*(1+WhatIf!$B$4) -> 12.1
A245: ORD-2025-509940 | B245: 45793 | C245: 45804 | D245: =IF(C245<B245, B245+14, C245) -> 45804 | E245: =C245-B245 -> 11 | F245: =D245-B245 -> 11 | G245: =IF(Table1[[#This Row],[CorrectedLeadTimeDays]]<=7, 1, 0) -> 0 | H245: =TEXT(B245, "mmmm") -> May | I245: ="Q"&ROUNDUP(MONTH(B245)/3,0)&"-"&YEAR(B245) -> Q2-2025 | J245: =TEXT(K245, "yyyy-mm") -> 2023-01 | K245: =_xlfn.MINIFS($B:$B,$M:$M,M245) -> 44938 | L245: Asia | M245: China | N245: Beijing | O245: Enterprise | P245: Online | Q245: F. Müller | R245: =DATEDIF(K245,B245,"m") -> 28 | S245: Phones | T245: PHN-3800 | U245: 918.12 | V245: =Table1[[#This Row],[UnitCost]]*(1+WhatIf!$B$3) -> 964.026 | W245: =U245*AI245 -> 7344.96 | X245: =Table1[[#This Row],[ScenarioRev]]-Table1[[#This Row],[ScenarioUnitCost]] -> 9689.3372 | Y245: 1337.69 | Z245: =Y245*AI245*(1-AD245) -> 9684.8756 | AA245: =Table1[[#This Row],[ScenarioQuanity]]*Table1[[#This Row],[UnitPrice]]*(1-Table1[[#This Row],[ScenarioDiscPct]]) -> 10653.363 | AB245: =Z245-W245 -> 2339.9156 | AC245: =Table1[[#This Row],[ScenarioRev]] - Table1[[#This Row],[ScenarioCostOfGoods]] -> 964.026 | AD245: 0.095 | AE245: =MIN(Table1[[#This Row],[DiscountPct]], WhatIf!$B$2) -> 0.095 | AF245: =IF(Table1[[#This Row],[DiscountPct]]>0.2, 1, 0) -> 0 | AG245: =IF(Y245<=_xlfn.PERCENTILE.INC($Y:$Y,0.33),"Low", IF(D245<=_xlfn.PERCENTILE.INC($Y:$Y,0.66),"Medium", "High")) -> High | AH245: =IF(Z245=0, 0, AB245/Z245) -> 0.24160513 | AI245: 8 | AJ245: =Table1[[#This Row],[Quantity]]*(1+WhatIf!$B$4) -> 8.8
A246: ORD-2024-970848 | B246: 45435 | C246: 45446 | D246: =IF(C246<B246, B246+14, C246) -> 45446 | E246: =C246-B246 -> 11 | F246: =D246-B246 -> 11 | G246: =IF(Table1[[#This Row],[CorrectedLeadTimeDays]]<=7, 1, 0) -> 0 | H246: =TEXT(B246, "mmmm") -> May | I246: ="Q"&ROUNDUP(MONTH(B246)/3,0)&"-"&YEAR(B246) -> Q2-2024 | J246: =TEXT(K246, "yyyy-mm") -> 2023-01 | K246: =_xlfn.MINIFS($B:$B,$M:$M,M246) -> 44933 | L246: Africa | M246: South Africa | N246: Johannesburg | O246: Small Business | P246: Distributor | Q246: F. Müller | R246: =DATEDIF(K246,B246,"m") -> 16 | S246: Printers | T246: PRN-3785 | U246: 180.89 | V246: =Table1[[#This Row],[UnitCost]]*(1+WhatIf!$B$3) -> 189.9345 | W246: =U246*AI246 -> 1447.12 | X246: =Table1[[#This Row],[ScenarioRev]]-Table1[[#This Row],[ScenarioUnitCost]] -> 1957.9647 | Y246: 249.57 | Z246: =Y246*AI246*(1-AD246) -> 1952.6357 | AA246: =Table1[[#This Row],[ScenarioQuanity]]*Table1[[#This Row],[UnitPrice]]*(1-Table1[[#This Row],[ScenarioDiscPct]]) -> 2147.8992 | AB246: =Z246-W246 -> 505.51568 | AC246: =Table1[[#This Row],[ScenarioRev]] - Table1[[#This Row],[ScenarioCostOfGoods]] -> 189.9345 | AD246: 0.022 | AE246: =MIN(Table1[[#This Row],[DiscountPct]], WhatIf!$B$2) -> 0.022 | AF246: =IF(Table1[[#This Row],[DiscountPct]]>0.2, 1, 0) -> 0 | AG246: =IF(Y246<=_xlfn.PERCENTILE.INC($Y:$Y,0.33),"Low", IF(D246<=_xlfn.PERCENTILE.INC($Y:$Y,0.66),"Medium", "High")) -> Low | AH246: =IF(Z246=0, 0, AB246/Z246) -> 0.25888889 | AI246: 8 | AJ246: =Table1[[#This Row],[Quantity]]*(1+WhatIf!$B$4) -> 8.8
A247: ORD-2025-762301 | B247: 45779 | C247: 45790 | D247: =IF(C247<B247, B247+14, C247) -> 45790 | E247: =C247-B247 -> 11 | F247: =D247-B247 -> 11 | G247: =IF(Table1[[#This Row],[CorrectedLeadTimeDays]]<=7, 1, 0) -> 0 | H247: =TEXT(B247, "mmmm") -> May | I247: ="Q"&ROUNDUP(MONTH(B247)/3,0)&"-"&YEAR(B247) -> Q2-2025 | J247: =TEXT(K247, "yyyy-mm") -> 2023-01 | K247: =_xlfn.MINIFS($B:$B,$M:$M,M247) -> 44946 | L247: Africa | M247: Kenya | N247: Nakuru | O247: Small Business | P247: Online | Q247: A. Patel | R247: =DATEDIF(K247,B247,"m") -> 27 | S247: Accessories | T247: ACC-2252 | U247: 1057.6 | V247: =Table1[[#This Row],[UnitCost]]*(1+WhatIf!$B$3) -> 1110.48 | W247: =U247*AI247 -> 4230.4 | X247: =Table1[[#This Row],[ScenarioRev]]-Table1[[#This Row],[ScenarioUnitCost]] -> 3947.9712 | Y247: 1437.06 | Z247: =Y247*AI247*(1-AD247) -> 4569.8508 | AA247: =Table1[[#This Row],[ScenarioQuanity]]*Table1[[#This Row],[UnitPrice]]*(1-Table1[[#This Row],[ScenarioDiscPct]]) -> 5058.4512 | AB247: =Z247-W247 -> 339.4508 | AC247: =Table1[[#This Row],[ScenarioRev]] - Table1[[#This Row],[ScenarioCostOfGoods]] -> 1110.48 | AD247: 0.205 | AE247: =MIN(Table1[[#This Row],[DiscountPct]], WhatIf!$B$2) -> 0.2 | AF247: =IF(Table1[[#This Row],[DiscountPct]]>0.2, 1, 0) -> 1 | AG247: =IF(Y247<=_xlfn.PERCENTILE.INC($Y:$Y,0.33),"Low", IF(D247<=_xlfn.PERCENTILE.INC($Y:$Y,0.66),"Medium", "High")) -> High | AH247: =IF(Z247=0, 0, AB247/Z247) -> 0.074280499 | AI247: 4 | AJ247: =Table1[[#This Row],[Quantity]]*(1+WhatIf!$B$4) -> 4.4
A248: ORD-2024-207669 | B248: 45315 | C248: 45326 | D248: =IF(C248<B248, B248+14, C248) -> 45326 | E248: =C248-B248 -> 11 | F248: =D248-B248 -> 11 | G248: =IF(Table1[[#This Row],[CorrectedLeadTimeDays]]<=7, 1, 0) -> 0 | H248: =TEXT(B248, "mmmm") -> January | I248: ="Q"&ROUNDUP(MONTH(B248)/3,0)&"-"&YEAR(B248) -> Q1-2024 | J248: =TEXT(K248, "yyyy-mm") -> 2023-01 | K248: =_xlfn.MINIFS($B:$B,$M:$M,M248) -> 44945 | L248: Europe | M248: United Kingdom | N248: Manchester | O248: Consumer | P248: Retail | Q248: B. Chen | R248: =DATEDIF(K248,B248,"m") -> 12 | S248: Laptops | T248: LAP-5689 | U248: 525.34 | V248: =Table1[[#This Row],[UnitCost]]*(1+WhatIf!$B$3) -> 551.607 | W248: =U248*AI248 -> 2101.36 | X248: =Table1[[#This Row],[ScenarioRev]]-Table1[[#This Row],[ScenarioUnitCost]] -> 4100.7683 | Y248: 1233.79 | Z248: =Y248*AI248*(1-AD248) -> 4229.4321 | AA248: =Table1[[#This Row],[ScenarioQuanity]]*Table1[[#This Row],[UnitPrice]]*(1-Table1[[#This Row],[ScenarioDiscPct]]) -> 4652.3753 | AB248: =Z248-W248 -> 2128.0721 | AC248: =Table1[[#This Row],[ScenarioRev]] - Table1[[#This Row],[ScenarioCostOfGoods]] -> 551.607 | AD248: 0.143 | AE248: =MIN(Table1[[#This Row],[DiscountPct]], WhatIf!$B$2) -> 0.143 | AF248: =IF(Table1[[#This Row],[DiscountPct]]>0.2, 1, 0) -> 0 | AG248: =IF(Y248<=_xlfn.PERCENTILE.INC($Y:$Y,0.33),"Low", IF(D248<=_xlfn.PERCENTILE.INC($Y:$Y,0.66),"Medium", "High")) -> High | AH248: =IF(Z248=0, 0, AB248/Z248) -> 0.50315788 | AI248: 4 | AJ248: =Table1[[#This Row],[Quantity]]*(1+WhatIf!$B$4) -> 4.4
A249: ORD-2023-769774 | B249: 45090 | C249: 45101 | D249: =IF(C249<B249, B249+14, C249) -> 45101 | E249: =C249-B249 -> 11 | F249: =D249-B249 -> 11 | G249: =IF(Table1[[#This Row],[CorrectedLeadTimeDays]]<=7, 1, 0) -> 0 | H249: =TEXT(B249, "mmmm") -> June | I249: ="Q"&ROUNDUP(MONTH(B249)/3,0)&"-"&YEAR(B249) -> Q2-2023 | J249: =TEXT(K249, "yyyy-mm") -> 2023-01 | K249: =_xlfn.MINIFS($B:$B,$M:$M,M249) -> 44928 | L249: Americas | M249: Canada | N249: Toronto | O249: Corporate | P249: Online | Q249: C. Otieno | R249: =DATEDIF(K249,B249,"m") -> 5 | S249: Printers | T249: PRN-8008 | U249: 247.07 | V249: =Table1[[#This Row],[UnitCost]]*(1+WhatIf!$B$3) -> 259.4235 | W249: =U249*AI249 -> 988.28 | X249: =Table1[[#This Row],[ScenarioRev]]-Table1[[#This Row],[ScenarioUnitCost]] -> 1858.4051 | Y249: 495.19 | Z249: =Y249*AI249*(1-AD249) -> 1925.2987 | AA249: =Table1[[#This Row],[ScenarioQuanity]]*Table1[[#This Row],[UnitPrice]]*(1-Table1[[#This Row],[ScenarioDiscPct]]) -> 2117.8286 | AB249: =Z249-W249 -> 937.01872 | AC249: =Table1[[#This Row],[ScenarioRev]] - Table1[[#This Row],[ScenarioCostOfGoods]] -> 259.4235 | AD249: 0.028 | AE249: =MIN(Table1[[#This Row],[DiscountPct]], WhatIf!$B$2) -> 0.028 | AF249: =IF(Table1[[#This Row],[DiscountPct]]>0.2, 1, 0) -> 0 | AG249: =IF(Y249<=_xlfn.PERCENTILE.INC($Y:$Y,0.33),"Low", IF(D249<=_xlfn.PERCENTILE.INC($Y:$Y,0.66),"Medium", "High")) -> Low | AH249: =IF(Z249=0, 0, AB249/Z249) -> 0.48668745 | AI249: 4 | AJ249: =Table1[[#This Row],[Quantity]]*(1+WhatIf!$B$4) -> 4.4
A250: ORD-2023-848013 | B250: 44977 | C250: 44989 | D250: =IF(C250<B250, B250+14, C250) -> 44989 | E250: =C250-B250 -> 12 | F250: =D250-B250 -> 12 | G250: =IF(Table1[[#This Row],[CorrectedLeadTimeDays]]<=7, 1, 0) -> 0 | H250: =TEXT(B250, "mmmm") -> February | I250: ="Q"&ROUNDUP(MONTH(B250)/3,0)&"-"&YEAR(B250) -> Q1-2023 | J250: =TEXT(K250, "yyyy-mm") -> 2023-01 | K250: =_xlfn.MINIFS($B:$B,$M:$M,M250) -> 44955 | L250: Asia | M250: India | N250: Delhi | O250: Consumer | P250: Distributor | Q250: M. Rossi | R250: =DATEDIF(K250,B250,"m") -> 0 | S250: Monitors | T250: MON-9906 | U250: 299.75 | V250: =Table1[[#This Row],[UnitCost]]*(1+WhatIf!$B$3) -> 314.7375 | W250: =U250*AI250 -> 14987.5 | X250: =Table1[[#This Row],[ScenarioRev]]-Table1[[#This Row],[ScenarioUnitCost]] -> 23934.621 | Y250: 523.01 | Z250: =Y250*AI250*(1-AD250) -> 22044.871 | AA250: =Table1[[#This Row],[ScenarioQuanity]]*Table1[[#This Row],[UnitPrice]]*(1-Table1[[#This Row],[ScenarioDiscPct]]) -> 24249.359 | AB250: =Z250-W250 -> 7057.3715 | AC250: =Table1[[#This Row],[ScenarioRev]] - Table1[[#This Row],[ScenarioCostOfGoods]] -> 314.7375 | AD250: 0.157 | AE250: =MIN(Table1[[#This Row],[DiscountPct]], WhatIf!$B$2) -> 0.157 | AF250: =IF(Table1[[#This Row],[DiscountPct]]>0.2, 1, 0) -> 0 | AG250: =IF(Y250<=_xlfn.PERCENTILE.INC($Y:$Y,0.33),"Low", IF(D250<=_xlfn.PERCENTILE.INC($Y:$Y,0.66),"Medium", "High")) -> Low | AH250: =IF(Z250=0, 0, AB250/Z250) -> 0.32013666 | AI250: 50 | AJ250: =Table1[[#This Row],[Quantity]]*(1+WhatIf!$B$4) -> 55
... A265: ORD-2024-961756 | B265: 45621 | C265: 45633 | D265: =IF(C265<B265, B265+14, C265) -> 45633 | E265: =C265-B265 -> 12 | F265: =D265-B265 -> 12 | G265: =IF(Table1[[#This Row],[CorrectedLeadTimeDays]]<=7, 1, 0) -> 0 | H265: =TEXT(B265, "mmmm") -> November | I265: ="Q"&ROUNDUP(MONTH(B265)/3,0)&"-"&YEAR(B265) -> Q4-2024 | J265: =TEXT(K265, "yyyy-mm") -> 2023-01 | K265: =_xlfn.MINIFS($B:$B,$M:$M,M265) -> 44938 | L265: Asia | M265: China | N265: Shanghai | O265: Corporate | P265: Distributor | Q265: A. Patel | R265: =DATEDIF(K265,B265,"m") -> 22 | S265: Accessories | T265: ACC-7047 | U265: 769.9 | V265: =Table1[[#This Row],[UnitCost]]*(1+WhatIf!$B$3) -> 808.395 | W265: =U265*AI265 -> 3849.5 | X265: =Table1[[#This Row],[ScenarioRev]]-Table1[[#This Row],[ScenarioUnitCost]] -> 3670.585 | Y265: 814.36 | Z265: =Y265*AI265*(1-AD265) -> 4071.8 | AA265: =Table1[[#This Row],[ScenarioQuanity]]*Table1[[#This Row],[UnitPrice]]*(1-Table1[[#This Row],[ScenarioDiscPct]]) -> 4478.98 | AB265: =Z265-W265 -> 222.3 | AC265: =Table1[[#This Row],[ScenarioRev]] - Table1[[#This Row],[ScenarioCostOfGoods]] -> 808.395 | AD265: 0 | AE265: =MIN(Table1[[#This Row],[DiscountPct]], WhatIf!$B$2) -> 0 | AF265: =IF(Table1[[#This Row],[DiscountPct]]>0.2, 1, 0) -> 0 | AG265: =IF(Y265<=_xlfn.PERCENTILE.INC($Y:$Y,0.33),"Low", IF(D265<=_xlfn.PERCENTILE.INC($Y:$Y,0.66),"Medium", "High")) -> Low | AH265: =IF(Z265=0, 0, AB265/Z265) -> 0.054595019 | AI265: 5 | AJ265: =Table1[[#This Row],[Quantity]]*(1+WhatIf!$B$4) -> 5.5
A266: ORD-2025-863978 | B266: 45876 | C266: 45888 | D266: =IF(C266<B266, B266+14, C266) -> 45888 | E266: =C266-B266 -> 12 | F266: =D266-B266 -> 12 | G266: =IF(Table1[[#This Row],[CorrectedLeadTimeDays]]<=7, 1, 0) -> 0 | H266: =TEXT(B266, "mmmm") -> August | I266: ="Q"&ROUNDUP(MONTH(B266)/3,0)&"-"&YEAR(B266) -> Q3-2025 | J266: =TEXT(K266, "yyyy-mm") -> 2023-01 | K266: =_xlfn.MINIFS($B:$B,$M:$M,M266) -> 44946 | L266: Africa | M266: Kenya | N266: Nakuru | O266: Corporate | Q266: M. Rossi | R266: =DATEDIF(K266,B266,"m") -> 30 | S266: Components | T266: CMP-2854 | U266: 601.51 | V266: =Table1[[#This Row],[UnitCost]]*(1+WhatIf!$B$3) -> 631.5855 | W266: =U266*AI266 -> 1804.53 | X266: =Table1[[#This Row],[ScenarioRev]]-Table1[[#This Row],[ScenarioUnitCost]] -> 1188.8008 | Y266: 679.35 | Z266: =Y266*AI266*(1-AD266) -> 1654.8966 | AA266: =Table1[[#This Row],[ScenarioQuanity]]*Table1[[#This Row],[UnitPrice]]*(1-Table1[[#This Row],[ScenarioDiscPct]]) -> 1820.3863 | AB266: =Z266-W266 -> -149.6334 | AC266: =Table1[[#This Row],[ScenarioRev]] - Table1[[#This Row],[ScenarioCostOfGoods]] -> 631.5855 | AD266: 0.188 | AE266: =MIN(Table1[[#This Row],[DiscountPct]], WhatIf!$B$2) -> 0.188 | AF266: =IF(Table1[[#This Row],[DiscountPct]]>0.2, 1, 0) -> 0 | AG266: =IF(Y266<=_xlfn.PERCENTILE.INC($Y:$Y,0.33),"Low", IF(D266<=_xlfn.PERCENTILE.INC($Y:$Y,0.66),"Medium", "High")) -> Low | AH266: =IF(Z266=0, 0, AB266/Z266) -> -0.09041858 | AI266: 3 | AJ266: =Table1[[#This Row],[Quantity]]*(1+WhatIf!$B$4) -> 3.3
A267: ORD-2024-811752 | B267: 45347 | C267: 45360 | D267: =IF(C267<B267, B267+14, C267) -> 45360 | E267: =C267-B267 -> 13 | F267: =D267-B267 -> 13 | G267: =IF(Table1[[#This Row],[CorrectedLeadTimeDays]]<=7, 1, 0) -> 0 | H267: =TEXT(B267, "mmmm") -> February | I267: ="Q"&ROUNDUP(MONTH(B267)/3,0)&"-"&YEAR(B267) -> Q1-2024 | J267: =TEXT(K267, "yyyy-mm") -> 2023-01 | K267: =_xlfn.MINIFS($B:$B,$M:$M,M267) -> 44936 | L267: Europe | M267: France | N267: Marseille | O267: Small Business | P267: Distributor | Q267: E. Garcia | R267: =DATEDIF(K267,B267,"m") -> 13 | S267: Monitors | T267: MON-3350 | U267: 322.44 | V267: =Table1[[#This Row],[UnitCost]]*(1+WhatIf!$B$3) -> 338.562 | W267: =U267*AI267 -> 10962.96 | X267: =Table1[[#This Row],[ScenarioRev]]-Table1[[#This Row],[ScenarioUnitCost]] -> 14457.252 | Y267: 395.61 | Z267: =Y267*AI267*(1-AD267) -> 13450.74 | AA267: =Table1[[#This Row],[ScenarioQuanity]]*Table1[[#This Row],[UnitPrice]]*(1-Table1[[#This Row],[ScenarioDiscPct]]) -> 14795.814 | AB267: =Z267-W267 -> 2487.78 | AC267: =Table1[[#This Row],[ScenarioRev]] - Table1[[#This Row],[ScenarioCostOfGoods]] -> 338.562 | AD267: 0 | AE267: =MIN(Table1[[#This Row],[DiscountPct]], WhatIf!$B$2) -> 0 | AF267: =IF(Table1[[#This Row],[DiscountPct]]>0.2, 1, 0) -> 0 | AG267: =IF(Y267<=_xlfn.PERCENTILE.INC($Y:$Y,0.33),"Low", IF(D267<=_xlfn.PERCENTILE.INC($Y:$Y,0.66),"Medium", "High")) -> Low | AH267: =IF(Z267=0, 0, AB267/Z267) -> 0.18495488 | AI267: 34 | AJ267: =Table1[[#This Row],[Quantity]]*(1+WhatIf!$B$4) -> 37.4
A268: ORD-2024-745424 | B268: 45526 | C268: 45539 | D268: =IF(C268<B268, B268+14, C268) -> 45539 | E268: =C268-B268 -> 13 | F268: =D268-B268 -> 13 | G268: =IF(Table1[[#This Row],[CorrectedLeadTimeDays]]<=7, 1, 0) -> 0 | H268: =TEXT(B268, "mmmm") -> August | I268: ="Q"&ROUNDUP(MONTH(B268)/3,0)&"-"&YEAR(B268) -> Q3-2024 | J268: =TEXT(K268, "yyyy-mm") -> 2023-01 | K268: =_xlfn.MINIFS($B:$B,$M:$M,M268) -> 44948 | L268: Europe | M268: Germany | N268: Frankfurt | O268: Non-Profit | P268: Retail | Q268: L. Okafor | R268: =DATEDIF(K268,B268,"m") -> 19 | S268: Printers | T268: PRN-4892 | U268: 90.04 | V268: =Table1[[#This Row],[UnitCost]]*(1+WhatIf!$B$3) -> 94.542 | W268: =U268*AI268 -> 2881.28 | X268: =Table1[[#This Row],[ScenarioRev]]-Table1[[#This Row],[ScenarioUnitCost]] -> 6461.5052 | Y268: 194.62 | Z268: =Y268*AI268*(1-AD268) -> 5960.0429 | AA268: =Table1[[#This Row],[ScenarioQuanity]]*Table1[[#This Row],[UnitPrice]]*(1-Table1[[#This Row],[ScenarioDiscPct]]) -> 6556.0472 | AB268: =Z268-W268 -> 3078.7629 | AC268: =Table1[[#This Row],[ScenarioRev]] - Table1[[#This Row],[ScenarioCostOfGoods]] -> 94.542 | AD268: 0.043 | AE268: =MIN(Table1[[#This Row],[DiscountPct]], WhatIf!$B$2) -> 0.043 | AF268: =IF(Table1[[#This Row],[DiscountPct]]>0.2, 1, 0) -> 0 | AG268: =IF(Y268<=_xlfn.PERCENTILE.INC($Y:$Y,0.33),"Low", IF(D268<=_xlfn.PERCENTILE.INC($Y:$Y,0.66),"Medium", "High")) -> Low | AH268: =IF(Z268=0, 0, AB268/Z268) -> 0.51656724 | AI268: 32 | AJ268: =Table1[[#This Row],[Quantity]]*(1+WhatIf!$B$4) -> 35.2
A269: ORD-2025-415018 | B269: 45679 | C269: 45692 | D269: =IF(C269<B269, B269+14, C269) -> 45692 | E269: =C269-B269 -> 13 | F269: =D269-B269 -> 13 | G269: =IF(Table1[[#This Row],[CorrectedLeadTimeDays]]<=7, 1, 0) -> 0 | H269: =TEXT(B269, "mmmm") -> January | I269: ="Q"&ROUNDUP(MONTH(B269)/3,0)&"-"&YEAR(B269) -> Q1-2025 | J269: =TEXT(K269, "yyyy-mm") -> 2023-03 | K269: =_xlfn.MINIFS($B:$B,$M:$M,M269) -> 44988 | L269: Asia | M269: Japan | N269: Tokyo | O269: Small Business | P269: Distributor | Q269: L. Okafor | R269: =DATEDIF(K269,B269,"m") -> 22 | S269: Printers | T269: PRN-2991 | U269: 122.29 | V269: =Table1[[#This Row],[UnitCost]]*(1+WhatIf!$B$3) -> 128.4045 | W269: =U269*AI269 -> 3424.12 | X269: =Table1[[#This Row],[ScenarioRev]]-Table1[[#This Row],[ScenarioUnitCost]] -> 5740.0011 | Y269: 224.95 | Z269: =Y269*AI269*(1-AD269) -> 5334.9142 | AA269: =Table1[[#This Row],[ScenarioQuanity]]*Table1[[#This Row],[UnitPrice]]*(1-Table1[[#This Row],[ScenarioDiscPct]]) -> 5868.4056 | AB269: =Z269-W269 -> 1910.7942 | AC269: =Table1[[#This Row],[ScenarioRev]] - Table1[[#This Row],[ScenarioCostOfGoods]] -> 128.4045 | AD269: 0.153 | AE269: =MIN(Table1[[#This Row],[DiscountPct]], WhatIf!$B$2) -> 0.153 | AF269: =IF(Table1[[#This Row],[DiscountPct]]>0.2, 1, 0) -> 0 | AG269: =IF(Y269<=_xlfn.PERCENTILE.INC($Y:$Y,0.33),"Low", IF(D269<=_xlfn.PERCENTILE.INC($Y:$Y,0.66),"Medium", "High")) -> Low | AH269: =IF(Z269=0, 0, AB269/Z269) -> 0.35816775 | AI269: 28 | AJ269: =Table1[[#This Row],[Quantity]]*(1+WhatIf!$B$4) -> 30.8
A270: ORD-2024-389336 | B270: 45432 | C270: 45445 | D270: =IF(C270<B270, B270+14, C270) -> 45445 | E270: =C270-B270 -> 13 | F270: =D270-B270 -> 13 | G270: =IF(Table1[[#This Row],[CorrectedLeadTimeDays]]<=7, 1, 0) -> 0 | H270: =TEXT(B270, "mmmm") -> May | I270: ="Q"&ROUNDUP(MONTH(B270)/3,0)&"-"&YEAR(B270) -> Q2-2024 | J270: =TEXT(K270, "yyyy-mm") -> 2023-01 | K270: =_xlfn.MINIFS($B:$B,$M:$M,M270) -> 44928 | L270: Americas | M270: Canada | N270: Vancouver | O270: Enterprise | P270: Marketplace | Q270: K. Singh | R270: =DATEDIF(K270,B270,"m") -> 16 | S270: Components | T270: CMP-5946 | U270: 675.43 | V270: =Table1[[#This Row],[UnitCost]]*(1+WhatIf!$B$3) -> 709.2015 | W270: =U270*AI270 -> 14859.46 | X270: =Table1[[#This Row],[ScenarioRev]]-Table1[[#This Row],[ScenarioUnitCost]] -> 19014.343 | Y270: 996.36 | Z270: =Y270*AI270*(1-AD270) -> 17930.495 | AA270: =Table1[[#This Row],[ScenarioQuanity]]*Table1[[#This Row],[UnitPrice]]*(1-Table1[[#This Row],[ScenarioDiscPct]]) -> 19723.544 | AB270: =Z270-W270 -> 3071.0346 | AC270: =Table1[[#This Row],[ScenarioRev]] - Table1[[#This Row],[ScenarioCostOfGoods]] -> 709.2015 | AD270: 0.182 | AE270: =MIN(Table1[[#This Row],[DiscountPct]], WhatIf!$B$2) -> 0.182 | AF270: =IF(Table1[[#This Row],[DiscountPct]]>0.2, 1, 0) -> 0 | AG270: =IF(Y270<=_xlfn.PERCENTILE.INC($Y:$Y,0.33),"Low", IF(D270<=_xlfn.PERCENTILE.INC($Y:$Y,0.66),"Medium", "High")) -> High | AH270: =IF(Z270=0, 0, AB270/Z270) -> 0.17127439 | AI270: 22 | AJ270: =Table1[[#This Row],[Quantity]]*(1+WhatIf!$B$4) -> 24.2
A271: ORD-2024-907733 | B271: 45360 | C271: 45373 | D271: =IF(C271<B271, B271+14, C271) -> 45373 | E271: =C271-B271 -> 13 | F271: =D271-B271 -> 13 | G271: =IF(Table1[[#This Row],[CorrectedLeadTimeDays]]<=7, 1, 0) -> 0 | H271: =TEXT(B271, "mmmm") -> March | I271: ="Q"&ROUNDUP(MONTH(B271)/3,0)&"-"&YEAR(B271) -> Q1-2024 | J271: =TEXT(K271, "yyyy-mm") -> 2023-01 | K271: =_xlfn.MINIFS($B:$B,$M:$M,M271) -> 44945 | L271: Europe | M271: United Kingdom | N271: Manchester | O271: Consumer | P271: Online | Q271: E. Garcia | R271: =DATEDIF(K271,B271,"m") -> 13 | S271: Laptops | T271: LAP-8633 | U271: 985.45 | V271: =Table1[[#This Row],[UnitCost]]*(1+WhatIf!$B$3) -> 1034.7225 | W271: =U271*AI271 -> 18723.55 | X271: =Table1[[#This Row],[ScenarioRev]]-Table1[[#This Row],[ScenarioUnitCost]] -> 36297.235 | Y271: 1802.44 | Z271: =Y271*AI271*(1-AD271) -> 33938.143 | AA271: =Table1[[#This Row],[ScenarioQuanity]]*Table1[[#This Row],[UnitPrice]]*(1-Table1[[#This Row],[ScenarioDiscPct]]) -> 37331.957 | AB271: =Z271-W271 -> 15214.593 | AC271: =Table1[[#This Row],[ScenarioRev]] - Table1[[#This Row],[ScenarioCostOfGoods]] -> 1034.7225 | AD271: 0.009 | AE271: =MIN(Table1[[#This Row],[DiscountPct]], WhatIf!$B$2) -> 0.009 | AF271: =IF(Table1[[#This Row],[DiscountPct]]>0.2, 1, 0) -> 0 | AG271: =IF(Y271<=_xlfn.PERCENTILE.INC($Y:$Y,0.33),"Low", IF(D271<=_xlfn.PERCENTILE.INC($Y:$Y,0.66),"Medium", "High")) -> High | AH271: =IF(Z271=0, 0, AB271/Z271) -> 0.44830363 | AI271: 19 | AJ271: =Table1[[#This Row],[Quantity]]*(1+WhatIf!$B$4) -> 20.9
A272: ORD-2023-957692 | B272: 45053 | C272: 45066 | D272: =IF(C272<B272, B272+14, C272) -> 45066 | E272: =C272-B272 -> 13 | F272: =D272-B272 -> 13 | G272: =IF(Table1[[#This Row],[CorrectedLeadTimeDays]]<=7, 1, 0) -> 0 | H272: =TEXT(B272, "mmmm") -> May | I272: ="Q"&ROUNDUP(MONTH(B272)/3,0)&"-"&YEAR(B272) -> Q2-2023 | J272: =TEXT(K272, "yyyy-mm") -> 2023-01 | K272: =_xlfn.MINIFS($B:$B,$M:$M,M272) -> 44955 | L272: Asia | M272: India | N272: Mumbai | O272: Enterprise | P272: Retail | Q272: D. Smith | R272: =DATEDIF(K272,B272,"m") -> 3 | S272: Accessories | T272: ACC-9283 | U272: 1443.28 | V272: =Table1[[#This Row],[UnitCost]]*(1+WhatIf!$B$3) -> 1515.444 | W272: =U272*AI272 -> 25979.04 | X272: =Table1[[#This Row],[ScenarioRev]]-Table1[[#This Row],[ScenarioUnitCost]] -> 49579.842 | Y272: 2580.57 | Z272: =Y272*AI272*(1-AD272) -> 46450.26 | AA272: =Table1[[#This Row],[ScenarioQuanity]]*Table1[[#This Row],[UnitPrice]]*(1-Table1[[#This Row],[ScenarioDiscPct]]) -> 51095.286 | AB272: =Z272-W272 -> 20471.22 | AC272: =Table1[[#This Row],[ScenarioRev]] - Table1[[#This Row],[ScenarioCostOfGoods]] -> 1515.444 | AD272: 0 | AE272: =MIN(Table1[[#This Row],[DiscountPct]], WhatIf!$B$2) -> 0 | AF272: =IF(Table1[[#This Row],[DiscountPct]]>0.2, 1, 0) -> 0 | AG272: =IF(Y272<=_xlfn.PERCENTILE.INC($Y:$Y,0.33),"Low", IF(D272<=_xlfn.PERCENTILE.INC($Y:$Y,0.66),"Medium", "High")) -> High | AH272: =IF(Z272=0, 0, AB272/Z272) -> 0.44071271 | AI272: 18 | AJ272: =Table1[[#This Row],[Quantity]]*(1+WhatIf!$B$4) -> 19.8
...

Sheet Brief
A1: Assignment
A2: Excel Mastery Assignment: Sales Operations & Analytics
A4: Overview:
A5: You are an analyst for a multi-regional electronics distributor. The 'Data' sheet contains 632 rows and 15 columns of transactional data with intentional data-quality issues.
A6: Your job is to clean, enrich, analyze, and present insights via a dynamic dashboard.
A8: Part A — Data Cleaning & Preparation:
A9: 1) Create a staging table where you:
A10: • Remove exact duplicate rows (define and document your duplicate criteria).
A11: • Fix data types (dates as Dates, numeric fields as numbers).
A12: • Handle missing values for City, Salesperson, and Channel using reasonable business logic (document your approach).
A13: • Flag and correct suspicious UnitPrice values (e.g., negative prices) and discounts (e.g., > 30%).
A14: • Ensure RequiredDate is not earlier than OrderDate; where it is, impute a corrected RequiredDate (explain your rule).
... A67: 15) Ensure your dashboard responds to slicers without broken references.

Sheet Cleaning Documentation
A1: Data Cleaning
A2: 1. No duplicates found- no data in all rows and columns is exactly identical.
A3: 2. Found negative values in unit price column, I removed - sign.
A4: 3. Fixed datatypes
A5: 4. Corrected negative unit price
A6: 5. Negative delivery times indicated invalid records where RequiredDate occurred before OrderDate. To correct these records, RequiredDate was imputed as OrderDate plus 14 days, based on the average delivery lead time calculated from valid records (14.26 days, rounded to 14 days).
A7: 6. Created Leadtimedays column
A8: 7. Created calculated columns; Gross revenue, costofgoods, grossprofit, marginpct
A9: 8. standardized dimensions, month, quarter from order date
A10: 9. Created priceband column using quantiles/percentiles.

Sheet CountryFirstMonth
A3: Sum of GrossRevenue | B3: Column Labels
A4: Row Labels | B4: 0 | C4: 1 | D4: 2 | E4: 3 | F4: 4 | G4: 5 | H4: 6 | I4: 7 | J4: 8 | K4: 9 | L4: 10 | M4: 11 | N4: 12 | O4: 13 | P4: 14 | Q4: 15 | R4: 16 | S4: 17 | T4: 18 | U4: 19 | V4: 20 | W4: 21 | X4: 22 | Y4: 23 | Z4: 24 | AA4: 25 | AB4: 26 | AC4: 27 | AD4: 28 | AE4: 29 | AF4: 30 | AG4: 31 | AH4: 32 | AI4: Grand Total
A5: 2023-01 | B5: 332830.45 | C5: 337910.78 | D5: 369512.58 | E5: 447670.15 | F5: 216540.34 | G5: 462306.83 | H5: 293599.39 | I5: 288023.35 | J5: 202853.33 | K5: 152839.14 | L5: 198000.54 | M5: 291876.21 | N5: 304758.53 | O5: 306263.26 | P5: 340216.74 | Q5: 325426.47 | R5: 455472.21 | S5: 375344.27 | T5: 307996.63 | U5: 362547.49 | V5: 290176.6 | W5: 352571.84 | X5: 333593.43 | Y5: 302280.03 | Z5: 307423.13 | AA5: 95964.412 | AB5: 328395.95 | AC5: 236619.76 | AD5: 282712.73 | AE5: 463226.64 | AF5: 440339.63 | AG5: 243020.9 | AH5: 25783.065 | AI5: 10074097
A6: Brazil | B6: 26695.838 | C6: 24523.007 | D6: 12248.676 | E6: 27194.152 | F6: 46991.747 | G6: 93430.735 | H6: 37330.003 | I6: 7071.6331 | J6: 16213.633 | K6: 24161.263 | L6: 61471.697 | M6: 8567.3925 | N6: 39239.198 | O6: 110.1492 | P6: 57491.063 | Q6: 9469.7678 | S6: 52596.047 | T6: 41358.42 | U6: 85419.018 | W6: 11939.431 | Y6: 22987.328 | Z6: 70563.592 | AA6: 15158.393 | AB6: 70019.054 | AC6: 67158.245 | AE6: 38096.184 | AF6: 45754.744 | AG6: 24172.045 | AI6: 1037432.5
A7: Canada | B7: 4141.76 | C7: 26150.364 | D7: 17453.344 | E7: 15618.845 | G7: 46226.12 | H7: 29536.716 | I7: 52625.804 | J7: 15530.93 | K7: 27756.432 | M7: 14466.951 | N7: 19139.594 | O7: 9774.3888 | P7: 21931.504 | R7: 17930.495 | S7: 55516.604 | T7: 79082.507 | U7: 7466.3064 | V7: 64160.245 | X7: 60697.471 | Y7: 20713.04 | AA7: 8128.5187 | AC7: 7901.5042 | AD7: 76122.593 | AE7: 5335.5655 | AF7: 141645.57 | AG7: 24972.288 | AH7: 12597.522 | AI7: 882622.98
A8: China | B8: 11406.96 | C8: 24306.483 | E8: 51137.289 | F8: 27108.715 | H8: 55186.877 | I8: 8909.8587 | J8: 72072.389 | K8: 4402.1165 | M8: 23668.56 | N8: 19542.975 | O8: 105288.56 | P8: 14197.064 | R8: 70180.56 | S8: 50774.407 | U8: 8934.8278 | V8: 60223.534 | W8: 20974.101 | X8: 4071.8 | Y8: 80623.678 | Z8: 52780.07 | AB8: 9378.6258 | AD8: 9684.8756 | AE8: 70923.21 | AF8: 34592.244 | AG8: 4420.5962 | AI8: 894790.38
A9: France | B9: 9847.2359 | C9: 39546.775 | D9: 9022.35 | E9: 31788.702 | G9: 18211.877 | H9: 52945.156 | I9: 36549.429 | J9: 14877.464 | K9: 5159.7894 | L9: 22983.346 | M9: 28412.1 | N9: 36467.166 | O9: 13450.74 | P9: 61324.276 | Q9: 24321.57 | R9: 19313.865 | S9: 7399.4832 | T9: 20507.941 | U9: 9189.1635 | W9: 66499.005 | X9: 48264.828 | Y9: 25948.415 | Z9: 20050.102 | AA9: 12040.644 | AB9: 21725.844 | AC9: 11482.481 | AD9: 14385.237 | AE9: 8366.02 | AG9: 68199.913 | AI9: 758280.92
A10: Germany | B10: 99559.246 | C10: 63596.315 | D10: 104633.05 | F10: 23154.287 | G10: 14114.069 | I10: 215.1984 | L10: 64606.506 | M10: 25014.766 | N10: 16328.076 | O10: 33660.622 | P10: 47953.246 | Q10: 33968.99 | R10: 87491.59 | U10: 47066.844 | W10: 12955.825 | X10: 5538.3298 | Y10: 73330.964 | Z10: 30546.068 | AA10: 618.1998 | AB10: 16328.359 | AC10: 5734.3457 | AD10: 56391.305 | AE10: 10441.908 | AF10: 56176.778 | AI10: 929424.89
A11: India | B11: 48804.159 | C11: 6631.6443 | D11: 32506.559 | E11: 249678.14 | F11: 4577.148 | G11: 12462.651 | I11: 49929.55 | J11: 25897.348 | K11: 48296.266 | L11: 35984.637 | M11: 33792.866 | N11: 24305.883 | O11: 12668.507 | Q11: 35554.1 | R11: 31513.423 | S11: 30229.995 | T11: 43785.688 | U11: 20028.787 | V11: 599.532 | W11: 80963.246 | X11: 51589.538 | Y11: 33308.55 | Z11: 7120.6486 | AA11: 24075.09 | AB11: 4856.3573 | AC11: 62421.225 | AD11: 39717.144 | AF11: 11006.648 | AG11: 29627.32 | AI11: 1091932.6
A12: Kenya | B12: 47962.718 | C12: 10561.882 | D12: 67069.607 | E12: 18037.279 | F12: 3799.8031 | G12: 19581.87 | H12: 17735.678 | I12: 1030.7574 | J12: 27249 | K12: 11015.51 | M12: 16061.973 | N12: 66852.129 | O12: 4866.3288 | P12: 8326.6853 | Q12: 29230.059 | R12: 84556.747 | S12: 101032.66 | T12: 27605.926 | U12: 52863.981 | W12: 54242.046 | X12: 119943.7 | Z12: 68469.848 | AB12: 31401.433 | AC12: 4569.8508 | AE12: 17867.219 | AF12: 1654.8966 | AG12: 22570.034 | AI12: 936159.62
A13: Nigeria | B13: 5422.2876 | D13: 32280.325 | E13: 20656.558 | F13: 22882.675 | G13: 116202.88 | H13: 3021.5016 | I13: 24833.098 | J13: 10786.321 | M13: 27158.894 | O13: 28041.025 | P13: 32335.218 | Q13: 51003.081 | R13: 46428.36 | S13: 2719.8567 | U13: 2879.9836 | V13: 55700.646 | W13: 44369.071 | X13: 12967.959 | Z13: 2146.5581 | AA13: 25958.851 | AB13: 48310.143 | AC13: 40139.875 | AD13: 11947.368 | AE13: 146296.57 | AF13: 17847.907 | AG13: 49501.66 | AI13: 881838.68
A14: South Africa | B14: 3116.21 | C14: 86597.081 | D14: 29618.551 | F14: 15187.141 | G14: 21572.591 | H14: 56993.802 | I14: 58520.37 | K14: 434.45248 | L14: 12954.358 | M14: 79406.785 | N14: 54214.972 | O14: 4826.5396 | Q14: 20171.633 | R14: 14032.851 | S14: 39907.476 | U14: 40303.832 | V14: 18061.204 | Z14: 6576.299 | AB14: 5565.3273 | AC14: 1886.9916 | AD14: 31556.188 | AE14: 88311.187 | AF14: 76636.156 | AH14: 13185.543 | AI14: 779637.54
A15: United Kingdom | B15: 27965.367 | C15: 4132.0325 | D15: 64680.119 | E15: 17884.688 | F15: 49706.427 | G15: 48616.566 | H15: 8763.285 | I15: 23038.616 | K15: 31613.31 | M15: 23195.018 | N15: 4229.4321 | O15: 33938.143 | P15: 13218.5 | Q15: 121707.26 | R15: 30151.675 | S15: 35167.745 | T15: 23687.524 | U15: 25249.613 | V15: 91431.438 | W15: 44605.989 | X15: 30519.802 | Y15: 30799.274 | Z15: 47052.461 | AB15: 117895.35 | AD15: 39263.703 | AE15: 77588.78 | AF15: 38415.603 | AG15: 8764.4066 | AI15: 1113282.1
A16: USA | B16: 47908.668 | C16: 51865.197 | E16: 15674.498 | F16: 23132.398 | G16: 71887.464 | H16: 32086.376 | I16: 25299.04 | J16: 20226.246 | M16: 12130.904 | N16: 24439.103 | O16: 59638.251 | P16: 83439.188 | R16: 53872.641 | T16: 71968.627 | U16: 63145.135 | W16: 16023.123 | Y16: 14568.782 | Z16: 2117.4835 | AA16: 9984.7161 | AB16: 2915.4541 | AC16: 35325.243 | AD16: 3644.3213 | AF16: 16609.091 | AG16: 10792.637 | AI16: 768694.59
A17: 2023-03 | B17: 31024.839 | C17: 21196.913 | D17: 9062.3469 | E17: 4603.0824 | F17: 32142.114 | H17: 31130.742 | I17: 14527.748 | J17: 27905.896 | K17: 65358.034 | L17: 26621.873 | M17: 15253.07 | P17: 14287.896 | Q17: 68665.574 | R17: 23449.834 | S17: 82602.551 | T17: 50582.706 | U17: 29808.425 | W17: 18641.222 | X17: 23394.92 | Y17: 266.17822 | Z17: 49494.319 | AA17: 20606.464 | AB17: 63856.507 | AC17: 11984.891 | AD17: 43398.362 | AF17: 74882.386 | AI17: 854748.89
A18: Japan | B18: 31024.839 | C18: 21196.913 | D18: 9062.3469 | E18: 4603.0824 | F18: 32142.114 | H18: 31130.742 | I18: 14527.748 | J18: 27905.896 | K18: 65358.034 | L18: 26621.873 | M18: 15253.07 | P18: 14287.896 | Q18: 68665.574 | R18: 23449.834 | S18: 82602.551 | T18: 50582.706 | U18: 29808.425 | W18: 18641.222 | X18: 23394.92 | Y18: 266.17822 | Z18: 49494.319 | AA18: 20606.464 | AB18: 63856.507 | AC18: 11984.891 | AD18: 43398.362 | AF18: 74882.386 | AI18: 854748.89
A19: Grand Total | B19: 363855.29 | C19: 359107.69 | D19: 378574.93 | E19: 452273.23 | F19: 248682.46 | G19: 462306.83 | H19: 324730.14 | I19: 302551.1 | J19: 230759.23 | K19: 218197.17 | L19: 224622.42 | M19: 307129.28 | N19: 304758.53 | O19: 306263.26 | P19: 354504.64 | Q19: 394092.04 | R19: 478922.04 | S19: 457946.82 | T19: 358579.34 | U19: 392355.92 | V19: 290176.6 | W19: 371213.06 | X19: 356988.35 | Y19: 302546.21 | Z19: 356917.45 | AA19: 116570.88 | AB19: 392252.46 | AC19: 248604.65 | AD19: 326111.1 | AE19: 463226.64 | AF19: 515222.02 | AG19: 243020.9 | AH19: 25783.065 | AI19: 10928846

Sheet ABC Classification
A1: ProductCategory | B1: SKU | C1: Sum of GrossRevenue | D1: CategoryTotal | E1: RunningRev | F1: CumulativePct | G1: ABC
A2: Accessories | B2: ACC-6626 | C2: 79082.507 | D2: =SUMIF($A:$A,A2,$C:$C) -> 1331648.9 | E2: =IF(A2=A1,E1+C2,C2) -> 79082.507 | F2: =E2/D2 -> 0.059386905 | G2: =IF(F2<=0.8,"A",IF(F2<=0.95,"B","C")) -> A
A3: Accessories | B3: ACC-2988 | C3: 53034.364 | D3: =SUMIF($A:$A,A3,$C:$C) -> 1331648.9 | E3: =IF(A3=A2,E2+C3,C3) -> 132116.87 | F3: =E3/D3 -> 0.09921299 | G3: =IF(F3<=0.8,"A",IF(F3<=0.95,"B","C")) -> A
A4: Accessories | B4: ACC-9283 | C4: 46450.26 | D4: =SUMIF($A:$A,A4,$C:$C) -> 1331648.9 | E4: =IF(A4=A3,E3+C4,C4) -> 178567.13 | F4: =E4/D4 -> 0.13409475 | G4: =IF(F4<=0.8,"A",IF(F4<=0.95,"B","C")) -> A
A5: Accessories | B5: ACC-9533 | C5: 43084.872 | D5: =SUMIF($A:$A,A5,$C:$C) -> 1331648.9 | E5: =IF(A5=A4,E4+C5,C5) -> 221652 | F5: =E5/D5 -> 0.16644928 | G5: =IF(F5<=0.8,"A",IF(F5<=0.95,"B","C")) -> A
A6: Accessories | B6: ACC-8098 | C6: 38096.184 | D6: =SUMIF($A:$A,A6,$C:$C) -> 1331648.9 | E6: =IF(A6=A5,E5+C6,C6) -> 259748.19 | F6: =E6/D6 -> 0.19505756 | G6: =IF(F6<=0.8,"A",IF(F6<=0.95,"B","C")) -> A
A7: Accessories | B7: ACC-4490 | C7: 35396.278 | D7: =SUMIF($A:$A,A7,$C:$C) -> 1331648.9 | E7: =IF(A7=A6,E6+C7,C7) -> 295144.47 | F7: =E7/D7 -> 0.22163835 | G7: =IF(F7<=0.8,"A",IF(F7<=0.95,"B","C")) -> A
A8: Accessories | B8: ACC-7838 | C8: 35167.745 | D8: =SUMIF($A:$A,A8,$C:$C) -> 1331648.9 | E8: =IF(A8=A7,E7+C8,C8) -> 330312.21 | F8: =E8/D8 -> 0.24804752 | G8: =IF(F8<=0.8,"A",IF(F8<=0.95,"B","C")) -> A
A9: Accessories | B9: ACC-5177 | C9: 34139.16 | D9: =SUMIF($A:$A,A9,$C:$C) -> 1331648.9 | E9: =IF(A9=A8,E8+C9,C9) -> 364451.37 | F9: =E9/D9 -> 0.27368428 | G9: =IF(F9<=0.8,"A",IF(F9<=0.95,"B","C")) -> A
A10: Accessories | B10: ACC-9162 | C10: 33062.236 | D10: =SUMIF($A:$A,A10,$C:$C) -> 1331648.9 | E10: =IF(A10=A9,E9+C10,C10) -> 397513.61 | F10: =E10/D10 -> 0.29851232 | G10: =IF(F10<=0.8,"A",IF(F10<=0.95,"B","C")) -> A
A11: Accessories | B11: ACC-7078 | C11: 32086.376 | D11: =SUMIF($A:$A,A11,$C:$C) -> 1331648.9 | E11: =IF(A11=A10,E10+C11,C11) -> 429599.98 | F11: =E11/D11 -> 0.32260754 | G11: =IF(F11<=0.8,"A",IF(F11<=0.95,"B","C")) -> A
A12: Accessories | B12: ACC-1375 | C12: 31513.085 | D12: =SUMIF($A:$A,A12,$C:$C) -> 1331648.9 | E12: =IF(A12=A11,E11+C12,C12) -> 461113.07 | F12: =E12/D12 -> 0.34627225 | G12: =IF(F12<=0.8,"A",IF(F12<=0.95,"B","C")) -> A
A13: Accessories | B13: ACC-1659 | C13: 28386.016 | D13: =SUMIF($A:$A,A13,$C:$C) -> 1331648.9 | E13: =IF(A13=A12,E12+C13,C13) -> 489499.08 | F13: =E13/D13 -> 0.36758869 | G13: =IF(F13<=0.8,"A",IF(F13<=0.95,"B","C")) -> A
... A81: Accessories | B81: ACC-2990 | C81: 1547.35 | D81: =SUMIF($A:$A,A81,$C:$C) -> 1331648.9 | E81: =IF(A81=A80,E80+C81,C81) -> 1325481.2 | F81: =E81/D81 -> 0.99536834 | G81: =IF(F81<=0.8,"A",IF(F81<=0.95,"B","C")) -> C
A82: Accessories | B82: ACC-1021 | C82: 1446.9507 | D82: =SUMIF($A:$A,A82,$C:$C) -> 1331648.9 | E82: =C82 -> 1446.9507 | F82: =E82/D82 -> 0.0010865857 | G82: =IF(F82<=0.8,"A",IF(F82<=0.95,"B","C")) -> A
A83: Accessories | B83: ACC-4766 | C83: 1030.7574 | D83: =SUMIF($A:$A,A83,$C:$C) -> 1331648.9 | E83: =IF(A83=A82,E82+C83,C83) -> 2477.7081 | F83: =E83/D83 -> 0.0018606316 | G83: =IF(F83<=0.8,"A",IF(F83<=0.95,"B","C")) -> A
A84: Accessories | B84: ACC-3349 | C84: 1010.3759 | D84: =SUMIF($A:$A,A84,$C:$C) -> 1331648.9 | E84: =IF(A84=A83,E83+C84,C84) -> 3488.084 | F84: =E84/D84 -> 0.0026193721 | G84: =IF(F84<=0.8,"A",IF(F84<=0.95,"B","C")) -> A
A85: Accessories | B85: ACC-5206 | C85: 930.17574 | D85: =SUMIF($A:$A,A85,$C:$C) -> 1331648.9 | E85: =IF(A85=A84,E84+C85,C85) -> 4418.2598 | F85: =E85/D85 -> 0.0033178863 | G85: =IF(F85<=0.8,"A",IF(F85<=0.95,"B","C")) -> A
A86: Accessories | B86: ACC-3551 | C86: 908.037 | D86: =SUMIF($A:$A,A86,$C:$C) -> 1331648.9 | E86: =IF(A86=A85,E85+C86,C86) -> 5326.2968 | F86: =E86/D86 -> 0.0039997755 | G86: =IF(F86<=0.8,"A",IF(F86<=0.95,"B","C")) -> A
A87: Accessories | B87: ACC-9820 | C87: 549.8001 | D87: =SUMIF($A:$A,A87,$C:$C) -> 1331648.9 | E87: =IF(A87=A86,E86+C87,C87) -> 5876.0969 | F87: =E87/D87 -> 0.0044126472 | G87: =IF(F87<=0.8,"A",IF(F87<=0.95,"B","C")) -> A
A88: Accessories | B88: ACC-1770 | C88: 272.986 | D88: =SUMIF($A:$A,A88,$C:$C) -> 1331648.9 | E88: =IF(A88=A87,E87+C88,C88) -> 6149.0829 | F88: =E88/D88 -> 0.0046176457 | G88: =IF(F88<=0.8,"A",IF(F88<=0.95,"B","C")) -> A
A89: Accessories | B89: ACC-6777 | C89: 18.65984 | D89: =SUMIF($A:$A,A89,$C:$C) -> 1331648.9 | E89: =IF(A89=A88,E88+C89,C89) -> 6167.7427 | F89: =E89/D89 -> 0.0046316583 | G89: =IF(F89<=0.8,"A",IF(F89<=0.95,"B","C")) -> A
A90: Components | B90: CMP-8851 | C90: 139277.83 | D90: =SUMIF($A:$A,A90,$C:$C) -> 1545647 | E90: =IF(A90=A89,E89+C90,C90) -> 139277.83 | F90: =E90/D90 -> 0.090109728 | G90: =IF(F90<=0.8,"A",IF(F90<=0.95,"B","C")) -> A
A91: Components | B91: CMP-3938 | C91: 84136.12 | D91: =SUMIF($A:$A,A91,$C:$C) -> 1545647 | E91: =IF(A91=A90,E90+C91,C91) -> 223413.95 | F91: =E91/D91 -> 0.14454397 | G91: =IF(F91<=0.8,"A",IF(F91<=0.95,"B","C")) -> A
A92: Components | B92: CMP-2040 | C92: 65111.386 | D92: =SUMIF($A:$A,A92,$C:$C) -> 1545647 | E92: =IF(A92=A91,E91+C92,C92) -> 288525.34 | F92: =E92/D92 -> 0.18666962 | G92: =IF(F92<=0.8,"A",IF(F92<=0.95,"B","C")) -> A
A93: Components | B93: CMP-3731 | C93: 60928.502 | D93: =SUMIF($A:$A,A93,$C:$C) -> 1545647 | E93: =IF(A93=A92,E92+C93,C93) -> 349453.84 | F93: =E93/D93 -> 0.22608904 | G93: =IF(F93<=0.8,"A",IF(F93<=0.95,"B","C")) -> A
A94: Components | B94: CMP-8127 | C94: 50296.415 | D94: =SUMIF($A:$A,A94,$C:$C) -> 1545647 | E94: =IF(A94=A93,E93+C94,C94) -> 399750.25 | F94: =E94/D94 -> 0.25862972 | G94: =IF(F94<=0.8,"A",IF(F94<=0.95,"B","C")) -> A
... A631: Printers | B631: PRN-6276 | C631: 685.06776 | D631: =SUMIF($A:$A,A631,$C:$C) -> 1616102.7 | E631: =IF(A631=A630,E630+C631,C631) -> 1616102.7 | F631: =E631/D631 -> 1 | G631: =IF(F631<=0.8,"A",IF(F631<=0.95,"B","C")) -> C

Sheet SalespersonProdPivot
A3: Row Labels | B3: Count of OrderID | C3: Sum of HighDiscPct
A4: Africa | B4: 145 | C4: 22
A5: Americas | B5: 157 | C5: 27
A6: Asia | B6: 171 | C6: 24
A7: Europe | B7: 159 | C7: 17
A8: Grand Total | B8: 632 | C8: 90 | E8: =GETPIVOTDATA("Sum of HighDiscPct",$A$3)/GETPIVOTDATA("Count of OrderID",$A$3) -> 0.14240506
A15: Row Labels | B15: Count of OrderID | C15: Sum of HighDiscPct
A16: A. Patel | B16: 46 | C16: 9
A17: B. Chen | B17: 48 | C17: 5
A18: C. Otieno | B18: 37 | C18: 8
A19: D. Smith | B19: 38 | C19: 8
A20: E. Garcia | B20: 34 | C20: 3
A21: F. Müller | B21: 51 | C21: 4
A22: G. Dubois | B22: 30 | C22: 3
A23: H. Kim | B23: 45 | C23: 4
A24: I. Johnson | B24: 38 | C24: 9
A25: J. Njeri | B25: 50 | C25: 6
A26: K. Singh | B26: 44 | C26: 4
A27: L. Okafor | B27: 46 | C27: 8
... A32: Grand Total | B32: 632 | C32: 90

Sheet Salesperson
A3: Row Labels | B3: Sum of GrossRevenue | C3: Count of OrderID | D3: Sum of GrossProfit
A4: F. Müller | B4: 812637.17 | C4: 51 | D4: 251733.01
A5: J. Njeri | B5: 802384.66 | C5: 50 | D5: 273113.11
A6: B. Chen | B6: 893735.66 | C6: 48 | D6: 315969.97
A7: M. Rossi | B7: 966298.99 | C7: 48 | D7: 302657.06
A8: L. Okafor | B8: 853038.52 | C8: 46 | D8: 269716.55
A9: A. Patel | B9: 877159.52 | C9: 46 | D9: 281944.47
A10: H. Kim | B10: 697568.3 | C10: 45 | D10: 137020.81
A11: K. Singh | B11: 883348.13 | C11: 44 | D11: 278762.27
A12: D. Smith | B12: 576820.19 | C12: 38 | D12: 151076.93
A13: I. Johnson | B13: 541165.67 | C13: 38 | D13: 140021.69
A14: O. Wang | B14: 647724.9 | C14: 37 | D14: 185219.44
A15: C. Otieno | B15: 685111.86 | C15: 37 | D15: 225695.02
... A20: Grand Total | B20: 10928846 | C20: 632 | D20: 3401098
A29: Salesperson | B29: Gross Revenue | C29: Orders | D29: Grossprofit | E29: Rev/order | F29: Profit/Order
A30: A. Patel | B30: 877159.52 | C30: 46 | D30: 281944.47 | E30: =B30/C30 -> 19068.685 | F30: =D30/C30 -> 6129.2276
A31: B. Chen | B31: 893735.66 | C31: 48 | D31: 315969.97 | E31: =B31/C31 -> 18619.493 | F31: =D31/C31 -> 6582.7077
A32: C. Otieno | B32: 685111.86 | C32: 37 | D32: 225695.02 | E32: =B32/C32 -> 18516.537 | F32: =D32/C32 -> 6099.8654
A33: D. Smith | B33: 576820.19 | C33: 38 | D33: 151076.93 | E33: =B33/C33 -> 15179.479 | F33: =D33/C33 -> 3975.7087
A34: E. Garcia | B34: 543846.44 | C34: 34 | D34: 204981.34 | E34: =B34/C34 -> 15995.484 | F34: =D34/C34 -> 6028.863
A35: F. Müller | B35: 812637.17 | C35: 51 | D35: 251733.01 | E35: =B35/C35 -> 15934.062 | F35: =D35/C35 -> 4935.9414
A36: G. Dubois | B36: 510653.71 | C36: 30 | D36: 172441.87 | E36: =B36/C36 -> 17021.79 | F36: =D36/C36 -> 5748.0624
A37: H. Kim | B37: 697568.3 | C37: 45 | D37: 137020.81 | E37: =B37/C37 -> 15501.518 | F37: =D37/C37 -> 3044.9069
A38: I. Johnson | B38: 541165.67 | C38: 38 | D38: 140021.69 | E38: =B38/C38 -> 14241.202 | F38: =D38/C38 -> 3684.7814
A39: J. Njeri | B39: 802384.66 | C39: 50 | D39: 273113.11 | E39: =B39/C39 -> 16047.693 | F39: =D39/C39 -> 5462.2622
A40: K. Singh | B40: 883348.13 | C40: 44 | D40: 278762.27 | E40: =B40/C40 -> 20076.094 | F40: =D40/C40 -> 6335.5061
A41: L. Okafor | B41: 853038.52 | C41: 46 | D41: 269716.55 | E41: =B41/C41 -> 18544.316 | F41: =D41/C41 -> 5863.4033
... A45: (blank) | B45: 249026.85 | C45: 8 | D45: 100098 | E45: =B45/C45 -> 31128.356 | F45: =D45/C45 -> 12512.25

Sheet Cannibalization
A1: Sum of GrossRevenue | B1: Column Labels
A2: Row Labels | B2: Direct | C2: Distributor | D2: Marketplace | E2: Online | F2: Retail | G2: (blank) | H2: Grand Total
A3: Africa | B3: 0.1776342 | C3: 0.24017767 | D3: 0.2030569 | E3: 0.16684646 | F3: 0.1996899 | G3: 0.012594885 | H3: 1
A4: Americas | B4: 0.27964209 | C4: 0.21140873 | D4: 0.13626255 | E4: 0.25660677 | F4: 0.11263731 | G4: 0.0034425439 | H4: 1
A5: Asia | B5: 0.22609014 | C5: 0.1792799 | D5: 0.19054974 | E5: 0.14558001 | F5: 0.24393754 | G5: 0.014562662 | H5: 1
A6: Europe | B6: 0.30082759 | C6: 0.11379438 | D6: 0.20338414 | E6: 0.20900009 | F6: 0.16654949 | G6: 0.0064443142 | H6: 1
A7: Grand Total | B7: 0.24690255 | C7: 0.18487541 | D7: 0.18345598 | E7: 0.19420404 | F7: 0.18128356 | G7: 0.0092784644 | H7: 1
A15: Count of OrderID | B15: Column Labels
A16: Row Labels | B16: Direct | C16: Distributor | D16: Marketplace | E16: Online | F16: Retail | G16: (blank) | H16: Grand Total
A17: Africa | B17: 0.19310345 | C17: 0.2137931 | D17: 0.22758621 | E17: 0.17241379 | F17: 0.17241379 | G17: 0.020689655 | H17: 1
A18: Americas | B18: 0.24840764 | C18: 0.23566879 | D18: 0.17197452 | E18: 0.1910828 | F18: 0.14649682 | G18: 0.0063694268 | H18: 1
A19: Asia | B19: 0.21052632 | C19: 0.21052632 | D19: 0.19883041 | E19: 0.15789474 | F19: 0.21052632 | G19: 0.011695906 | H19: 1
A20: Europe | B20: 0.32075472 | C20: 0.11949686 | D20: 0.19496855 | E20: 0.17610063 | F20: 0.17610063 | G20: 0.012578616 | H20: 1
A21: Grand Total | B21: 0.24367089 | C21: 0.19462025 | D21: 0.19778481 | E21: 0.17405063 | F21: 0.17721519 | G21: 0.012658228 | H21: 1
A27: Cannibalization Analysis
A28: The strongest evidence of potential online cannibalization is observed in the Americas region.
A29: Online contributed 25.75% of revenue, significantly above the global average of 19.60%.
A30: Online generated 19.23% of orders, while Retail generated only 14.74% of orders.
A31: Retail contributed just 11.30% of revenue, the lowest channel revenue share in the region.
A32: These findings suggest that customers in the Americas may be shifting purchases from Retail to Online channels.
A33: While the available data cannot conclusively prove customer migration, the combination of strong onlineperformance and weak retail performance provides evidence consistent with potential retail channel cannibalization.
A34: In contrast, Asia shows the opposite pattern. Retail generated the highest revenue share (24.75%) while Online generated only 14.77%, indicating that retail remains the preferred purchasing channel and there is little evidence of online cannibalization.
A35: The channel mix varies considerably across regions. Direct sales are the dominant channel globally, while the Americas exhibit the strongest online presence. The revenue and order distribution patterns in the Americas suggest potential online cannibalization of retail sales, whereas Asia continues to rely heavily on retail channels with limited online substitution.

Sheet MeetingTarget
A3: Row Labels | B3: Sum of OnTimeFlag | C3: Count of OrderID
A4: Brazil | B4: 13 | C4: 62
A5: Canada | B5: 6 | C5: 44
A6: China | B6: 9 | C6: 51
A7: France | B7: 12 | C7: 54
A8: Germany | B8: 11 | C8: 51 | I8: % Meeting Target
A9: India | B9: 11 | C9: 61 | I9: =GETPIVOTDATA("Sum of OnTimeFlag",$A$3)/GETPIVOTDATA("Count of OrderID",$A$3) -> 0.21835443
A10: Japan | B10: 10 | C10: 59
A11: Kenya | B11: 15 | C11: 56
A12: Nigeria | B12: 14 | C12: 44
A13: South Africa | B13: 10 | C13: 45
A14: United Kingdom | B14: 13 | C14: 54
A15: USA | B15: 14 | C15: 51
A16: Grand Total | B16: 138 | C16: 632
A24: Row Labels | B24: Sum of OnTimeFlag | C24: Count of OrderID
A25: Accessories | B25: 28 | C25: 88
A26: Brazil | B26: 3 | C26: 10
A27: Canada | B27: 1 | C27: 6 | E27: =GETPIVOTDATA("Sum of OnTimeFlag",$A$24)/GETPIVOTDATA("Count of OrderID",$A$24) -> 0.21835443
A28: China | B28: 3 | C28: 4
A29: France | B29: 1 | C29: 7
A30: Germany | B30: 4 | C30: 9
A31: India | B31: 2 | C31: 8
A32: Japan | B32: 1 | C32: 5
A33: Kenya | B33: 4 | C33: 10
A34: Nigeria | B34: 4 | C34: 13
A35: South Africa | B35: 2 | C35: 4
A36: United Kingdom | B36: 1 | C36: 8
A37: USA | B37: 2 | C37: 4
A38: Components | B38: 20 | C38: 91
A39: Brazil | B39: 1 | C39: 7
... A116: Grand Total | B116: 138 | C116: 632

Sheet PriceCompliance
A3: Row Labels | B3: Sum of HighDiscPct | C3: Count of OrderID
A4: Africa | B4: 22 | C4: 145
A5: A. Patel | B5: 3 | C5: 16
A6: B. Chen | B6: 0 | C6: 8
A7: C. Otieno | B7: 2 | C7: 8
A8: D. Smith | B8: 2 | C8: 10
A9: E. Garcia | B9: 1 | C9: 5
A10: F. Müller | B10: 0 | C10: 13
A11: G. Dubois | B11: 0 | C11: 3 | F11: Percentage of high discount orders
A12: H. Kim | B12: 1 | C12: 7 | F12: =GETPIVOTDATA("Sum of HighDiscPct",$A$3)/GETPIVOTDATA("Count of OrderID",$A$3) -> 0.14240506
A13: I. Johnson | B13: 2 | C13: 8
A14: J. Njeri | B14: 3 | C14: 12
A15: K. Singh | B15: 0 | C15: 14
A16: L. Okafor | B16: 2 | C16: 10
A17: M. Rossi | B17: 5 | C17: 16
A18: N. Brown | B18: 0 | C18: 4
A19: O. Wang | B19: 0 | C19: 9
A20: (blank) | B20: 1 | C20: 2
A21: Americas | B21: 27 | C21: 157
A22: A. Patel | B22: 5 | C22: 10
A23: B. Chen | B23: 1 | C23: 8
A24: C. Otieno | B24: 2 | C24: 14
... A72: Grand Total | B72: 90 | C72: 632
A84: Row Labels | B84: Count of OrderID | C84: Sum of HighDiscPct | D84: Share
A85: A. Patel | B85: 46 | C85: 9 | D85: =GETPIVOTDATA("Sum of HighDiscPct",$A$84,"Salesperson","A. Patel")/GETPIVOTDATA("Count of OrderID",$A$84,"Salesperson","A. Patel") -> 0.19565217
A86: B. Chen | B86: 48 | C86: 5 | D86: =GETPIVOTDATA("Sum of HighDiscPct",$A$84,"Salesperson","B. Chen")/GETPIVOTDATA("Count of OrderID",$A$84,"Salesperson","B. Chen") -> 0.10416667
A87: C. Otieno | B87: 37 | C87: 8 | D87: =GETPIVOTDATA("Sum of HighDiscPct",$A$84,"Salesperson","C. Otieno")/GETPIVOTDATA("Count of OrderID",$A$84,"Salesperson","C. Otieno") -> 0.21621622
A88: D. Smith | B88: 38 | C88: 8 | D88: =GETPIVOTDATA("Sum of HighDiscPct",$A$84,"Salesperson","D. Smith")/GETPIVOTDATA("Count of OrderID",$A$84,"Salesperson","D. Smith") -> 0.21052632
A89: E. Garcia | B89: 34 | C89: 3 | D89: =GETPIVOTDATA("Sum of HighDiscPct",$A$84,"Salesperson","E. Garcia")/GETPIVOTDATA("Count of OrderID",$A$84,"Salesperson","E. Garcia") -> 0.088235294
A90: F. Müller | B90: 51 | C90: 4 | D90: =GETPIVOTDATA("Sum of HighDiscPct",$A$84,"Salesperson","F. Müller")/GETPIVOTDATA("Count of OrderID",$A$84,"Salesperson","F. Müller") -> 0.078431373
A91: G. Dubois | B91: 30 | C91: 3 | D91: =GETPIVOTDATA("Sum of HighDiscPct",$A$84,"Salesperson","G. Dubois")/GETPIVOTDATA("Count of OrderID",$A$84,"Salesperson","G. Dubois") -> 0.1
A92: H. Kim | B92: 45 | C92: 4 | D92: =GETPIVOTDATA("Sum of HighDiscPct",$A$84,"Salesperson","H. Kim")/GETPIVOTDATA("Count of OrderID",$A$84,"Salesperson","H. Kim") -> 0.088888889
A93: I. Johnson | B93: 38 | C93: 9 | D93: =GETPIVOTDATA("Sum of HighDiscPct",$A$84,"Salesperson","I. Johnson")/GETPIVOTDATA("Count of OrderID",$A$84,"Salesperson","I. Johnson") -> 0.23684211
A94: J. Njeri | B94: 50 | C94: 6 | D94: =GETPIVOTDATA("Sum of HighDiscPct",$A$84,"Salesperson","J. Njeri")/GETPIVOTDATA("Count of OrderID",$A$84,"Salesperson","J. Njeri") -> 0.12
A95: K. Singh | B95: 44 | C95: 4 | D95: =GETPIVOTDATA("Sum of HighDiscPct",$A$84,"Salesperson","K. Singh")/GETPIVOTDATA("Count of OrderID",$A$84,"Salesperson","K. Singh") -> 0.090909091
A96: L. Okafor | B96: 46 | C96: 8 | D96: =GETPIVOTDATA("Sum of HighDiscPct",$A$84,"Salesperson","L. Okafor")/GETPIVOTDATA("Count of OrderID",$A$84,"Salesperson","L. Okafor") -> 0.17391304
A97: M. Rossi | B97: 48 | C97: 8 | D97: =GETPIVOTDATA("Sum of HighDiscPct",$A$84,"Salesperson","M. Rossi")/GETPIVOTDATA("Count of OrderID",$A$84,"Salesperson","M. Rossi") -> 0.16666667
A98: N. Brown | B98: 32 | C98: 5 | D98: =GETPIVOTDATA("Sum of HighDiscPct",$A$84,"Salesperson","N. Brown")/GETPIVOTDATA("Count of OrderID",$A$84,"Salesperson","N. Brown") -> 0.15625
A99: O. Wang | B99: 37 | C99: 4 | D99: =GETPIVOTDATA("Sum of HighDiscPct",$A$84,"Salesperson","O. Wang")/GETPIVOTDATA("Count of OrderID",$A$84,"Salesperson","O. Wang") -> 0.10810811
A100: (blank) | B100: 8 | C100: 2 | D100: =GETPIVOTDATA("Sum of HighDiscPct",$A$84)/GETPIVOTDATA("Count of OrderID",$A$84) -> 0.14240506
A101: Grand Total | B101: 632 | C101: 90

Sheet WhatIf
A1: Parameter | B1: Value
A2: Discount Cap | B2: 0.2
A3: Cost Inflation | B3: 0.05
A4: Quantity Uplift | B4: 0.1

Sheet Scenario_Results
A1: Metric | B1: Baseline | C1: Scenario
A2: Revenue | B2: =SUM(Table1[GrossRevenue]) -> 10928846 | C2: =SUM(Table1[ScenarioRev]) -> 12137817
A3: Profit | B3: =SUM(Table1[GrossProfit]) -> 3401098 | C3: =SUM(Table1[ScenarioProfit]) -> 515464.94
A4: Margin % | B4: =B3/B2 -> 0.31120377 | C4: =C3/C2 -> 0.042467679

Sheet PivotTables
A3: Row Labels | B3: Sum of GrossRevenue
A4: Jan | B4: 701241.31
A5: Feb | B5: 963190.85
A6: Mar | B6: 798978.3
A7: Apr | B7: 947246.58
A8: May | B8: 1262173.9
A9: Jun | B9: 1252974.2
A10: Jul | B10: 1313062.3
A11: Aug | B11: 1089608.8
A12: Sep | B12: 661159.43
A13: Oct | B13: 658776.06
A14: Nov | B14: 543953.69
A15: Dec | B15: 736480.3
A16: Grand Total | B16: 10928846
A25: Row Labels | B25: Sum of GrossProfit
A26: Africa | B26: 837663.85
A27: Americas | B27: 862340.77
A28: Asia | B28: 831257.73
A29: Europe | B29: 869835.66
A30: Grand Total | B30: 3401098
A43: Row Labels | B43: Sum of GrossRevenue
A44: NET-5523 | B44: 79548.756
A45: NET-5987 | B45: 82141.34
A46: LAP-3904 | B46: 82514.712
A47: CMP-3938 | B47: 84136.12
A48: MON-6699 | B48: 85637.74
A49: MON-2266 | B49: 87404.93
A50: MON-6962 | B50: 92715.25
A51: LAP-8910 | B51: 102122.94
A52: NET-2365 | B52: 109244
A53: CMP-8851 | B53: 139277.83
A54: Grand Total | B54: 944743.62
